Workbook

Sheet How to Use
A1: How to use this dashboard
A2: 1. Add a transaction: Open the relevant 'Txn-…' sheet and type a new row anywhere below the existing data — the Excel table extends automatically and the dashboard recalculates.
A3: 2. Delete a transaction: Right-click a row inside the Txn-* table → Delete → Table Rows.
A4: 3. Refresh NAVs: Edit values on the 'NAV Reference' sheet. Current Value, Gain, and % Return all update.
A5: 4. Merge two scheme variants under one MF: Open 'Scheme Map' and edit the Display Scheme for a raw scheme to match another. Also update the 'Display Scheme' column in the affected Txn-* sheets so the dashboard groups them together.
A6: 5. Status column: 'Redeemed' = net units near zero. 'In Profit' / 'In Loss' = current value vs. invested.
A7: 6. Net Invested = Buy amount − Sell amount per scheme. Avg Cost NAV = Net Invested / Net Units.
A8: 7. NAV Source 'MoneyControl' = pulled from the latest MC export. 'Last txn NAV' = no MC entry; we used the most recent transaction NAV (likely stale for fully-redeemed schemes).
A9: 8. To re-build from raw platform/MC files, run python build_dashboard.py followed by python write_dashboard.py.

Sheet Dashboard
A1: Mutual Funds Portfolio Dashboard
A2: ="As of "&TEXT(MAX(NAVAll!F:F),"d mmm yyyy")&" • All KPIs and tables update automatically when transactions are added/deleted." -> As of 28 Jun 2026 • All KPIs and tables update automatically when transactions are added/deleted.
D3: 6857701
A4: Snapshot
A5: Net Invested | C5: Current Value | E5: Net Gain / Loss | G5: Total Return % | J5: Active Schemes | K5: XIRR
A6: =SUM(MFwise[Net Invested]) -> 4409837.1 | C6: =SUM(MFwise[Current Value]) -> 6847516.3 | E6: =SUM(MFwise[Gain/Loss]) -> 2632962.4 | G6: =IFERROR(SUM(MFwise[Gain/Loss])/SUM(MFwise[Net Invested]),0) -> 0.5970657 | J6: =SUMPRODUCT(--(MFwise[Net Units]>0.01)) -> 23 | K6: =$I$87 -> 0.12432699
D7: 1599887
D8: 1669183 | E8: =D8+D7+C6 -> 10116586
A9: MF-Wise Portfolio
A10: Display Scheme | B10: Net Units | C10: Net Invested | D10: Avg Cost NAV | E10: Latest NAV | F10: Current Value | G10: Gain/Loss | H10: P&L Type | I10: % Gain | J10: Status | K10: XIRR
A11: Aditya Birla Sun Life Banking And Financial Services Fund Growth | B11: =SUMIFS(tICICIAshu[Signed Unit],tICICIAshu[Display Scheme],$A11)+SUMIFS(tManiqAshu[Signed Unit],tManiqAshu[Display Scheme],$A11)+SUMIFS(tManiqHars[Signed Unit],tManiqHars[Display Scheme],$A11)+SUMIFS(tZerodhAshu[Signed Unit],tZerodhAshu[Display Scheme],$A11)+SUMIFS(tZerodhHars[Signed Unit],tZerodhHars[Display Scheme],$A11) -> 3475.826 | C11: =IF(B11<0.01,0,SUMIFS(tICICIAshu[Signed Amount],tICICIAshu[Display Scheme],$A11)+SUMIFS(tManiqAshu[Signed Amount],tManiqAshu[Display Scheme],$A11)+SUMIFS(tManiqHars[Signed Amount],tManiqHars[Display Scheme],$A11)+SUMIFS(tZerodhAshu[Signed Amount],tZerodhAshu[Display Scheme],$A11)+SUMIFS(tZerodhHars[Signed Amount],tZerodhHars[Display Scheme],$A11)) -> 159992.32 | D11: =IFERROR(IF(B11<0.01,0,C11/B11),0) -> 46.030014 | E11: =IFERROR(VLOOKUP($A11,tNAV[[Display Scheme]:[Latest NAV]],3,FALSE()),0) -> 63.59 | F11: =B11*E11 -> 221027.78 | G11: =F11-(SUMIFS(tICICIAshu[Signed Amount],tICICIAshu[Display Scheme],$A11)+SUMIFS(tManiqAshu[Signed Amount],tManiqAshu[Display Scheme],$A11)+SUMIFS(tManiqHars[Signed Amount],tManiqHars[Display Scheme],$A11)+SUMIFS(tZerodhAshu[Signed Amount],tZerodhAshu[Display Scheme],$A11)+SUMIFS(tZerodhHars[Signed Amount],tZerodhHars[Display Scheme],$A11)) -> 61035.455 | H11: =IF(B11<0.01,"Realized","Unrealized") -> Unrealized | I11: =IFERROR(G11/ABS(SUMIFS(tICICIAshu[Signed Amount],tICICIAshu[Display Scheme],$A11)+SUMIFS(tManiqAshu[Signed Amount],tManiqAshu[Display Scheme],$A11)+SUMIFS(tManiqHars[Signed Amount],tManiqHars[Display Scheme],$A11)+SUMIFS(tZerodhAshu[Signed Amount],tZerodhAshu[Display Scheme],$A11)+SUMIFS(tZerodhHars[Signed Amount],tZerodhHars[Display Scheme],$A11)),0) -> 0.38148991 | J11: =IF(B11<0.01,"Redeemed",IF(C11<=0,"Active",IF(G11>=0,"In Profit","In Loss"))) -> In Profit | K11: {=IFERROR(IF(F11<=0,"",XIRR(_xlfn.VSTACK(_xlfn._xlws.FILTER(-tAllCF[Signed Amount],tAllCF[Display Scheme]=$A11),F11),_xlfn.VSTACK(_xlfn._xlws.FILTER(tAllCF[Date],tAllCF[Display Scheme]=$A11),TODAY()))),"")} -> 0.13688293
A12: Aditya Birla Sun Life Value Fund Growth | B12: =SUMIFS(tICICIAshu[Signed Unit],tICICIAshu[Display Scheme],$A12)+SUMIFS(tManiqAshu[Signed Unit],tManiqAshu[Display Scheme],$A12)+SUMIFS(tManiqHars[Signed Unit],tManiqHars[Display Scheme],$A12)+SUMIFS(tZerodhAshu[Signed Unit],tZerodhAshu[Display Scheme],$A12)+SUMIFS(tZerodhHars[Signed Unit],tZerodhHars[Display Scheme],$A12) -> 912.432 | C12: =IF(B12<0.01,0,SUMIFS(tICICIAshu[Signed Amount],tICICIAshu[Display Scheme],$A12)+SUMIFS(tManiqAshu[Signed Amount],tManiqAshu[Display Scheme],$A12)+SUMIFS(tManiqHars[Signed Amount],tManiqHars[Display Scheme],$A12)+SUMIFS(tZerodhAshu[Signed Amount],tZerodhAshu[Display Scheme],$A12)+SUMIFS(tZerodhHars[Signed Amount],tZerodhHars[Display Scheme],$A12)) -> 64996.75 | D12: =IFERROR(IF(B12<0.01,0,C12/B12),0) -> 71.234624 | E12: =IFERROR(VLOOKUP($A12,tNAV[[Display Scheme]:[Latest NAV]],3,FALSE()),0) -> 133.0035 | F12: =B12*E12 -> 121356.65 | G12: =F12-(SUMIFS(tICICIAshu[Signed Amount],tICICIAshu[Display Scheme],$A12)+SUMIFS(tManiqAshu[Signed Amount],tManiqAshu[Display Scheme],$A12)+SUMIFS(tManiqHars[Signed Amount],tManiqHars[Display Scheme],$A12)+SUMIFS(tZerodhAshu[Signed Amount],tZerodhAshu[Display Scheme],$A12)+SUMIFS(tZerodhHars[Signed Amount],tZerodhHars[Display Scheme],$A12)) -> 56359.9 | H12: =IF(B12<0.01,"Realized","Unrealized") -> Unrealized | I12: =IFERROR(G12/ABS(SUMIFS(tICICIAshu[Signed Amount],tICICIAshu[Display Scheme],$A12)+SUMIFS(tManiqAshu[Signed Amount],tManiqAshu[Display Scheme],$A12)+SUMIFS(tManiqHars[Signed Amount],tManiqHars[Display Scheme],$A12)+SUMIFS(tZerodhAshu[Signed Amount],tZerodhAshu[Display Scheme],$A12)+SUMIFS(tZerodhHars[Signed Amount],tZerodhHars[Display Scheme],$A12)),0) -> 0.86711873 | J12: =IF(B12<0.01,"Redeemed",IF(C12<=0,"Active",IF(G12>=0,"In Profit","In Loss"))) -> In Profit | K12: {=IFERROR(IF(F12<=0,"",XIRR(_xlfn.VSTACK(_xlfn._xlws.FILTER(-tAllCF[Signed Amount],tAllCF[Display Scheme]=$A12),F12),_xlfn.VSTACK(_xlfn._xlws.FILTER(tAllCF[Date],tAllCF[Display Scheme]=$A12),TODAY()))),"")} -> 0.14765902
A13: Canara Robeco Large And Mid Cap Fund Growth | B13: =SUMIFS(tICICIAshu[Signed Unit],tICICIAshu[Display Scheme],$A13)+SUMIFS(tManiqAshu[Signed Unit],tManiqAshu[Display Scheme],$A13)+SUMIFS(tManiqHars[Signed Unit],tManiqHars[Display Scheme],$A13)+SUMIFS(tZerodhAshu[Signed Unit],tZerodhAshu[Display Scheme],$A13)+SUMIFS(tZerodhHars[Signed Unit],tZerodhHars[Display Scheme],$A13) -> 5337.045 | C13: =IF(B13<0.01,0,SUMIFS(tICICIAshu[Signed Amount],tICICIAshu[Display Scheme],$A13)+SUMIFS(tManiqAshu[Signed Amount],tManiqAshu[Display Scheme],$A13)+SUMIFS(tManiqHars[Signed Amount],tManiqHars[Display Scheme],$A13)+SUMIFS(tZerodhAshu[Signed Amount],tZerodhAshu[Display Scheme],$A13)+SUMIFS(tZerodhHars[Signed Amount],tZerodhHars[Display Scheme],$A13)) -> 792485.68 | D13: =IFERROR(IF(B13<0.01,0,C13/B13),0) -> 148.48773 | E13: =IFERROR(VLOOKUP($A13,tNAV[[Display Scheme]:[Latest NAV]],3,FALSE()),0) -> 250.89 | F13: =B13*E13 -> 1339011.2 | G13: =F13-(SUMIFS(tICICIAshu[Signed Amount],tICICIAshu[Display Scheme],$A13)+SUMIFS(tManiqAshu[Signed Amount],tManiqAshu[Display Scheme],$A13)+SUMIFS(tManiqHars[Signed Amount],tManiqHars[Display Scheme],$A13)+SUMIFS(tZerodhAshu[Signed Amount],tZerodhAshu[Display Scheme],$A13)+SUMIFS(tZerodhHars[Signed Amount],tZerodhHars[Display Scheme],$A13)) -> 546525.54 | H13: =IF(B13<0.01,"Realized","Unrealized") -> Unrealized | I13: =IFERROR(G13/ABS(SUMIFS(tICICIAshu[Signed Amount],tICICIAshu[Display Scheme],$A13)+SUMIFS(tManiqAshu[Signed Amount],tManiqAshu[Display Scheme],$A13)+SUMIFS(tManiqHars[Signed Amount],tManiqHars[Display Scheme],$A13)+SUMIFS(tZerodhAshu[Signed Amount],tZerodhAshu[Display Scheme],$A13)+SUMIFS(tZerodhHars[Signed Amount],tZerodhHars[Display Scheme],$A13)),0) -> 0.68963459 | J13: =IF(B13<0.01,"Redeemed",IF(C13<=0,"Active",IF(G13>=0,"In Profit","In Loss"))) -> In Profit | K13: {=IFERROR(IF(F13<=0,"",XIRR(_xlfn.VSTACK(_xlfn._xlws.FILTER(-tAllCF[Signed Amount],tAllCF[Display Scheme]=$A13),F13),_xlfn.VSTACK(_xlfn._xlws.FILTER(tAllCF[Date],tAllCF[Display Scheme]=$A13),TODAY()))),"")} -> 0.12094044
A14: Canara Robeco Large Cap Fund Regulargrowth | B14: =SUMIFS(tICICIAshu[Signed Unit],tICICIAshu[Display Scheme],$A14)+SUMIFS(tManiqAshu[Signed Unit],tManiqAshu[Display Scheme],$A14)+SUMIFS(tManiqHars[Signed Unit],tManiqHars[Display Scheme],$A14)+SUMIFS(tZerodhAshu[Signed Unit],tZerodhAshu[Display Scheme],$A14)+SUMIFS(tZerodhHars[Signed Unit],tZerodhHars[Display Scheme],$A14) -> 1410.698 | C14: =IF(B14<0.01,0,SUMIFS(tICICIAshu[Signed Amount],tICICIAshu[Display Scheme],$A14)+SUMIFS(tManiqAshu[Signed Amount],tManiqAshu[Display Scheme],$A14)+SUMIFS(tManiqHars[Signed Amount],tManiqHars[Display Scheme],$A14)+SUMIFS(tZerodhAshu[Signed Amount],tZerodhAshu[Display Scheme],$A14)+SUMIFS(tZerodhHars[Signed Amount],tZerodhHars[Display Scheme],$A14)) -> 60000 | D14: =IFERROR(IF(B14<0.01,0,C14/B14),0) -> 42.532137 | E14: =IFERROR(VLOOKUP($A14,tNAV[[Display Scheme]:[Latest NAV]],3,FALSE()),0) -> 61.15 | F14: =B14*E14 -> 86264.183 | G14: =F14-(SUMIFS(tICICIAshu[Signed Amount],tICICIAshu[Display Scheme],$A14)+SUMIFS(tManiqAshu[Signed Amount],tManiqAshu[Display Scheme],$A14)+SUMIFS(tManiqHars[Signed Amount],tManiqHars[Display Scheme],$A14)+SUMIFS(tZerodhAshu[Signed Amount],tZerodhAshu[Display Scheme],$A14)+SUMIFS(tZerodhHars[Signed Amount],tZerodhHars[Display Scheme],$A14)) -> 26264.183 | H14: =IF(B14<0.01,"Realized","Unrealized") -> Unrealized | I14: =IFERROR(G14/ABS(SUMIFS(tICICIAshu[Signed Amount],tICICIAshu[Display Scheme],$A14)+SUMIFS(tManiqAshu[Signed Amount],tManiqAshu[Display Scheme],$A14)+SUMIFS(tManiqHars[Signed Amount],tManiqHars[Display Scheme],$A14)+SUMIFS(tZerodhAshu[Signed Amount],tZerodhAshu[Display Scheme],$A14)+SUMIFS(tZerodhHars[Signed Amount],tZerodhHars[Display Scheme],$A14)),0) -> 0.43773638 | J14: =IF(B14<0.01,"Redeemed",IF(C14<=0,"Active",IF(G14>=0,"In Profit","In Loss"))) -> In Profit | K14: {=IFERROR(IF(F14<=0,"",XIRR(_xlfn.VSTACK(_xlfn._xlws.FILTER(-tAllCF[Signed Amount],tAllCF[Display Scheme]=$A14),F14),_xlfn.VSTACK(_xlfn._xlws.FILTER(tAllCF[Date],tAllCF[Display Scheme]=$A14),TODAY()))),"")} -> 0.079373416
A15: Hdfc Flexicap Fund Direct Growth Option | B15: =SUMIFS(tICICIAshu[Signed Unit],tICICIAshu[Display Scheme],$A15)+SUMIFS(tManiqAshu[Signed Unit],tManiqAshu[Display Scheme],$A15)+SUMIFS(tManiqHars[Signed Unit],tManiqHars[Display Scheme],$A15)+SUMIFS(tZerodhAshu[Signed Unit],tZerodhAshu[Display Scheme],$A15)+SUMIFS(tZerodhHars[Signed Unit],tZerodhHars[Display Scheme],$A15) -> 110.823 | C15: =IF(B15<0.01,0,SUMIFS(tICICIAshu[Signed Amount],tICICIAshu[Display Scheme],$A15)+SUMIFS(tManiqAshu[Signed Amount],tManiqAshu[Display Scheme],$A15)+SUMIFS(tManiqHars[Signed Amount],tManiqHars[Display Scheme],$A15)+SUMIFS(tZerodhAshu[Signed Amount],tZerodhAshu[Display Scheme],$A15)+SUMIFS(tZerodhHars[Signed Amount],tZerodhHars[Display Scheme],$A15)) -> 249989.61 | D15: =IFERROR(IF(B15<0.01,0,C15/B15),0) -> 2255.7557 | E15: =IFERROR(VLOOKUP($A15,tNAV[[Display Scheme]:[Latest NAV]],3,FALSE()),0) -> 2215.087 | F15: =B15*E15 -> 245482.59 | G15: =F15-(SUMIFS(tICICIAshu[Signed Amount],tICICIAshu[Display Scheme],$A15)+SUMIFS(tManiqAshu[Signed Amount],tManiqAshu[Display Scheme],$A15)+SUMIFS(tManiqHars[Signed Amount],tManiqHars[Display Scheme],$A15)+SUMIFS(tZerodhAshu[Signed Amount],tZerodhAshu[Display Scheme],$A15)+SUMIFS(tZerodhHars[Signed Amount],tZerodhHars[Display Scheme],$A15)) -> -4507.0234 | H15: =IF(B15<0.01,"Realized","Unrealized") -> Unrealized | I15: =IFERROR(G15/ABS(SUMIFS(tICICIAshu[Signed Amount],tICICIAshu[Display Scheme],$A15)+SUMIFS(tManiqAshu[Signed Amount],tManiqAshu[Display Scheme],$A15)+SUMIFS(tManiqHars[Signed Amount],tManiqHars[Display Scheme],$A15)+SUMIFS(tZerodhAshu[Signed Amount],tZerodhAshu[Display Scheme],$A15)+SUMIFS(tZerodhHars[Signed Amount],tZerodhHars[Display Scheme],$A15)),0) -> -0.018028843 | J15: =IF(B15<0.01,"Redeemed",IF(C15<=0,"Active",IF(G15>=0,"In Profit","In Loss"))) -> In Loss | K15: {=IFERROR(IF(F15<=0,"",XIRR(_xlfn.VSTACK(_xlfn._xlws.FILTER(-tAllCF[Signed Amount],tAllCF[Display Scheme]=$A15),F15),_xlfn.VSTACK(_xlfn._xlws.FILTER(tAllCF[Date],tAllCF[Display Scheme]=$A15),TODAY()))),"")} -> -0.029031786
A16: Hdfc Gold Etf Fund Of Fund Direct Growth Option | B16: =SUMIFS(tICICIAshu[Signed Unit],tICICIAshu[Display Scheme],$A16)+SUMIFS(tManiqAshu[Signed Unit],tManiqAshu[Display Scheme],$A16)+SUMIFS(tManiqHars[Signed Unit],tManiqHars[Display Scheme],$A16)+SUMIFS(tZerodhAshu[Signed Unit],tZerodhAshu[Display Scheme],$A16)+SUMIFS(tZerodhHars[Signed Unit],tZerodhHars[Display Scheme],$A16) -> 4570.112 | C16: =IF(B16<0.01,0,SUMIFS(tICICIAshu[Signed Amount],tICICIAshu[Display Scheme],$A16)+SUMIFS(tManiqAshu[Signed Amount],tManiqAshu[Display Scheme],$A16)+SUMIFS(tManiqHars[Signed Amount],tManiqHars[Display Scheme],$A16)+SUMIFS(tZerodhAshu[Signed Amount],tZerodhAshu[Display Scheme],$A16)+SUMIFS(tZerodhHars[Signed Amount],tZerodhHars[Display Scheme],$A16)) -> 199990.01 | D16: =IFERROR(IF(B16<0.01,0,C16/B16),0) -> 43.760418 | E16: =IFERROR(VLOOKUP($A16,tNAV[[Display Scheme]:[Latest NAV]],3,FALSE()),0) -> 43.279 | F16: =B16*E16 -> 197789.88 | G16: =F16-(SUMIFS(tICICIAshu[Signed Amount],tICICIAshu[Display Scheme],$A16)+SUMIFS(tManiqAshu[Signed Amount],tManiqAshu[Display Scheme],$A16)+SUMIFS(tManiqHars[Signed Amount],tManiqHars[Display Scheme],$A16)+SUMIFS(tZerodhAshu[Signed Amount],tZerodhAshu[Display Scheme],$A16)+SUMIFS(tZerodhHars[Signed Amount],tZerodhHars[Display Scheme],$A16)) -> -2200.1328 | H16: =IF(B16<0.01,"Realized","Unrealized") -> Unrealized | I16: =IFERROR(G16/ABS(SUMIFS(tICICIAshu[Signed Amount],tICICIAshu[Display Scheme],$A16)+SUMIFS(tManiqAshu[Signed Amount],tManiqAshu[Display Scheme],$A16)+SUMIFS(tManiqHars[Signed Amount],tManiqHars[Display Scheme],$A16)+SUMIFS(tZerodhAshu[Signed Amount],tZerodhAshu[Display Scheme],$A16)+SUMIFS(tZerodhHars[Signed Amount],tZerodhHars[Display Scheme],$A16)),0) -> -0.011001213 | J16: =IF(B16<0.01,"Redeemed",IF(C16<=0,"Active",IF(G16>=0,"In Profit","In Loss"))) -> In Loss | K16: {=IFERROR(IF(F16<=0,"",XIRR(_xlfn.VSTACK(_xlfn._xlws.FILTER(-tAllCF[Signed Amount],tAllCF[Display Scheme]=$A16),F16),_xlfn.VSTACK(_xlfn._xlws.FILTER(tAllCF[Date],tAllCF[Display Scheme]=$A16),TODAY()))),"")} -> -0.021680173
A17: Hdfc Mid Cap Fund - Growth Option | B17: =SUMIFS(tICICIAshu[Signed Unit],tICICIAshu[Display Scheme],$A17)+SUMIFS(tManiqAshu[Signed Unit],tManiqAshu[Display Scheme],$A17)+SUMIFS(tManiqHars[Signed Unit],tManiqHars[Display Scheme],$A17)+SUMIFS(tZerodhAshu[Signed Unit],tZerodhAshu[Display Scheme],$A17)+SUMIFS(tZerodhHars[Signed Unit],tZerodhHars[Display Scheme],$A17) -> 2069.522 | C17: =IF(B17<0.01,0,SUMIFS(tICICIAshu[Signed Amount],tICICIAshu[Display Scheme],$A17)+SUMIFS(tManiqAshu[Signed Amount],tManiqAshu[Display Scheme],$A17)+SUMIFS(tManiqHars[Signed Amount],tManiqHars[Display Scheme],$A17)+SUMIFS(tZerodhAshu[Signed Amount],tZerodhAshu[Display Scheme],$A17)+SUMIFS(tZerodhHars[Signed Amount],tZerodhHars[Display Scheme],$A17)) -> 90000 | D17: =IFERROR(IF(B17<0.01,0,C17/B17),0) -> 43.488303 | E17: =IFERROR(VLOOKUP($A17,tNAV[[Display Scheme]:[Latest NAV]],3,FALSE()),0) -> 204.864 | F17: =B17*E17 -> 423970.56 | G17: =F17-(SUMIFS(tICICIAshu[Signed Amount],tICICIAshu[Display Scheme],$A17)+SUMIFS(tManiqAshu[Signed Amount],tManiqAshu[Display Scheme],$A17)+SUMIFS(tManiqHars[Signed Amount],tManiqHars[Display Scheme],$A17)+SUMIFS(tZerodhAshu[Signed Amount],tZerodhAshu[Display Scheme],$A17)+SUMIFS(tZerodhHars[Signed Amount],tZerodhHars[Display Scheme],$A17)) -> 333970.56 | H17: =IF(B17<0.01,"Realized","Unrealized") -> Unrealized | I17: =IFERROR(G17/ABS(SUMIFS(tICICIAshu[Signed Amount],tICICIAshu[Display Scheme],$A17)+SUMIFS(tManiqAshu[Signed Amount],tManiqAshu[Display Scheme],$A17)+SUMIFS(tManiqHars[Signed Amount],tManiqHars[Display Scheme],$A17)+SUMIFS(tZerodhAshu[Signed Amount],tZerodhAshu[Display Scheme],$A17)+SUMIFS(tZerodhHars[Signed Amount],tZerodhHars[Display Scheme],$A17)),0) -> 3.7107839 | J17: =IF(B17<0.01,"Redeemed",IF(C17<=0,"Active",IF(G17>=0,"In Profit","In Loss"))) -> In Profit | K17: {=IFERROR(IF(F17<=0,"",XIRR(_xlfn.VSTACK(_xlfn._xlws.FILTER(-tAllCF[Signed Amount],tAllCF[Display Scheme]=$A17),F17),_xlfn.VSTACK(_xlfn._xlws.FILTER(tAllCF[Date],tAllCF[Display Scheme]=$A17),TODAY()))),"")} -> 0.16650087
A18: Hdfc Silver Etf Fund Of Fund Direct Growth | B18: =SUMIFS(tICICIAshu[Signed Unit],tICICIAshu[Display Scheme],$A18)+SUMIFS(tManiqAshu[Signed Unit],tManiqAshu[Display Scheme],$A18)+SUMIFS(tManiqHars[Signed Unit],tManiqHars[Display Scheme],$A18)+SUMIFS(tZerodhAshu[Signed Unit],tZerodhAshu[Display Scheme],$A18)+SUMIFS(tZerodhHars[Signed Unit],tZerodhHars[Display Scheme],$A18) -> 2613.312 | C18: =IF(B18<0.01,0,SUMIFS(tICICIAshu[Signed Amount],tICICIAshu[Display Scheme],$A18)+SUMIFS(tManiqAshu[Signed Amount],tManiqAshu[Display Scheme],$A18)+SUMIFS(tManiqHars[Signed Amount],tManiqHars[Display Scheme],$A18)+SUMIFS(tZerodhAshu[Signed Amount],tZerodhAshu[Display Scheme],$A18)+SUMIFS(tZerodhHars[Signed Amount],tZerodhHars[Display Scheme],$A18)) -> 129993.47 | D18: =IFERROR(IF(B18<0.01,0,C18/B18),0) -> 49.742805 | E18: =IFERROR(VLOOKUP($A18,tNAV[[Display Scheme]:[Latest NAV]],3,FALSE()),0) -> 35.6537 | F18: =B18*E18 -> 93174.242 | G18: =F18-(SUMIFS(tICICIAshu[Signed Amount],tICICIAshu[Display Scheme],$A18)+SUMIFS(tManiqAshu[Signed Amount],tManiqAshu[Display Scheme],$A18)+SUMIFS(tManiqHars[Signed Amount],tManiqHars[Display Scheme],$A18)+SUMIFS(tZerodhAshu[Signed Amount],tZerodhAshu[Display Scheme],$A18)+SUMIFS(tZerodhHars[Signed Amount],tZerodhHars[Display Scheme],$A18)) -> -36819.228 | H18: =IF(B18<0.01,"Realized","Unrealized") -> Unrealized | I18: =IFERROR(G18/ABS(SUMIFS(tICICIAshu[Signed Amount],tICICIAshu[Display Scheme],$A18)+SUMIFS(tManiqAshu[Signed Amount],tManiqAshu[Display Scheme],$A18)+SUMIFS(tManiqHars[Signed Amount],tManiqHars[Display Scheme],$A18)+SUMIFS(tZerodhAshu[Signed Amount],tZerodhAshu[Display Scheme],$A18)+SUMIFS(tZerodhHars[Signed Amount],tZerodhHars[Display Scheme],$A18)),0) -> -0.28323906 | J18: =IF(B18<0.01,"Redeemed",IF(C18<=0,"Active",IF(G18>=0,"In Profit","In Loss"))) -> In Loss | K18: {=IFERROR(IF(F18<=0,"",XIRR(_xlfn.VSTACK(_xlfn._xlws.FILTER(-tAllCF[Signed Amount],tAllCF[Display Scheme]=$A18),F18),_xlfn.VSTACK(_xlfn._xlws.FILTER(tAllCF[Date],tAllCF[Display Scheme]=$A18),TODAY()))),"")} -> -0.54444951
A19: Icici Prudential Balanced Advantage Fund Direct Growth | B19: =SUMIFS(tICICIAshu[Signed Unit],tICICIAshu[Display Scheme],$A19)+SUMIFS(tManiqAshu[Signed Unit],tManiqAshu[Display Scheme],$A19)+SUMIFS(tManiqHars[Signed Unit],tManiqHars[Display Scheme],$A19)+SUMIFS(tZerodhAshu[Signed Unit],tZerodhAshu[Display Scheme],$A19)+SUMIFS(tZerodhHars[Signed Unit],tZerodhHars[Display Scheme],$A19) -> 295.359 | C19: =IF(B19<0.01,0,SUMIFS(tICICIAshu[Signed Amount],tICICIAshu[Display Scheme],$A19)+SUMIFS(tManiqAshu[Signed Amount],tManiqAshu[Display Scheme],$A19)+SUMIFS(tManiqHars[Signed Amount],tManiqHars[Display Scheme],$A19)+SUMIFS(tZerodhAshu[Signed Amount],tZerodhAshu[Display Scheme],$A19)+SUMIFS(tZerodhHars[Signed Amount],tZerodhHars[Display Scheme],$A19)) -> 24998.93 | D19: =IFERROR(IF(B19<0.01,0,C19/B19),0) -> 84.639134 | E19: =IFERROR(VLOOKUP($A19,tNAV[[Display Scheme]:[Latest NAV]],3,FALSE()),0) -> 86.86 | F19: =B19*E19 -> 25654.883 | G19: =F19-(SUMIFS(tICICIAshu[Signed Amount],tICICIAshu[Display Scheme],$A19)+SUMIFS(tManiqAshu[Signed Amount],tManiqAshu[Display Scheme],$A19)+SUMIFS(tManiqHars[Signed Amount],tManiqHars[Display Scheme],$A19)+SUMIFS(tZerodhAshu[Signed Amount],tZerodhAshu[Display Scheme],$A19)+SUMIFS(tZerodhHars[Signed Amount],tZerodhHars[Display Scheme],$A19)) -> 655.95274 | H19: =IF(B19<0.01,"Realized","Unrealized") -> Unrealized | I19: =IFERROR(G19/ABS(SUMIFS(tICICIAshu[Signed Amount],tICICIAshu[Display Scheme],$A19)+SUMIFS(tManiqAshu[Signed Amount],tManiqAshu[Display Scheme],$A19)+SUMIFS(tManiqHars[Signed Amount],tManiqHars[Display Scheme],$A19)+SUMIFS(tZerodhAshu[Signed Amount],tZerodhAshu[Display Scheme],$A19)+SUMIFS(tZerodhHars[Signed Amount],tZerodhHars[Display Scheme],$A19)),0) -> 0.026239233 | J19: =IF(B19<0.01,"Redeemed",IF(C19<=0,"Active",IF(G19>=0,"In Profit","In Loss"))) -> In Profit | K19: {=IFERROR(IF(F19<=0,"",XIRR(_xlfn.VSTACK(_xlfn._xlws.FILTER(-tAllCF[Signed Amount],tAllCF[Display Scheme]=$A19),F19),_xlfn.VSTACK(_xlfn._xlws.FILTER(tAllCF[Date],tAllCF[Display Scheme]=$A19),TODAY()))),"")} -> 4.0666502
A20: Icici Prudential Focused Equity Fund Growth | B20: =SUMIFS(tICICIAshu[Signed Unit],tICICIAshu[Display Scheme],$A20)+SUMIFS(tManiqAshu[Signed Unit],tManiqAshu[Display Scheme],$A20)+SUMIFS(tManiqHars[Signed Unit],tManiqHars[Display Scheme],$A20)+SUMIFS(tZerodhAshu[Signed Unit],tZerodhAshu[Display Scheme],$A20)+SUMIFS(tZerodhHars[Signed Unit],tZerodhHars[Display Scheme],$A20) -> 2413.867 | C20: =IF(B20<0.01,0,SUMIFS(tICICIAshu[Signed Amount],tICICIAshu[Display Scheme],$A20)+SUMIFS(tManiqAshu[Signed Amount],tManiqAshu[Display Scheme],$A20)+SUMIFS(tManiqHars[Signed Amount],tManiqHars[Display Scheme],$A20)+SUMIFS(tZerodhAshu[Signed Amount],tZerodhAshu[Display Scheme],$A20)+SUMIFS(tZerodhHars[Signed Amount],tZerodhHars[Display Scheme],$A20)) -> 149992.8 | D20: =IFERROR(IF(B20<0.01,0,C20/B20),0) -> 62.137972 | E20: =IFERROR(VLOOKUP($A20,tNAV[[Display Scheme]:[Latest NAV]],3,FALSE()),0) -> 93.49 | F20: =B20*E20 -> 225672.43 | G20: =F20-(SUMIFS(tICICIAshu[Signed Amount],tICICIAshu[Display Scheme],$A20)+SUMIFS(tManiqAshu[Signed Amount],tManiqAshu[Display Scheme],$A20)+SUMIFS(tManiqHars[Signed Amount],tManiqHars[Display Scheme],$A20)+SUMIFS(tZerodhAshu[Signed Amount],tZerodhAshu[Display Scheme],$A20)+SUMIFS(tZerodhHars[Signed Amount],tZerodhHars[Display Scheme],$A20)) -> 75679.626 | H20: =IF(B20<0.01,"Realized","Unrealized") -> Unrealized | I20: =IFERROR(G20/ABS(SUMIFS(tICICIAshu[Signed Amount],tICICIAshu[Display Scheme],$A20)+SUMIFS(tManiqAshu[Signed Amount],tManiqAshu[Display Scheme],$A20)+SUMIFS(tManiqHars[Signed Amount],tManiqHars[Display Scheme],$A20)+SUMIFS(tZerodhAshu[Signed Amount],tZerodhAshu[Display Scheme],$A20)+SUMIFS(tZerodhHars[Signed Amount],tZerodhHars[Display Scheme],$A20)),0) -> 0.50455506 | J20: =IF(B20<0.01,"Redeemed",IF(C20<=0,"Active",IF(G20>=0,"In Profit","In Loss"))) -> In Profit | K20: {=IFERROR(IF(F20<=0,"",XIRR(_xlfn.VSTACK(_xlfn._xlws.FILTER(-tAllCF[Signed Amount],tAllCF[Display Scheme]=$A20),F20),_xlfn.VSTACK(_xlfn._xlws.FILTER(tAllCF[Date],tAllCF[Display Scheme]=$A20),TODAY()))),"")} -> 0.16801437
A21: Icici Prudential Value Fund Growth | B21: =SUMIFS(tICICIAshu[Signed Unit],tICICIAshu[Display Scheme],$A21)+SUMIFS(tManiqAshu[Signed Unit],tManiqAshu[Display Scheme],$A21)+SUMIFS(tManiqHars[Signed Unit],tManiqHars[Display Scheme],$A21)+SUMIFS(tZerodhAshu[Signed Unit],tZerodhAshu[Display Scheme],$A21)+SUMIFS(tZerodhHars[Signed Unit],tZerodhHars[Display Scheme],$A21) -> 269.373 | C21: =IF(B21<0.01,0,SUMIFS(tICICIAshu[Signed Amount],tICICIAshu[Display Scheme],$A21)+SUMIFS(tManiqAshu[Signed Amount],tManiqAshu[Display Scheme],$A21)+SUMIFS(tManiqHars[Signed Amount],tManiqHars[Display Scheme],$A21)+SUMIFS(tZerodhAshu[Signed Amount],tZerodhAshu[Display Scheme],$A21)+SUMIFS(tZerodhHars[Signed Amount],tZerodhHars[Display Scheme],$A21)) -> 64996.75 | D21: =IFERROR(IF(B21<0.01,0,C21/B21),0) -> 241.28903 | E21: =IFERROR(VLOOKUP($A21,tNAV[[Display Scheme]:[Latest NAV]],3,FALSE()),0) -> 462.41 | F21: =B21*E21 -> 124560.77 | G21: =F21-(SUMIFS(tICICIAshu[Signed Amount],tICICIAshu[Display Scheme],$A21)+SUMIFS(tManiqAshu[Signed Amount],tManiqAshu[Display Scheme],$A21)+SUMIFS(tManiqHars[Signed Amount],tManiqHars[Display Scheme],$A21)+SUMIFS(tZerodhAshu[Signed Amount],tZerodhAshu[Display Scheme],$A21)+SUMIFS(tZerodhHars[Signed Amount],tZerodhHars[Display Scheme],$A21)) -> 59564.019 | H21: =IF(B21<0.01,"Realized","Unrealized") -> Unrealized | I21: =IFERROR(G21/ABS(SUMIFS(tICICIAshu[Signed Amount],tICICIAshu[Display Scheme],$A21)+SUMIFS(tManiqAshu[Signed Amount],tManiqAshu[Display Scheme],$A21)+SUMIFS(tManiqHars[Signed Amount],tManiqHars[Display Scheme],$A21)+SUMIFS(tZerodhAshu[Signed Amount],tZerodhAshu[Display Scheme],$A21)+SUMIFS(tZerodhHars[Signed Amount],tZerodhHars[Display Scheme],$A21)),0) -> 0.91641534 | J21: =IF(B21<0.01,"Redeemed",IF(C21<=0,"Active",IF(G21>=0,"In Profit","In Loss"))) -> In Profit | K21: {=IFERROR(IF(F21<=0,"",XIRR(_xlfn.VSTACK(_xlfn._xlws.FILTER(-tAllCF[Signed Amount],tAllCF[Display Scheme]=$A21),F21),_xlfn.VSTACK(_xlfn._xlws.FILTER(tAllCF[Date],tAllCF[Display Scheme]=$A21),TODAY()))),"")} -> 0.15426112
A22: Invesco India Arbitrage Fund - Direct Plan Growth | B22: =SUMIFS(tICICIAshu[Signed Unit],tICICIAshu[Display Scheme],$A22)+SUMIFS(tManiqAshu[Signed Unit],tManiqAshu[Display Scheme],$A22)+SUMIFS(tManiqHars[Signed Unit],tManiqHars[Display Scheme],$A22)+SUMIFS(tZerodhAshu[Signed Unit],tZerodhAshu[Display Scheme],$A22)+SUMIFS(tZerodhHars[Signed Unit],tZerodhHars[Display Scheme],$A22) -> 2787.776 | C22: =IF(B22<0.01,0,SUMIFS(tICICIAshu[Signed Amount],tICICIAshu[Display Scheme],$A22)+SUMIFS(tManiqAshu[Signed Amount],tManiqAshu[Display Scheme],$A22)+SUMIFS(tManiqHars[Signed Amount],tManiqHars[Display Scheme],$A22)+SUMIFS(tZerodhAshu[Signed Amount],tZerodhAshu[Display Scheme],$A22)+SUMIFS(tZerodhHars[Signed Amount],tZerodhHars[Display Scheme],$A22)) -> 99995.02 | D22: =IFERROR(IF(B22<0.01,0,C22/B22),0) -> 35.869101 | E22: =IFERROR(VLOOKUP($A22,tNAV[[Display Scheme]:[Latest NAV]],3,FALSE()),0) -> 36.7857 | F22: =B22*E22 -> 102550.29 | G22: =F22-(SUMIFS(tICICIAshu[Signed Amount],tICICIAshu[Display Scheme],$A22)+SUMIFS(tManiqAshu[Signed Amount],tManiqAshu[Display Scheme],$A22)+SUMIFS(tManiqHars[Signed Amount],tManiqHars[Display Scheme],$A22)+SUMIFS(tZerodhAshu[Signed Amount],tZerodhAshu[Display Scheme],$A22)+SUMIFS(tZerodhHars[Signed Amount],tZerodhHars[Display Scheme],$A22)) -> 2555.2716 | H22: =IF(B22<0.01,"Realized","Unrealized") -> Unrealized | I22: =IFERROR(G22/ABS(SUMIFS(tICICIAshu[Signed Amount],tICICIAshu[Display Scheme],$A22)+SUMIFS(tManiqAshu[Signed Amount],tManiqAshu[Display Scheme],$A22)+SUMIFS(tManiqHars[Signed Amount],tManiqHars[Display Scheme],$A22)+SUMIFS(tZerodhAshu[Signed Amount],tZerodhAshu[Display Scheme],$A22)+SUMIFS(tZerodhHars[Signed Amount],tZerodhHars[Display Scheme],$A22)),0) -> 0.025553989 | J22: =IF(B22<0.01,"Redeemed",IF(C22<=0,"Active",IF(G22>=0,"In Profit","In Loss"))) -> In Profit | K22: {=IFERROR(IF(F22<=0,"",XIRR(_xlfn.VSTACK(_xlfn._xlws.FILTER(-tAllCF[Signed Amount],tAllCF[Display Scheme]=$A22),F22),_xlfn.VSTACK(_xlfn._xlws.FILTER(tAllCF[Date],tAllCF[Display Scheme]=$A22),TODAY()))),"")} -> 0.064206973
... A41: Uti Focused Fund Growth | B41: =SUMIFS(tICICIAshu[Signed Unit],tICICIAshu[Display Scheme],$A41)+SUMIFS(tManiqAshu[Signed Unit],tManiqAshu[Display Scheme],$A41)+SUMIFS(tManiqHars[Signed Unit],tManiqHars[Display Scheme],$A41)+SUMIFS(tZerodhAshu[Signed Unit],tZerodhAshu[Display Scheme],$A41)+SUMIFS(tZerodhHars[Signed Unit],tZerodhHars[Display Scheme],$A41) -> 0 | C41: =IF(B41<0.01,0,SUMIFS(tICICIAshu[Signed Amount],tICICIAshu[Display Scheme],$A41)+SUMIFS(tManiqAshu[Signed Amount],tManiqAshu[Display Scheme],$A41)+SUMIFS(tManiqHars[Signed Amount],tManiqHars[Display Scheme],$A41)+SUMIFS(tZerodhAshu[Signed Amount],tZerodhAshu[Display Scheme],$A41)+SUMIFS(tZerodhHars[Signed Amount],tZerodhHars[Display Scheme],$A41)) -> 0 | D41: =IFERROR(IF(B41<0.01,0,C41/B41),0) -> 0 | E41: =IFERROR(VLOOKUP($A41,tNAV[[Display Scheme]:[Latest NAV]],3,FALSE()),0) -> 0 | F41: =B41*E41 -> 0 | G41: =F41-(SUMIFS(tICICIAshu[Signed Amount],tICICIAshu[Display Scheme],$A41)+SUMIFS(tManiqAshu[Signed Amount],tManiqAshu[Display Scheme],$A41)+SUMIFS(tManiqHars[Signed Amount],tManiqHars[Display Scheme],$A41)+SUMIFS(tZerodhAshu[Signed Amount],tZerodhAshu[Display Scheme],$A41)+SUMIFS(tZerodhHars[Signed Amount],tZerodhHars[Display Scheme],$A41)) -> 69316.53 | H41: =IF(B41<0.01,"Realized","Unrealized") -> Realized | I41: =IFERROR(G41/ABS(SUMIFS(tICICIAshu[Signed Amount],tICICIAshu[Display Scheme],$A41)+SUMIFS(tManiqAshu[Signed Amount],tManiqAshu[Display Scheme],$A41)+SUMIFS(tManiqHars[Signed Amount],tManiqHars[Display Scheme],$A41)+SUMIFS(tZerodhAshu[Signed Amount],tZerodhAshu[Display Scheme],$A41)+SUMIFS(tZerodhHars[Signed Amount],tZerodhHars[Display Scheme],$A41)),0) -> 1 | J41: =IF(B41<0.01,"Redeemed",IF(C41<=0,"Active",IF(G41>=0,"In Profit","In Loss"))) -> Redeemed | K41: {=IFERROR(IF(F41<=0,"",XIRR(_xlfn.VSTACK(_xlfn._xlws.FILTER(-tAllCF[Signed Amount],tAllCF[Display Scheme]=$A41),F41),_xlfn.VSTACK(_xlfn._xlws.FILTER(tAllCF[Date],tAllCF[Display Scheme]=$A41),TODAY()))),"")}
A42: TOTAL | C42: =SUBTOTAL(9,MFwise[Net Invested]) -> 4409837.1 | F42: =SUBTOTAL(9,MFwise[Current Value]) -> 6847516.3 | G42: =SUBTOTAL(9,MFwise[Gain/Loss]) -> 2437679.2 | I42: =IFERROR(G42/C42,0) -> 0.55278215
A45: Account-Wise Portfolio
A46: Account / Scheme | B46: Transactions | C46: Schemes | D46: Net Invested | E46: Current Value | F46: Gain/Loss | G46: % Gain | H46: P&L Type | I46: XIRR | J46: Status
A47: ICICI Direct - Ashutosh | B47: =COUNTA(tICICIAshu[Date]) -> 102 | C47: {=SUMPRODUCT((COUNTIF(tICICIAshu[Display Scheme],tICICIAshu[Display Scheme])>0)/COUNTIF(tICICIAshu[Display Scheme],tICICIAshu[Display Scheme]))} -> 10 | D47: =SUM(tICICIAshu[Signed Amount]) -> 1016099.4 | E47: {=SUMPRODUCT(SUMIFS(tICICIAshu[Signed Unit],tICICIAshu[Display Scheme],MFwise[Display Scheme])*MFwise[Latest NAV])} -> 2092589.2 | F47: =E47-D47 -> 1076489.7 | G47: =IFERROR(F47/D47,0) -> 1.0594335 | I47: {=IFERROR(IF(E47<=0,"",XIRR(_xlfn.VSTACK(-tICICIAshu[Signed Amount],E47),_xlfn.VSTACK(tICICIAshu[Date],TODAY()))),"")} -> 0.13134245 | J47: =IF(F47>=0,"In Profit","In Loss") -> In Profit
A48: Canara Robeco Large And Mid Cap Fund Growth | B48: =COUNTIFS(tICICIAshu[Display Scheme],"Canara Robeco Large And Mid Cap Fund Growth") -> 1 | D48: =MAX(0,SUMIFS(tICICIAshu[Signed Amount],tICICIAshu[Display Scheme],"Canara Robeco Large And Mid Cap Fund Growth")) -> 500000 | E48: =SUMIFS(tICICIAshu[Signed Unit],tICICIAshu[Display Scheme],"Canara Robeco Large And Mid Cap Fund Growth")*IFERROR(VLOOKUP("Canara Robeco Large And Mid Cap Fund Growth",tNAV[[Display Scheme]:[Latest NAV]],3,FALSE()),0) -> 886618.16 | F48: =E48-D48 -> 386618.16 | G48: =IF(E48<0.01,"",IFERROR(F48/D48,0)) -> 0.77323633 | H48: =IF(E48<0.01,"Realized","Unrealized") -> Unrealized | I48: {=IFERROR(IF(E48<=0,"",XIRR(_xlfn.VSTACK(_xlfn._xlws.FILTER(-tICICIAshu[Signed Amount],tICICIAshu[Display Scheme]="Canara Robeco Large And Mid Cap Fund Growth"),E48),_xlfn.VSTACK(_xlfn._xlws.FILTER(tICICIAshu[Date],tICICIAshu[Display Scheme]="Canara Robeco Large And Mid Cap Fund Growth"),TODAY()))),"")} -> 0.11992086 | J48: =IF(E48<0.01,"Redeemed",IF(F48>=0,"In Profit","In Loss")) -> In Profit
A49: Canara Robeco Large Cap Fund Regulargrowth | B49: =COUNTIFS(tICICIAshu[Display Scheme],"Canara Robeco Large Cap Fund Regulargrowth") -> 1 | D49: =MAX(0,SUMIFS(tICICIAshu[Signed Amount],tICICIAshu[Display Scheme],"Canara Robeco Large Cap Fund Regulargrowth")) -> 60000 | E49: =SUMIFS(tICICIAshu[Signed Unit],tICICIAshu[Display Scheme],"Canara Robeco Large Cap Fund Regulargrowth")*IFERROR(VLOOKUP("Canara Robeco Large Cap Fund Regulargrowth",tNAV[[Display Scheme]:[Latest NAV]],3,FALSE()),0) -> 86264.183 | F49: =E49-D49 -> 26264.183 | G49: =IF(E49<0.01,"",IFERROR(F49/D49,0)) -> 0.43773638 | H49: =IF(E49<0.01,"Realized","Unrealized") -> Unrealized | I49: {=IFERROR(IF(E49<=0,"",XIRR(_xlfn.VSTACK(_xlfn._xlws.FILTER(-tICICIAshu[Signed Amount],tICICIAshu[Display Scheme]="Canara Robeco Large Cap Fund Regulargrowth"),E49),_xlfn.VSTACK(_xlfn._xlws.FILTER(tICICIAshu[Date],tICICIAshu[Display Scheme]="Canara Robeco Large Cap Fund Regulargrowth"),TODAY()))),"")} -> 0.079373416 | J49: =IF(E49<0.01,"Redeemed",IF(F49>=0,"In Profit","In Loss")) -> In Profit
A50: Hdfc Mid Cap Fund - Growth Option | B50: =COUNTIFS(tICICIAshu[Display Scheme],"Hdfc Mid Cap Fund - Growth Option") -> 16 | D50: =MAX(0,SUMIFS(tICICIAshu[Signed Amount],tICICIAshu[Display Scheme],"Hdfc Mid Cap Fund - Growth Option")) -> 90000 | E50: =SUMIFS(tICICIAshu[Signed Unit],tICICIAshu[Display Scheme],"Hdfc Mid Cap Fund - Growth Option")*IFERROR(VLOOKUP("Hdfc Mid Cap Fund - Growth Option",tNAV[[Display Scheme]:[Latest NAV]],3,FALSE()),0) -> 423970.56 | F50: =E50-D50 -> 333970.56 | G50: =IF(E50<0.01,"",IFERROR(F50/D50,0)) -> 3.7107839 | H50: =IF(E50<0.01,"Realized","Unrealized") -> Unrealized | I50: {=IFERROR(IF(E50<=0,"",XIRR(_xlfn.VSTACK(_xlfn._xlws.FILTER(-tICICIAshu[Signed Amount],tICICIAshu[Display Scheme]="Hdfc Mid Cap Fund - Growth Option"),E50),_xlfn.VSTACK(_xlfn._xlws.FILTER(tICICIAshu[Date],tICICIAshu[Display Scheme]="Hdfc Mid Cap Fund - Growth Option"),TODAY()))),"")} -> 0.16650087 | J50: =IF(E50<0.01,"Redeemed",IF(F50>=0,"In Profit","In Loss")) -> In Profit
A51: Kotak Contra Fund - Growth | B51: =COUNTIFS(tICICIAshu[Display Scheme],"Kotak Contra Fund - Growth") -> 63 | D51: =MAX(0,SUMIFS(tICICIAshu[Signed Amount],tICICIAshu[Display Scheme],"Kotak Contra Fund - Growth")) -> 349000 | E51: =SUMIFS(tICICIAshu[Signed Unit],tICICIAshu[Display Scheme],"Kotak Contra Fund - Growth")*IFERROR(VLOOKUP("Kotak Contra Fund - Growth",tNAV[[Display Scheme]:[Latest NAV]],3,FALSE()),0) -> 499887.48 | F51: =E51-D51 -> 150887.48 | G51: =IF(E51<0.01,"",IFERROR(F51/D51,0)) -> 0.43234236 | H51: =IF(E51<0.01,"Realized","Unrealized") -> Unrealized | I51: {=IFERROR(IF(E51<=0,"",XIRR(_xlfn.VSTACK(_xlfn._xlws.FILTER(-tICICIAshu[Signed Amount],tICICIAshu[Display Scheme]="Kotak Contra Fund - Growth"),E51),_xlfn.VSTACK(_xlfn._xlws.FILTER(tICICIAshu[Date],tICICIAshu[Display Scheme]="Kotak Contra Fund - Growth"),TODAY()))),"")} -> 0.14008961 | J51: =IF(E51<0.01,"Redeemed",IF(F51>=0,"In Profit","In Loss")) -> In Profit
A52: Lnt Flexicap Fund Regular Growth Option | B52: =COUNTIFS(tICICIAshu[Display Scheme],"Lnt Flexicap Fund Regular Growth Option") -> 2 | D52: =MAX(0,SUMIFS(tICICIAshu[Signed Amount],tICICIAshu[Display Scheme],"Lnt Flexicap Fund Regular Growth Option")) -> 0 | E52: =SUMIFS(tICICIAshu[Signed Unit],tICICIAshu[Display Scheme],"Lnt Flexicap Fund Regular Growth Option")*IFERROR(VLOOKUP("Lnt Flexicap Fund Regular Growth Option",tNAV[[Display Scheme]:[Latest NAV]],3,FALSE()),0) -> 0 | F52: =E52-D52 -> 0 | G52: =IF(E52<0.01,"",IFERROR(F52/D52,0)) | H52: =IF(E52<0.01,"Realized","Unrealized") -> Realized | I52: {=IFERROR(IF(E52<=0,"",XIRR(_xlfn.VSTACK(_xlfn._xlws.FILTER(-tICICIAshu[Signed Amount],tICICIAshu[Display Scheme]="Lnt Flexicap Fund Regular Growth Option"),E52),_xlfn.VSTACK(_xlfn._xlws.FILTER(tICICIAshu[Date],tICICIAshu[Display Scheme]="Lnt Flexicap Fund Regular Growth Option"),TODAY()))),"")} | J52: =IF(E52<0.01,"Redeemed",IF(F52>=0,"In Profit","In Loss")) -> Redeemed
A53: Nippon India Elss Tax Saver Fund - Growth Plan | B53: =COUNTIFS(tICICIAshu[Display Scheme],"Nippon India Elss Tax Saver Fund - Growth Plan") -> 2 | D53: =MAX(0,SUMIFS(tICICIAshu[Signed Amount],tICICIAshu[Display Scheme],"Nippon India Elss Tax Saver Fund - Growth Plan")) -> 0 | E53: =SUMIFS(tICICIAshu[Signed Unit],tICICIAshu[Display Scheme],"Nippon India Elss Tax Saver Fund - Growth Plan")*IFERROR(VLOOKUP("Nippon India Elss Tax Saver Fund - Growth Plan",tNAV[[Display Scheme]:[Latest NAV]],3,FALSE()),0) -> 0 | F53: =E53-D53 -> 0 | G53: =IF(E53<0.01,"",IFERROR(F53/D53,0)) | H53: =IF(E53<0.01,"Realized","Unrealized") -> Realized | I53: {=IFERROR(IF(E53<=0,"",XIRR(_xlfn.VSTACK(_xlfn._xlws.FILTER(-tICICIAshu[Signed Amount],tICICIAshu[Display Scheme]="Nippon India Elss Tax Saver Fund - Growth Plan"),E53),_xlfn.VSTACK(_xlfn._xlws.FILTER(tICICIAshu[Date],tICICIAshu[Display Scheme]="Nippon India Elss Tax Saver Fund - Growth Plan"),TODAY()))),"")} | J53: =IF(E53<0.01,"Redeemed",IF(F53>=0,"In Profit","In Loss")) -> Redeemed
A54: Nippon India Equity Linked Savings Fund Series - I Growth | B54: =COUNTIFS(tICICIAshu[Display Scheme],"Nippon India Equity Linked Savings Fund Series - I Growth") -> 2 | D54: =MAX(0,SUMIFS(tICICIAshu[Signed Amount],tICICIAshu[Display Scheme],"Nippon India Equity Linked Savings Fund Series - I Growth")) -> 0 | E54: =SUMIFS(tICICIAshu[Signed Unit],tICICIAshu[Display Scheme],"Nippon India Equity Linked Savings Fund Series - I Growth")*IFERROR(VLOOKUP("Nippon India Equity Linked Savings Fund Series - I Growth",tNAV[[Display Scheme]:[Latest NAV]],3,FALSE()),0) -> 0 | F54: =E54-D54 -> 0 | G54: =IF(E54<0.01,"",IFERROR(F54/D54,0)) | H54: =IF(E54<0.01,"Realized","Unrealized") -> Realized | I54: {=IFERROR(IF(E54<=0,"",XIRR(_xlfn.VSTACK(_xlfn._xlws.FILTER(-tICICIAshu[Signed Amount],tICICIAshu[Display Scheme]="Nippon India Equity Linked Savings Fund Series - I Growth"),E54),_xlfn.VSTACK(_xlfn._xlws.FILTER(tICICIAshu[Date],tICICIAshu[Display Scheme]="Nippon India Equity Linked Savings Fund Series - I Growth"),TODAY()))),"")} | J54: =IF(E54<0.01,"Redeemed",IF(F54>=0,"In Profit","In Loss")) -> Redeemed
A55: Sbi Contra Fund Regular Idcw | B55: =COUNTIFS(tICICIAshu[Display Scheme],"Sbi Contra Fund Regular Idcw") -> 2 | D55: =MAX(0,SUMIFS(tICICIAshu[Signed Amount],tICICIAshu[Display Scheme],"Sbi Contra Fund Regular Idcw")) -> 0 | E55: =SUMIFS(tICICIAshu[Signed Unit],tICICIAshu[Display Scheme],"Sbi Contra Fund Regular Idcw")*IFERROR(VLOOKUP("Sbi Contra Fund Regular Idcw",tNAV[[Display Scheme]:[Latest NAV]],3,FALSE()),0) -> 0 | F55: =E55-D55 -> 0 | G55: =IF(E55<0.01,"",IFERROR(F55/D55,0)) | H55: =IF(E55<0.01,"Realized","Unrealized") -> Realized | I55: {=IFERROR(IF(E55<=0,"",XIRR(_xlfn.VSTACK(_xlfn._xlws.FILTER(-tICICIAshu[Signed Amount],tICICIAshu[Display Scheme]="Sbi Contra Fund Regular Idcw"),E55),_xlfn.VSTACK(_xlfn._xlws.FILTER(tICICIAshu[Date],tICICIAshu[Display Scheme]="Sbi Contra Fund Regular Idcw"),TODAY()))),"")} | J55: =IF(E55<0.01,"Redeemed",IF(F55>=0,"In Profit","In Loss")) -> Redeemed
A56: Sbi Elss Tax Saver Fund - Growth | B56: =COUNTIFS(tICICIAshu[Display Scheme],"Sbi Elss Tax Saver Fund - Growth") -> 1 | D56: =MAX(0,SUMIFS(tICICIAshu[Signed Amount],tICICIAshu[Display Scheme],"Sbi Elss Tax Saver Fund - Growth")) -> 5000 | E56: =SUMIFS(tICICIAshu[Signed Unit],tICICIAshu[Display Scheme],"Sbi Elss Tax Saver Fund - Growth")*IFERROR(VLOOKUP("Sbi Elss Tax Saver Fund - Growth",tNAV[[Display Scheme]:[Latest NAV]],3,FALSE()),0) -> 32675.35 | F56: =E56-D56 -> 27675.35 | G56: =IF(E56<0.01,"",IFERROR(F56/D56,0)) -> 5.5350699 | H56: =IF(E56<0.01,"Realized","Unrealized") -> Unrealized | I56: {=IFERROR(IF(E56<=0,"",XIRR(_xlfn.VSTACK(_xlfn._xlws.FILTER(-tICICIAshu[Signed Amount],tICICIAshu[Display Scheme]="Sbi Elss Tax Saver Fund - Growth"),E56),_xlfn.VSTACK(_xlfn._xlws.FILTER(tICICIAshu[Date],tICICIAshu[Display Scheme]="Sbi Elss Tax Saver Fund - Growth"),TODAY()))),"")} -> 0.10653883 | J56: =IF(E56<0.01,"Redeemed",IF(F56>=0,"In Profit","In Loss")) -> In Profit
A57: Sbi Flexicap Fund - Growth | B57: =COUNTIFS(tICICIAshu[Display Scheme],"Sbi Flexicap Fund - Growth") -> 12 | D57: =MAX(0,SUMIFS(tICICIAshu[Signed Amount],tICICIAshu[Display Scheme],"Sbi Flexicap Fund - Growth")) -> 60000 | E57: =SUMIFS(tICICIAshu[Signed Unit],tICICIAshu[Display Scheme],"Sbi Flexicap Fund - Growth")*IFERROR(VLOOKUP("Sbi Flexicap Fund - Growth",tNAV[[Display Scheme]:[Latest NAV]],3,FALSE()),0) -> 163173.44 | F57: =E57-D57 -> 103173.44 | G57: =IF(E57<0.01,"",IFERROR(F57/D57,0)) -> 1.7195574 | H57: =IF(E57<0.01,"Realized","Unrealized") -> Unrealized | I57: {=IFERROR(IF(E57<=0,"",XIRR(_xlfn.VSTACK(_xlfn._xlws.FILTER(-tICICIAshu[Signed Amount],tICICIAshu[Display Scheme]="Sbi Flexicap Fund - Growth"),E57),_xlfn.VSTACK(_xlfn._xlws.FILTER(tICICIAshu[Date],tICICIAshu[Display Scheme]="Sbi Flexicap Fund - Growth"),TODAY()))),"")} -> 0.11332076 | J57: =IF(E57<0.01,"Redeemed",IF(F57>=0,"In Profit","In Loss")) -> In Profit
A58: Maniqmala - Ashutosh | B58: =COUNTA(tManiqAshu[Date]) -> 191 | C58: {=SUMPRODUCT((COUNTIF(tManiqAshu[Display Scheme],tManiqAshu[Display Scheme])>0)/COUNTIF(tManiqAshu[Display Scheme],tManiqAshu[Display Scheme]))} -> 4 | D58: =SUM(tManiqAshu[Signed Amount]) -> 943453.46 | E58: {=SUMPRODUCT(SUMIFS(tManiqAshu[Signed Unit],tManiqAshu[Display Scheme],MFwise[Display Scheme])*MFwise[Latest NAV])} -> 1392549.7 | F58: =E58-D58 -> 449096.19 | G58: =IFERROR(F58/D58,0) -> 0.47601309 | I58: {=IFERROR(IF(E58<=0,"",XIRR(_xlfn.VSTACK(-tManiqAshu[Signed Amount],E58),_xlfn.VSTACK(tManiqAshu[Date],TODAY()))),"")} -> 0.10531805 | J58: =IF(F58>=0,"In Profit","In Loss") -> In Profit
A59: Aditya Birla Sun Life Banking And Financial Services Fund Growth | B59: =COUNTIFS(tManiqAshu[Display Scheme],"Aditya Birla Sun Life Banking And Financial Services Fund Growth") -> 64 | D59: =MAX(0,SUMIFS(tManiqAshu[Signed Amount],tManiqAshu[Display Scheme],"Aditya Birla Sun Life Banking And Financial Services Fund Growth")) -> 159992.32 | E59: =SUMIFS(tManiqAshu[Signed Unit],tManiqAshu[Display Scheme],"Aditya Birla Sun Life Banking And Financial Services Fund Growth")*IFERROR(VLOOKUP("Aditya Birla Sun Life Banking And Financial Services Fund Growth",tNAV[[Display Scheme]:[Latest NAV]],3,FALSE()),0) -> 221027.78 | F59: =E59-D59 -> 61035.455 | G59: =IF(E59<0.01,"",IFERROR(F59/D59,0)) -> 0.38148991 | H59: =IF(E59<0.01,"Realized","Unrealized") -> Unrealized | I59: {=IFERROR(IF(E59<=0,"",XIRR(_xlfn.VSTACK(_xlfn._xlws.FILTER(-tManiqAshu[Signed Amount],tManiqAshu[Display Scheme]="Aditya Birla Sun Life Banking And Financial Services Fund Growth"),E59),_xlfn.VSTACK(_xlfn._xlws.FILTER(tManiqAshu[Date],tManiqAshu[Display Scheme]="Aditya Birla Sun Life Banking And Financial Services Fund Growth"),TODAY()))),"")} -> 0.12381911 | J59: =IF(E59<0.01,"Redeemed",IF(F59>=0,"In Profit","In Loss")) -> In Profit
A60: Mahindra Manulife Flexi Cap Fund Growth | B60: =COUNTIFS(tManiqAshu[Display Scheme],"Mahindra Manulife Flexi Cap Fund Growth") -> 1 | D60: =MAX(0,SUMIFS(tManiqAshu[Signed Amount],tManiqAshu[Display Scheme],"Mahindra Manulife Flexi Cap Fund Growth")) -> 499975 | E60: =SUMIFS(tManiqAshu[Signed Unit],tManiqAshu[Display Scheme],"Mahindra Manulife Flexi Cap Fund Growth")*IFERROR(VLOOKUP("Mahindra Manulife Flexi Cap Fund Growth",tNAV[[Display Scheme]:[Latest NAV]],3,FALSE()),0) -> 779663.3 | F60: =E60-D60 -> 279688.3 | G60: =IF(E60<0.01,"",IFERROR(F60/D60,0)) -> 0.55940457 | H60: =IF(E60<0.01,"Realized","Unrealized") -> Unrealized | I60: {=IFERROR(IF(E60<=0,"",XIRR(_xlfn.VSTACK(_xlfn._xlws.FILTER(-tManiqAshu[Signed Amount],tManiqAshu[Display Scheme]="Mahindra Manulife Flexi Cap Fund Growth"),E60),_xlfn.VSTACK(_xlfn._xlws.FILTER(tManiqAshu[Date],tManiqAshu[Display Scheme]="Mahindra Manulife Flexi Cap Fund Growth"),TODAY()))),"")} -> 0.096809071 | J60: =IF(E60<0.01,"Redeemed",IF(F60>=0,"In Profit","In Loss")) -> In Profit
A61: Mahindra Manulife Focused Fund Growth | B61: =COUNTIFS(tManiqAshu[Display Scheme],"Mahindra Manulife Focused Fund Growth") -> 63 | D61: =MAX(0,SUMIFS(tManiqAshu[Signed Amount],tManiqAshu[Display Scheme],"Mahindra Manulife Focused Fund Growth")) -> 125993.7 | E61: =SUMIFS(tManiqAshu[Signed Unit],tManiqAshu[Display Scheme],"Mahindra Manulife Focused Fund Growth")*IFERROR(VLOOKUP("Mahindra Manulife Focused Fund Growth",tNAV[[Display Scheme]:[Latest NAV]],3,FALSE()),0) -> 178273.67 | F61: =E61-D61 -> 52279.97 | G61: =IF(E61<0.01,"",IFERROR(F61/D61,0)) -> 0.41494115 | H61: =IF(E61<0.01,"Realized","Unrealized") -> Unrealized | I61: {=IFERROR(IF(E61<=0,"",XIRR(_xlfn.VSTACK(_xlfn._xlws.FILTER(-tManiqAshu[Signed Amount],tManiqAshu[Display Scheme]="Mahindra Manulife Focused Fund Growth"),E61),_xlfn.VSTACK(_xlfn._xlws.FILTER(tManiqAshu[Date],tManiqAshu[Display Scheme]="Mahindra Manulife Focused Fund Growth"),TODAY()))),"")} -> 0.13388144 | J61: =IF(E61<0.01,"Redeemed",IF(F61>=0,"In Profit","In Loss")) -> In Profit
A62: Mirae Asset Large And Mid Cap Fund Growth | B62: =COUNTIFS(tManiqAshu[Display Scheme],"Mirae Asset Large And Mid Cap Fund Growth") -> 63 | D62: =MAX(0,SUMIFS(tManiqAshu[Signed Amount],tManiqAshu[Display Scheme],"Mirae Asset Large And Mid Cap Fund Growth")) -> 157492.44 | E62: =SUMIFS(tManiqAshu[Signed Unit],tManiqAshu[Display Scheme],"Mirae Asset Large And Mid Cap Fund Growth")*IFERROR(VLOOKUP("Mirae Asset Large And Mid Cap Fund Growth",tNAV[[Display Scheme]:[Latest NAV]],3,FALSE()),0) -> 213584.91 | F62: =E62-D62 -> 56092.47 | G62: =IF(E62<0.01,"",IFERROR(F62/D62,0)) -> 0.35615976 | H62: =IF(E62<0.01,"Realized","Unrealized") -> Unrealized | I62: {=IFERROR(IF(E62<=0,"",XIRR(_xlfn.VSTACK(_xlfn._xlws.FILTER(-tManiqAshu[Signed Amount],tManiqAshu[Display Scheme]="Mirae Asset Large And Mid Cap Fund Growth"),E62),_xlfn.VSTACK(_xlfn._xlws.FILTER(tManiqAshu[Date],tManiqAshu[Display Scheme]="Mirae Asset Large And Mid Cap Fund Growth"),TODAY()))),"")} -> 0.11738086 | J62: =IF(E62<0.01,"Redeemed",IF(F62>=0,"In Profit","In Loss")) -> In Profit
A63: Maniqmala - Harsha | B63: =COUNTA(tManiqHars[Date]) -> 313 | C63: {=SUMPRODUCT((COUNTIF(tManiqHars[Display Scheme],tManiqHars[Display Scheme])>0)/COUNTIF(tManiqHars[Display Scheme],tManiqHars[Display Scheme]))} -> 13 | D63: =SUM(tManiqHars[Signed Amount]) -> 1300046.2 | E63: {=SUMPRODUCT(SUMIFS(tManiqHars[Signed Unit],tManiqHars[Display Scheme],MFwise[Display Scheme])*MFwise[Latest NAV])} -> 2403992.1 | F63: =E63-D63 -> 1103945.9 | G63: =IFERROR(F63/D63,0) -> 0.84915897 | I63: {=IFERROR(IF(E63<=0,"",XIRR(_xlfn.VSTACK(-tManiqHars[Signed Amount],E63),_xlfn.VSTACK(tManiqHars[Date],TODAY()))),"")} -> 0.11884239 | J63: =IF(F63>=0,"In Profit","In Loss") -> In Profit
A64: Aditya Birla Sun Life Value Fund Growth | B64: =COUNTIFS(tManiqHars[Display Scheme],"Aditya Birla Sun Life Value Fund Growth") -> 13 | D64: =MAX(0,SUMIFS(tManiqHars[Signed Amount],tManiqHars[Display Scheme],"Aditya Birla Sun Life Value Fund Growth")) -> 64996.75 | E64: =SUMIFS(tManiqHars[Signed Unit],tManiqHars[Display Scheme],"Aditya Birla Sun Life Value Fund Growth")*IFERROR(VLOOKUP("Aditya Birla Sun Life Value Fund Growth",tNAV[[Display Scheme]:[Latest NAV]],3,FALSE()),0) -> 121356.65 | F64: =E64-D64 -> 56359.9 | G64: =IF(E64<0.01,"",IFERROR(F64/D64,0)) -> 0.86711873 | H64: =IF(E64<0.01,"Realized","Unrealized") -> Unrealized | I64: {=IFERROR(IF(E64<=0,"",XIRR(_xlfn.VSTACK(_xlfn._xlws.FILTER(-tManiqHars[Signed Amount],tManiqHars[Display Scheme]="Aditya Birla Sun Life Value Fund Growth"),E64),_xlfn.VSTACK(_xlfn._xlws.FILTER(tManiqHars[Date],tManiqHars[Display Scheme]="Aditya Birla Sun Life Value Fund Growth"),TODAY()))),"")} -> 0.14765902 | J64: =IF(E64<0.01,"Redeemed",IF(F64>=0,"In Profit","In Loss")) -> In Profit
A65: Canara Robeco Large And Mid Cap Fund Growth | B65: =COUNTIFS(tManiqHars[Display Scheme],"Canara Robeco Large And Mid Cap Fund Growth") -> 75 | D65: =MAX(0,SUMIFS(tManiqHars[Signed Amount],tManiqHars[Display Scheme],"Canara Robeco Large And Mid Cap Fund Growth")) -> 292485.68 | E65: =SUMIFS(tManiqHars[Signed Unit],tManiqHars[Display Scheme],"Canara Robeco Large And Mid Cap Fund Growth")*IFERROR(VLOOKUP("Canara Robeco Large And Mid Cap Fund Growth",tNAV[[Display Scheme]:[Latest NAV]],3,FALSE()),0) -> 452393.06 | F65: =E65-D65 -> 159907.38 | G65: =IF(E65<0.01,"",IFERROR(F65/D65,0)) -> 0.54671865 | H65: =IF(E65<0.01,"Realized","Unrealized") -> Unrealized | I65: {=IFERROR(IF(E65<=0,"",XIRR(_xlfn.VSTACK(_xlfn._xlws.FILTER(-tManiqHars[Signed Amount],tManiqHars[Display Scheme]="Canara Robeco Large And Mid Cap Fund Growth"),E65),_xlfn.VSTACK(_xlfn._xlws.FILTER(tManiqHars[Date],tManiqHars[Display Scheme]="Canara Robeco Large And Mid Cap Fund Growth"),TODAY()))),"")} -> 0.11879911 | J65: =IF(E65<0.01,"Redeemed",IF(F65>=0,"In Profit","In Loss")) -> In Profit
A66: Icici Prudential Focused Equity Fund Growth | B66: =COUNTIFS(tManiqHars[Display Scheme],"Icici Prudential Focused Equity Fund Growth") -> 60 | D66: =MAX(0,SUMIFS(tManiqHars[Signed Amount],tManiqHars[Display Scheme],"Icici Prudential Focused Equity Fund Growth")) -> 149992.8 | E66: =SUMIFS(tManiqHars[Signed Unit],tManiqHars[Display Scheme],"Icici Prudential Focused Equity Fund Growth")*IFERROR(VLOOKUP("Icici Prudential Focused Equity Fund Growth",tNAV[[Display Scheme]:[Latest NAV]],3,FALSE()),0) -> 225672.43 | F66: =E66-D66 -> 75679.626 | G66: =IF(E66<0.01,"",IFERROR(F66/D66,0)) -> 0.50455506 | H66: =IF(E66<0.01,"Realized","Unrealized") -> Unrealized | I66: {=IFERROR(IF(E66<=0,"",XIRR(_xlfn.VSTACK(_xlfn._xlws.FILTER(-tManiqHars[Signed Amount],tManiqHars[Display Scheme]="Icici Prudential Focused Equity Fund Growth"),E66),_xlfn.VSTACK(_xlfn._xlws.FILTER(tManiqHars[Date],tManiqHars[Display Scheme]="Icici Prudential Focused Equity Fund Growth"),TODAY()))),"")} -> 0.15521806 | J66: =IF(E66<0.01,"Redeemed",IF(F66>=0,"In Profit","In Loss")) -> In Profit
A67: Icici Prudential Value Fund Growth | B67: =COUNTIFS(tManiqHars[Display Scheme],"Icici Prudential Value Fund Growth") -> 13 | D67: =MAX(0,SUMIFS(tManiqHars[Signed Amount],tManiqHars[Display Scheme],"Icici Prudential Value Fund Growth")) -> 64996.75 | E67: =SUMIFS(tManiqHars[Signed Unit],tManiqHars[Display Scheme],"Icici Prudential Value Fund Growth")*IFERROR(VLOOKUP("Icici Prudential Value Fund Growth",tNAV[[Display Scheme]:[Latest NAV]],3,FALSE()),0) -> 124560.77 | F67: =E67-D67 -> 59564.019 | G67: =IF(E67<0.01,"",IFERROR(F67/D67,0)) -> 0.91641534 | H67: =IF(E67<0.01,"Realized","Unrealized") -> Unrealized | I67: {=IFERROR(IF(E67<=0,"",XIRR(_xlfn.VSTACK(_xlfn._xlws.FILTER(-tManiqHars[Signed Amount],tManiqHars[Display Scheme]="Icici Prudential Value Fund Growth"),E67),_xlfn.VSTACK(_xlfn._xlws.FILTER(tManiqHars[Date],tManiqHars[Display Scheme]="Icici Prudential Value Fund Growth"),TODAY()))),"")} -> 0.15426112 | J67: =IF(E67<0.01,"Redeemed",IF(F67>=0,"In Profit","In Loss")) -> In Profit
A68: Invesco India Multicap Fund Growth | B68: =COUNTIFS(tManiqHars[Display Scheme],"Invesco India Multicap Fund Growth") -> 2 | D68: =MAX(0,SUMIFS(tManiqHars[Signed Amount],tManiqHars[Display Scheme],"Invesco India Multicap Fund Growth")) -> 0 | E68: =SUMIFS(tManiqHars[Signed Unit],tManiqHars[Display Scheme],"Invesco India Multicap Fund Growth")*IFERROR(VLOOKUP("Invesco India Multicap Fund Growth",tNAV[[Display Scheme]:[Latest NAV]],3,FALSE()),0) -> 0 | F68: =E68-D68 -> 0 | G68: =IF(E68<0.01,"",IFERROR(F68/D68,0)) | H68: =IF(E68<0.01,"Realized","Unrealized") -> Realized | I68: {=IFERROR(IF(E68<=0,"",XIRR(_xlfn.VSTACK(_xlfn._xlws.FILTER(-tManiqHars[Signed Amount],tManiqHars[Display Scheme]="Invesco India Multicap Fund Growth"),E68),_xlfn.VSTACK(_xlfn._xlws.FILTER(tManiqHars[Date],tManiqHars[Display Scheme]="Invesco India Multicap Fund Growth"),TODAY()))),"")} | J68: =IF(E68<0.01,"Redeemed",IF(F68>=0,"In Profit","In Loss")) -> Redeemed
A69: Kotak Multicap Fund Growth | B69: =COUNTIFS(tManiqHars[Display Scheme],"Kotak Multicap Fund Growth") -> 1 | D69: =MAX(0,SUMIFS(tManiqHars[Signed Amount],tManiqHars[Display Scheme],"Kotak Multicap Fund Growth")) -> 249987.5 | E69: =SUMIFS(tManiqHars[Signed Unit],tManiqHars[Display Scheme],"Kotak Multicap Fund Growth")*IFERROR(VLOOKUP("Kotak Multicap Fund Growth",tNAV[[Display Scheme]:[Latest NAV]],3,FALSE()),0) -> 499750.01 | F69: =E69-D69 -> 249762.51 | G69: =IF(E69<0.01,"",IFERROR(F69/D69,0)) -> 0.9991 | H69: =IF(E69<0.01,"Realized","Unrealized") -> Unrealized | I69: {=IFERROR(IF(E69<=0,"",XIRR(_xlfn.VSTACK(_xlfn._xlws.FILTER(-tManiqHars[Signed Amount],tManiqHars[Display Scheme]="Kotak Multicap Fund Growth"),E69),_xlfn.VSTACK(_xlfn._xlws.FILTER(tManiqHars[Date],tManiqHars[Display Scheme]="Kotak Multicap Fund Growth"),TODAY()))),"")} -> 0.15717109 | J69: =IF(E69<0.01,"Redeemed",IF(F69>=0,"In Profit","In Loss")) -> In Profit
A70: Mahindra Manulife Large And Mid Cap Fund Growth | B70: =COUNTIFS(tManiqHars[Display Scheme],"Mahindra Manulife Large And Mid Cap Fund Growth") -> 1 | D70: =MAX(0,SUMIFS(tManiqHars[Signed Amount],tManiqHars[Display Scheme],"Mahindra Manulife Large And Mid Cap Fund Growth")) -> 249987.5 | E70: =SUMIFS(tManiqHars[Signed Unit],tManiqHars[Display Scheme],"Mahindra Manulife Large And Mid Cap Fund Growth")*IFERROR(VLOOKUP("Mahindra Manulife Large And Mid Cap Fund Growth",tNAV[[Display Scheme]:[Latest NAV]],3,FALSE()),0) -> 413045.58 | F70: =E70-D70 -> 163058.08 | G70: =IF(E70<0.01,"",IFERROR(F70/D70,0)) -> 0.65226495 | H70: =IF(E70<0.01,"Realized","Unrealized") -> Unrealized | I70: {=IFERROR(IF(E70<=0,"",XIRR(_xlfn.VSTACK(_xlfn._xlws.FILTER(-tManiqHars[Signed Amount],tManiqHars[Display Scheme]="Mahindra Manulife Large And Mid Cap Fund Growth"),E70),_xlfn.VSTACK(_xlfn._xlws.FILTER(tManiqHars[Date],tManiqHars[Display Scheme]="Mahindra Manulife Large And Mid Cap Fund Growth"),TODAY()))),"")} -> 0.11108325 | J70: =IF(E70<0.01,"Redeemed",IF(F70>=0,"In Profit","In Loss")) -> In Profit
A71: Mahindra Manulife Mid Cap Fund Growth | B71: =COUNTIFS(tManiqHars[Display Scheme],"Mahindra Manulife Mid Cap Fund Growth") -> 13 | D71: =MAX(0,SUMIFS(tManiqHars[Signed Amount],tManiqHars[Display Scheme],"Mahindra Manulife Mid Cap Fund Growth")) -> 64996.75 | E71: =SUMIFS(tManiqHars[Signed Unit],tManiqHars[Display Scheme],"Mahindra Manulife Mid Cap Fund Growth")*IFERROR(VLOOKUP("Mahindra Manulife Mid Cap Fund Growth",tNAV[[Display Scheme]:[Latest NAV]],3,FALSE()),0) -> 139249.57 | F71: =E71-D71 -> 74252.821 | G71: =IF(E71<0.01,"",IFERROR(F71/D71,0)) -> 1.1424082 | H71: =IF(E71<0.01,"Realized","Unrealized") -> Unrealized | I71: {=IFERROR(IF(E71<=0,"",XIRR(_xlfn.VSTACK(_xlfn._xlws.FILTER(-tManiqHars[Signed Amount],tManiqHars[Display Scheme]="Mahindra Manulife Mid Cap Fund Growth"),E71),_xlfn.VSTACK(_xlfn._xlws.FILTER(tManiqHars[Date],tManiqHars[Display Scheme]="Mahindra Manulife Mid Cap Fund Growth"),TODAY()))),"")} -> 0.18292106 | J71: =IF(E71<0.01,"Redeemed",IF(F71>=0,"In Profit","In Loss")) -> In Profit
A72: Mirae Asset Large And Mid Cap Fund Growth | B72: =COUNTIFS(tManiqHars[Display Scheme],"Mirae Asset Large And Mid Cap Fund Growth") -> 62 | D72: =MAX(0,SUMIFS(tManiqHars[Signed Amount],tManiqHars[Display Scheme],"Mirae Asset Large And Mid Cap Fund Growth")) -> 154992.56 | E72: =SUMIFS(tManiqHars[Signed Unit],tManiqHars[Display Scheme],"Mirae Asset Large And Mid Cap Fund Growth")*IFERROR(VLOOKUP("Mirae Asset Large And Mid Cap Fund Growth",tNAV[[Display Scheme]:[Latest NAV]],3,FALSE()),0) -> 212497.2 | F72: =E72-D72 -> 57504.642 | G72: =IF(E72<0.01,"",IFERROR(F72/D72,0)) -> 0.3710155 | H72: =IF(E72<0.01,"Realized","Unrealized") -> Unrealized | I72: {=IFERROR(IF(E72<=0,"",XIRR(_xlfn.VSTACK(_xlfn._xlws.FILTER(-tManiqHars[Signed Amount],tManiqHars[Display Scheme]="Mirae Asset Large And Mid Cap Fund Growth"),E72),_xlfn.VSTACK(_xlfn._xlws.FILTER(tManiqHars[Date],tManiqHars[Display Scheme]="Mirae Asset Large And Mid Cap Fund Growth"),TODAY()))),"")} -> 0.11792247 | J72: =IF(E72<0.01,"Redeemed",IF(F72>=0,"In Profit","In Loss")) -> In Profit
A73: Principal Emerging Bluechip Fund Growth | B73: =COUNTIFS(tManiqHars[Display Scheme],"Principal Emerging Bluechip Fund Growth") -> 4 | D73: =MAX(0,SUMIFS(tManiqHars[Signed Amount],tManiqHars[Display Scheme],"Principal Emerging Bluechip Fund Growth")) -> 0 | E73: =SUMIFS(tManiqHars[Signed Unit],tManiqHars[Display Scheme],"Principal Emerging Bluechip Fund Growth")*IFERROR(VLOOKUP("Principal Emerging Bluechip Fund Growth",tNAV[[Display Scheme]:[Latest NAV]],3,FALSE()),0) -> 0 | F73: =E73-D73 -> 0 | G73: =IF(E73<0.01,"",IFERROR(F73/D73,0)) | H73: =IF(E73<0.01,"Realized","Unrealized") -> Realized | I73: {=IFERROR(IF(E73<=0,"",XIRR(_xlfn.VSTACK(_xlfn._xlws.FILTER(-tManiqHars[Signed Amount],tManiqHars[Display Scheme]="Principal Emerging Bluechip Fund Growth"),E73),_xlfn.VSTACK(_xlfn._xlws.FILTER(tManiqHars[Date],tManiqHars[Display Scheme]="Principal Emerging Bluechip Fund Growth"),TODAY()))),"")} | J73: =IF(E73<0.01,"Redeemed",IF(F73>=0,"In Profit","In Loss")) -> Redeemed
A74: Sbi Small Cap Fund Growth | B74: =COUNTIFS(tManiqHars[Display Scheme],"Sbi Small Cap Fund Growth") -> 62 | D74: =MAX(0,SUMIFS(tManiqHars[Signed Amount],tManiqHars[Display Scheme],"Sbi Small Cap Fund Growth")) -> 154992.56 | E74: =SUMIFS(tManiqHars[Signed Unit],tManiqHars[Display Scheme],"Sbi Small Cap Fund Growth")*IFERROR(VLOOKUP("Sbi Small Cap Fund Growth",tNAV[[Display Scheme]:[Latest NAV]],3,FALSE()),0) -> 215466.84 | F74: =E74-D74 -> 60474.283 | G74: =IF(E74<0.01,"",IFERROR(F74/D74,0)) -> 0.39017539 | H74: =IF(E74<0.01,"Realized","Unrealized") -> Unrealized | I74: {=IFERROR(IF(E74<=0,"",XIRR(_xlfn.VSTACK(_xlfn._xlws.FILTER(-tManiqHars[Signed Amount],tManiqHars[Display Scheme]="Sbi Small Cap Fund Growth"),E74),_xlfn.VSTACK(_xlfn._xlws.FILTER(tManiqHars[Date],tManiqHars[Display Scheme]="Sbi Small Cap Fund Growth"),TODAY()))),"")} -> 0.12317422 | J74: =IF(E74<0.01,"Redeemed",IF(F74>=0,"In Profit","In Loss")) -> In Profit
A75: Sundaram Large And Mid Cap Fund Growth | B75: =COUNTIFS(tManiqHars[Display Scheme],"Sundaram Large And Mid Cap Fund Growth") -> 4 | D75: =MAX(0,SUMIFS(tManiqHars[Signed Amount],tManiqHars[Display Scheme],"Sundaram Large And Mid Cap Fund Growth")) -> 0 | E75: =SUMIFS(tManiqHars[Signed Unit],tManiqHars[Display Scheme],"Sundaram Large And Mid Cap Fund Growth")*IFERROR(VLOOKUP("Sundaram Large And Mid Cap Fund Growth",tNAV[[Display Scheme]:[Latest NAV]],3,FALSE()),0) -> 0 | F75: =E75-D75 -> 0 | G75: =IF(E75<0.01,"",IFERROR(F75/D75,0)) | H75: =IF(E75<0.01,"Realized","Unrealized") -> Realized | I75: {=IFERROR(IF(E75<=0,"",XIRR(_xlfn.VSTACK(_xlfn._xlws.FILTER(-tManiqHars[Signed Amount],tManiqHars[Display Scheme]="Sundaram Large And Mid Cap Fund Growth"),E75),_xlfn.VSTACK(_xlfn._xlws.FILTER(tManiqHars[Date],tManiqHars[Display Scheme]="Sundaram Large And Mid Cap Fund Growth"),TODAY()))),"")} | J75: =IF(E75<0.01,"Redeemed",IF(F75>=0,"In Profit","In Loss")) -> Redeemed
A76: Uti Focused Fund Growth | B76: =COUNTIFS(tManiqHars[Display Scheme],"Uti Focused Fund Growth") -> 3 | D76: =MAX(0,SUMIFS(tManiqHars[Signed Amount],tManiqHars[Display Scheme],"Uti Focused Fund Growth")) -> 0 | E76: =SUMIFS(tManiqHars[Signed Unit],tManiqHars[Display Scheme],"Uti Focused Fund Growth")*IFERROR(VLOOKUP("Uti Focused Fund Growth",tNAV[[Display Scheme]:[Latest NAV]],3,FALSE()),0) -> 0 | F76: =E76-D76 -> 0 | G76: =IF(E76<0.01,"",IFERROR(F76/D76,0)) | H76: =IF(E76<0.01,"Realized","Unrealized") -> Realized | I76: {=IFERROR(IF(E76<=0,"",XIRR(_xlfn.VSTACK(_xlfn._xlws.FILTER(-tManiqHars[Signed Amount],tManiqHars[Display Scheme]="Uti Focused Fund Growth"),E76),_xlfn.VSTACK(_xlfn._xlws.FILTER(tManiqHars[Date],tManiqHars[Display Scheme]="Uti Focused Fund Growth"),TODAY()))),"")} | J76: =IF(E76<0.01,"Redeemed",IF(F76>=0,"In Profit","In Loss")) -> Redeemed
A77: Zerodha - Ashutosh | B77: =COUNTA(tZerodhAshu[Date]) -> 6 | C77: {=SUMPRODUCT((COUNTIF(tZerodhAshu[Display Scheme],tZerodhAshu[Display Scheme])>0)/COUNTIF(tZerodhAshu[Display Scheme],tZerodhAshu[Display Scheme]))} -> 3 | D77: =SUM(tZerodhAshu[Signed Amount]) -> 299985.23 | E77: {=SUMPRODUCT(SUMIFS(tZerodhAshu[Signed Unit],tZerodhAshu[Display Scheme],MFwise[Display Scheme])*MFwise[Latest NAV])} -> 349560.44 | F77: =E77-D77 -> 49575.214 | G77: =IFERROR(F77/D77,0) -> 0.16525885 | I77: {=IFERROR(IF(E77<=0,"",XIRR(_xlfn.VSTACK(-tZerodhAshu[Signed Amount],E77),_xlfn.VSTACK(tZerodhAshu[Date],TODAY()))),"")} -> 0.099623615 | J77: =IF(F77>=0,"In Profit","In Loss") -> In Profit
A78: Hdfc Gold Etf Fund Of Fund Direct Growth Option | B78: =COUNTIFS(tZerodhAshu[Display Scheme],"Hdfc Gold Etf Fund Of Fund Direct Growth Option") -> 1 | D78: =MAX(0,SUMIFS(tZerodhAshu[Signed Amount],tZerodhAshu[Display Scheme],"Hdfc Gold Etf Fund Of Fund Direct Growth Option")) -> 49997.51 | E78: =SUMIFS(tZerodhAshu[Signed Unit],tZerodhAshu[Display Scheme],"Hdfc Gold Etf Fund Of Fund Direct Growth Option")*IFERROR(VLOOKUP("Hdfc Gold Etf Fund Of Fund Direct Growth Option",tNAV[[Display Scheme]:[Latest NAV]],3,FALSE()),0) -> 55826.967 | F78: =E78-D78 -> 5829.457 | G78: =IF(E78<0.01,"",IFERROR(F78/D78,0)) -> 0.11659495 | H78: =IF(E78<0.01,"Realized","Unrealized") -> Unrealized | I78: {=IFERROR(IF(E78<=0,"",XIRR(_xlfn.VSTACK(_xlfn._xlws.FILTER(-tZerodhAshu[Signed Amount],tZerodhAshu[Display Scheme]="Hdfc Gold Etf Fund Of Fund Direct Growth Option"),E78),_xlfn.VSTACK(_xlfn._xlws.FILTER(tZerodhAshu[Date],tZerodhAshu[Display Scheme]="Hdfc Gold Etf Fund Of Fund Direct Growth Option"),TODAY()))),"")} -> 0.19402341 | J78: =IF(E78<0.01,"Redeemed",IF(F78>=0,"In Profit","In Loss")) -> In Profit
A79: Invesco India Contra Fund - Direct Plan | B79: =COUNTIFS(tZerodhAshu[Display Scheme],"Invesco India Contra Fund - Direct Plan") -> 2 | D79: =MAX(0,SUMIFS(tZerodhAshu[Signed Amount],tZerodhAshu[Display Scheme],"Invesco India Contra Fund - Direct Plan")) -> 99995.08 | E79: =SUMIFS(tZerodhAshu[Signed Unit],tZerodhAshu[Display Scheme],"Invesco India Contra Fund - Direct Plan")*IFERROR(VLOOKUP("Invesco India Contra Fund - Direct Plan",tNAV[[Display Scheme]:[Latest NAV]],3,FALSE()),0) -> 160166.15 | F79: =E79-D79 -> 60171.068 | G79: =IF(E79<0.01,"",IFERROR(F79/D79,0)) -> 0.60174028 | H79: =IF(E79<0.01,"Realized","Unrealized") -> Unrealized | I79: {=IFERROR(IF(E79<=0,"",XIRR(_xlfn.VSTACK(_xlfn._xlws.FILTER(-tZerodhAshu[Signed Amount],tZerodhAshu[Display Scheme]="Invesco India Contra Fund - Direct Plan"),E79),_xlfn.VSTACK(_xlfn._xlws.FILTER(tZerodhAshu[Date],tZerodhAshu[Display Scheme]="Invesco India Contra Fund - Direct Plan"),TODAY()))),"")} -> 0.14925649 | J79: =IF(E79<0.01,"Redeemed",IF(F79>=0,"In Profit","In Loss")) -> In Profit
A80: Mirae Asset Large And Mid Cap Fund Growth | B80: =COUNTIFS(tZerodhAshu[Display Scheme],"Mirae Asset Large And Mid Cap Fund Growth") -> 3 | D80: =MAX(0,SUMIFS(tZerodhAshu[Signed Amount],tZerodhAshu[Display Scheme],"Mirae Asset Large And Mid Cap Fund Growth")) -> 149992.64 | E80: =SUMIFS(tZerodhAshu[Signed Unit],tZerodhAshu[Display Scheme],"Mirae Asset Large And Mid Cap Fund Growth")*IFERROR(VLOOKUP("Mirae Asset Large And Mid Cap Fund Growth",tNAV[[Display Scheme]:[Latest NAV]],3,FALSE()),0) -> 133567.33 | F80: =E80-D80 -> -16425.31 | G80: =IF(E80<0.01,"",IFERROR(F80/D80,0)) -> -0.10950744 | H80: =IF(E80<0.01,"Realized","Unrealized") -> Unrealized | I80: {=IFERROR(IF(E80<=0,"",XIRR(_xlfn.VSTACK(_xlfn._xlws.FILTER(-tZerodhAshu[Signed Amount],tZerodhAshu[Display Scheme]="Mirae Asset Large And Mid Cap Fund Growth"),E80),_xlfn.VSTACK(_xlfn._xlws.FILTER(tZerodhAshu[Date],tZerodhAshu[Display Scheme]="Mirae Asset Large And Mid Cap Fund Growth"),TODAY()))),"")} -> -0.15871939 | J80: =IF(E80<0.01,"Redeemed",IF(F80>=0,"In Profit","In Loss")) -> In Loss
A81: Zerodha - Harsha | B81: =COUNTA(tZerodhHars[Date]) -> 20 | C81: {=SUMPRODUCT((COUNTIF(tZerodhHars[Display Scheme],tZerodhHars[Display Scheme])>0)/COUNTIF(tZerodhHars[Display Scheme],tZerodhHars[Display Scheme]))} -> 5 | D81: =SUM(tZerodhHars[Signed Amount]) -> 654969.53 | E81: {=SUMPRODUCT(SUMIFS(tZerodhHars[Signed Unit],tZerodhHars[Display Scheme],MFwise[Display Scheme])*MFwise[Latest NAV])} -> 608824.91 | F81: =E81-D81 -> -46144.617 | G81: =IFERROR(F81/D81,0) -> -0.070453074 | I81: {=IFERROR(IF(E81<=0,"",XIRR(_xlfn.VSTACK(-tZerodhHars[Signed Amount],E81),_xlfn.VSTACK(tZerodhHars[Date],TODAY()))),"")} -> 2.9802322e-09 | J81: =IF(F81>=0,"In Profit","In Loss") -> In Loss
A82: Hdfc Flexicap Fund Direct Growth Option | B82: =COUNTIFS(tZerodhHars[Display Scheme],"Hdfc Flexicap Fund Direct Growth Option") -> 2 | D82: =MAX(0,SUMIFS(tZerodhHars[Signed Amount],tZerodhHars[Display Scheme],"Hdfc Flexicap Fund Direct Growth Option")) -> 249989.61 | E82: =SUMIFS(tZerodhHars[Signed Unit],tZerodhHars[Display Scheme],"Hdfc Flexicap Fund Direct Growth Option")*IFERROR(VLOOKUP("Hdfc Flexicap Fund Direct Growth Option",tNAV[[Display Scheme]:[Latest NAV]],3,FALSE()),0) -> 245482.59 | F82: =E82-D82 -> -4507.0234 | G82: =IF(E82<0.01,"",IFERROR(F82/D82,0)) -> -0.018028843 | H82: =IF(E82<0.01,"Realized","Unrealized") -> Unrealized | I82: {=IFERROR(IF(E82<=0,"",XIRR(_xlfn.VSTACK(_xlfn._xlws.FILTER(-tZerodhHars[Signed Amount],tZerodhHars[Display Scheme]="Hdfc Flexicap Fund Direct Growth Option"),E82),_xlfn.VSTACK(_xlfn._xlws.FILTER(tZerodhHars[Date],tZerodhHars[Display Scheme]="Hdfc Flexicap Fund Direct Growth Option"),TODAY()))),"")} -> -0.029031786 | J82: =IF(E82<0.01,"Redeemed",IF(F82>=0,"In Profit","In Loss")) -> In Loss
A83: Hdfc Gold Etf Fund Of Fund Direct Growth Option | B83: =COUNTIFS(tZerodhHars[Display Scheme],"Hdfc Gold Etf Fund Of Fund Direct Growth Option") -> 3 | D83: =MAX(0,SUMIFS(tZerodhHars[Signed Amount],tZerodhHars[Display Scheme],"Hdfc Gold Etf Fund Of Fund Direct Growth Option")) -> 149992.5 | E83: =SUMIFS(tZerodhHars[Signed Unit],tZerodhHars[Display Scheme],"Hdfc Gold Etf Fund Of Fund Direct Growth Option")*IFERROR(VLOOKUP("Hdfc Gold Etf Fund Of Fund Direct Growth Option",tNAV[[Display Scheme]:[Latest NAV]],3,FALSE()),0) -> 141962.91 | F83: =E83-D83 -> -8029.5898 | G83: =IF(E83<0.01,"",IFERROR(F83/D83,0)) -> -0.053533275 | H83: =IF(E83<0.01,"Realized","Unrealized") -> Unrealized | I83: {=IFERROR(IF(E83<=0,"",XIRR(_xlfn.VSTACK(_xlfn._xlws.FILTER(-tZerodhHars[Signed Amount],tZerodhHars[Display Scheme]="Hdfc Gold Etf Fund Of Fund Direct Growth Option"),E83),_xlfn.VSTACK(_xlfn._xlws.FILTER(tZerodhHars[Date],tZerodhHars[Display Scheme]="Hdfc Gold Etf Fund Of Fund Direct Growth Option"),TODAY()))),"")} -> -0.11150357 | J83: =IF(E83<0.01,"Redeemed",IF(F83>=0,"In Profit","In Loss")) -> In Loss
A84: Hdfc Silver Etf Fund Of Fund Direct Growth | B84: =COUNTIFS(tZerodhHars[Display Scheme],"Hdfc Silver Etf Fund Of Fund Direct Growth") -> 4 | D84: =MAX(0,SUMIFS(tZerodhHars[Signed Amount],tZerodhHars[Display Scheme],"Hdfc Silver Etf Fund Of Fund Direct Growth")) -> 129993.47 | E84: =SUMIFS(tZerodhHars[Signed Unit],tZerodhHars[Display Scheme],"Hdfc Silver Etf Fund Of Fund Direct Growth")*IFERROR(VLOOKUP("Hdfc Silver Etf Fund Of Fund Direct Growth",tNAV[[Display Scheme]:[Latest NAV]],3,FALSE()),0) -> 93174.242 | F84: =E84-D84 -> -36819.228 | G84: =IF(E84<0.01,"",IFERROR(F84/D84,0)) -> -0.28323906 | H84: =IF(E84<0.01,"Realized","Unrealized") -> Unrealized | I84: {=IFERROR(IF(E84<=0,"",XIRR(_xlfn.VSTACK(_xlfn._xlws.FILTER(-tZerodhHars[Signed Amount],tZerodhHars[Display Scheme]="Hdfc Silver Etf Fund Of Fund Direct Growth"),E84),_xlfn.VSTACK(_xlfn._xlws.FILTER(tZerodhHars[Date],tZerodhHars[Display Scheme]="Hdfc Silver Etf Fund Of Fund Direct Growth"),TODAY()))),"")} -> -0.54444951 | J84: =IF(E84<0.01,"Redeemed",IF(F84>=0,"In Profit","In Loss")) -> In Loss
A85: Icici Prudential Balanced Advantage Fund Direct Growth | B85: =COUNTIFS(tZerodhHars[Display Scheme],"Icici Prudential Balanced Advantage Fund Direct Growth") -> 9 | D85: =MAX(0,SUMIFS(tZerodhHars[Signed Amount],tZerodhHars[Display Scheme],"Icici Prudential Balanced Advantage Fund Direct Growth")) -> 24998.93 | E85: =SUMIFS(tZerodhHars[Signed Unit],tZerodhHars[Display Scheme],"Icici Prudential Balanced Advantage Fund Direct Growth")*IFERROR(VLOOKUP("Icici Prudential Balanced Advantage Fund Direct Growth",tNAV[[Display Scheme]:[Latest NAV]],3,FALSE()),0) -> 25654.883 | F85: =E85-D85 -> 655.95274 | G85: =IF(E85<0.01,"",IFERROR(F85/D85,0)) -> 0.026239233 | H85: =IF(E85<0.01,"Realized","Unrealized") -> Unrealized | I85: {=IFERROR(IF(E85<=0,"",XIRR(_xlfn.VSTACK(_xlfn._xlws.FILTER(-tZerodhHars[Signed Amount],tZerodhHars[Display Scheme]="Icici Prudential Balanced Advantage Fund Direct Growth"),E85),_xlfn.VSTACK(_xlfn._xlws.FILTER(tZerodhHars[Date],tZerodhHars[Display Scheme]="Icici Prudential Balanced Advantage Fund Direct Growth"),TODAY()))),"")} -> 0.11313738 | J85: =IF(E85<0.01,"Redeemed",IF(F85>=0,"In Profit","In Loss")) -> In Profit
A86: Invesco India Arbitrage Fund - Direct Plan Growth | B86: =COUNTIFS(tZerodhHars[Display Scheme],"Invesco India Arbitrage Fund - Direct Plan Growth") -> 2 | D86: =MAX(0,SUMIFS(tZerodhHars[Signed Amount],tZerodhHars[Display Scheme],"Invesco India Arbitrage Fund - Direct Plan Growth")) -> 99995.02 | E86: =SUMIFS(tZerodhHars[Signed Unit],tZerodhHars[Display Scheme],"Invesco India Arbitrage Fund - Direct Plan Growth")*IFERROR(VLOOKUP("Invesco India Arbitrage Fund - Direct Plan Growth",tNAV[[Display Scheme]:[Latest NAV]],3,FALSE()),0) -> 102550.29 | F86: =E86-D86 -> 2555.2716 | G86: =IF(E86<0.01,"",IFERROR(F86/D86,0)) -> 0.025553989 | H86: =IF(E86<0.01,"Realized","Unrealized") -> Unrealized | I86: {=IFERROR(IF(E86<=0,"",XIRR(_xlfn.VSTACK(_xlfn._xlws.FILTER(-tZerodhHars[Signed Amount],tZerodhHars[Display Scheme]="Invesco India Arbitrage Fund - Direct Plan Growth"),E86),_xlfn.VSTACK(_xlfn._xlws.FILTER(tZerodhHars[Date],tZerodhHars[Display Scheme]="Invesco India Arbitrage Fund - Direct Plan Growth"),TODAY()))),"")} -> 0.064206973 | J86: =IF(E86<0.01,"Redeemed",IF(F86>=0,"In Profit","In Loss")) -> In Profit
A87: TOTAL | B87: =SUM(B47:B86)/2 -> 632 | C87: =COUNTA(MFwise[Display Scheme]) -> 31 | D87: =D47+D58+D63+D77+D81 -> 4214553.9 | E87: =E47+E58+E63+E77+E81 -> 6847516.3 | F87: =E87-D87 -> 2632962.4 | G87: =IFERROR(F87/D87,0) -> 0.624731 | I87: {=IFERROR(XIRR(_xlfn.VSTACK(-tAllCF[Signed Amount],E87),_xlfn.VSTACK(tAllCF[Date],TODAY())),"")} -> 0.12432699 | J87: =IF(F87>=0,"In Profit","In Loss") -> In Profit

Sheet NAV Reference
A1: NAV Reference — Latest NAV per Display Scheme
A2: NAVs sourced from MoneyControl portfolio exports where available; otherwise the most recent transaction NAV is used. Edit values here to refresh the dashboard.
A4: Display Scheme | B4: Scheme Key | C4: Latest NAV | D4: NAV Source | E4: Notes | F4: Scheme Code | G4: Remarks
A5: Aditya Birla Sun Life Banking And Financial Services Fund Growth | B5: adityabirlasunlifeba | C5: =IF(F5="",0,IFERROR(VLOOKUP(F5,NAVAll!$A:$E,5,FALSE),0)) -> 63.59 | D5: =IF(F5="","Redeemed",IF(ISNUMBER(VLOOKUP(F5,NAVAll!$A:$E,5,FALSE)),"NAVAll","Last txn NAV")) -> NAVAll | F5: 125595
A6: Aditya Birla Sun Life Value Fund Growth | B6: adityabirlasunlifeva | C6: =IF(F6="",0,IFERROR(VLOOKUP(F6,NAVAll!$A:$E,5,FALSE),0)) -> 133.0035 | D6: =IF(F6="","Redeemed",IF(ISNUMBER(VLOOKUP(F6,NAVAll!$A:$E,5,FALSE)),"NAVAll","Last txn NAV")) -> NAVAll | F6: 108167
A7: Canara Robeco Large And Mid Cap Fund Growth | B7: canararobecolargemid | C7: =IF(F7="",0,IFERROR(VLOOKUP(F7,NAVAll!$A:$E,5,FALSE),0)) -> 250.89 | D7: =IF(F7="","Redeemed",IF(ISNUMBER(VLOOKUP(F7,NAVAll!$A:$E,5,FALSE)),"NAVAll","Last txn NAV")) -> NAVAll | F7: 102920
A8: Canara Robeco Large Cap Fund Regulargrowth | B8: canararobecolargecap | C8: =IF(F8="",0,IFERROR(VLOOKUP(F8,NAVAll!$A:$E,5,FALSE),0)) -> 61.15 | D8: =IF(F8="","Redeemed",IF(ISNUMBER(VLOOKUP(F8,NAVAll!$A:$E,5,FALSE)),"NAVAll","Last txn NAV")) -> NAVAll | F8: 113221
A9: Hdfc Flexicap Fund Direct Growth Option | B9: hdfcflexicapfund | C9: =IF(F9="",0,IFERROR(VLOOKUP(F9,NAVAll!$A:$E,5,FALSE),0)) -> 2215.087 | D9: =IF(F9="","Redeemed",IF(ISNUMBER(VLOOKUP(F9,NAVAll!$A:$E,5,FALSE)),"NAVAll","Last txn NAV")) -> NAVAll | F9: 118955
A10: Hdfc Gold Etf Fund Of Fund Direct Growth Option | B10: hdfcgoldetffundoffun | C10: =IF(F10="",0,IFERROR(VLOOKUP(F10,NAVAll!$A:$E,5,FALSE),0)) -> 43.279 | D10: =IF(F10="","Redeemed",IF(ISNUMBER(VLOOKUP(F10,NAVAll!$A:$E,5,FALSE)),"NAVAll","Last txn NAV")) -> NAVAll | F10: 119132
A11: Hdfc Mid Cap Fund - Growth Option | B11: hdfcmidcapfund | C11: =IF(F11="",0,IFERROR(VLOOKUP(F11,NAVAll!$A:$E,5,FALSE),0)) -> 204.864 | D11: =IF(F11="","Redeemed",IF(ISNUMBER(VLOOKUP(F11,NAVAll!$A:$E,5,FALSE)),"NAVAll","Last txn NAV")) -> NAVAll | F11: 105758
A12: Hdfc Silver Etf Fund Of Fund Direct Growth | B12: hdfcsilveretffundoff | C12: =IF(F12="",0,IFERROR(VLOOKUP(F12,NAVAll!$A:$E,5,FALSE),0)) -> 35.6537 | D12: =IF(F12="","Redeemed",IF(ISNUMBER(VLOOKUP(F12,NAVAll!$A:$E,5,FALSE)),"NAVAll","Last txn NAV")) -> NAVAll | F12: 150737
A13: Icici Prudential Balanced Advantage Fund Direct Growth | B13: iciciprudentialbalan | C13: =IF(F13="",0,IFERROR(VLOOKUP(F13,NAVAll!$A:$E,5,FALSE),0)) -> 86.86 | D13: =IF(F13="","Redeemed",IF(ISNUMBER(VLOOKUP(F13,NAVAll!$A:$E,5,FALSE)),"NAVAll","Last txn NAV")) -> NAVAll | F13: 120377
A14: Icici Prudential Focused Equity Fund Growth | B14: iciciprudentialfocus | C14: =IF(F14="",0,IFERROR(VLOOKUP(F14,NAVAll!$A:$E,5,FALSE),0)) -> 93.49 | D14: =IF(F14="","Redeemed",IF(ISNUMBER(VLOOKUP(F14,NAVAll!$A:$E,5,FALSE)),"NAVAll","Last txn NAV")) -> NAVAll | F14: 111957
A15: Icici Prudential Value Fund Growth | B15: iciciprudentialvalue | C15: =IF(F15="",0,IFERROR(VLOOKUP(F15,NAVAll!$A:$E,5,FALSE),0)) -> 462.41 | D15: =IF(F15="","Redeemed",IF(ISNUMBER(VLOOKUP(F15,NAVAll!$A:$E,5,FALSE)),"NAVAll","Last txn NAV")) -> NAVAll | F15: 102594
A16: Invesco India Arbitrage Fund - Direct Plan Growth | B16: invescoindiaarbitrag | C16: =IF(F16="",0,IFERROR(VLOOKUP(F16,NAVAll!$A:$E,5,FALSE),0)) -> 36.7857 | D16: =IF(F16="","Redeemed",IF(ISNUMBER(VLOOKUP(F16,NAVAll!$A:$E,5,FALSE)),"NAVAll","Last txn NAV")) -> NAVAll | F16: 120401
A17: Invesco India Contra Fund - Direct Plan | B17: invescoindiacontrafu | C17: =IF(F17="",0,IFERROR(VLOOKUP(F17,NAVAll!$A:$E,5,FALSE),0)) -> 157.4 | D17: =IF(F17="","Redeemed",IF(ISNUMBER(VLOOKUP(F17,NAVAll!$A:$E,5,FALSE)),"NAVAll","Last txn NAV")) -> NAVAll | F17: 120348
A18: Invesco India Multicap Fund Growth | B18: invescoindiamulticap | C18: =IF(F18="",0,IFERROR(VLOOKUP(F18,NAVAll!$A:$E,5,FALSE),0)) -> 0 | D18: =IF(F18="","Redeemed",IF(ISNUMBER(VLOOKUP(F18,NAVAll!$A:$E,5,FALSE)),"NAVAll","Last txn NAV")) -> Redeemed | G18: Already redeemed
A19: Kotak Contra Fund - Growth | B19: kotakcontrafund | C19: =IF(F19="",0,IFERROR(VLOOKUP(F19,NAVAll!$A:$E,5,FALSE),0)) -> 151.745 | D19: =IF(F19="","Redeemed",IF(ISNUMBER(VLOOKUP(F19,NAVAll!$A:$E,5,FALSE)),"NAVAll","Last txn NAV")) -> NAVAll | F19: 103040
A20: Kotak Multicap Fund Growth | B20: kotakmulticapfund | C20: =IF(F20="",0,IFERROR(VLOOKUP(F20,NAVAll!$A:$E,5,FALSE),0)) -> 19.991 | D20: =IF(F20="","Redeemed",IF(ISNUMBER(VLOOKUP(F20,NAVAll!$A:$E,5,FALSE)),"NAVAll","Last txn NAV")) -> NAVAll | F20: 149182
A21: Lnt Flexicap Fund Regular Growth Option | B21: lntflexicapfund | C21: =IF(F21="",0,IFERROR(VLOOKUP(F21,NAVAll!$A:$E,5,FALSE),0)) -> 0 | D21: =IF(F21="","Redeemed",IF(ISNUMBER(VLOOKUP(F21,NAVAll!$A:$E,5,FALSE)),"NAVAll","Last txn NAV")) -> Redeemed | G21: Already redeemed
A22: Mahindra Manulife Flexi Cap Fund Growth | B22: mahindramanulifeflex | C22: =IF(F22="",0,IFERROR(VLOOKUP(F22,NAVAll!$A:$E,5,FALSE),0)) -> 15.7556 | D22: =IF(F22="","Redeemed",IF(ISNUMBER(VLOOKUP(F22,NAVAll!$A:$E,5,FALSE)),"NAVAll","Last txn NAV")) -> NAVAll | F22: 149101
A23: Mahindra Manulife Focused Fund Growth | B23: mahindramanulifefocu | C23: =IF(F23="",0,IFERROR(VLOOKUP(F23,NAVAll!$A:$E,5,FALSE),0)) -> 26.9523 | D23: =IF(F23="","Redeemed",IF(ISNUMBER(VLOOKUP(F23,NAVAll!$A:$E,5,FALSE)),"NAVAll","Last txn NAV")) -> NAVAll | F23: 148571
A24: Mahindra Manulife Large And Mid Cap Fund Growth | B24: mahindramanulifelarg | C24: =IF(F24="",0,IFERROR(VLOOKUP(F24,NAVAll!$A:$E,5,FALSE),0)) -> 26.9111 | D24: =IF(F24="","Redeemed",IF(ISNUMBER(VLOOKUP(F24,NAVAll!$A:$E,5,FALSE)),"NAVAll","Last txn NAV")) -> NAVAll | F24: 147843
A25: Mahindra Manulife Mid Cap Fund Growth | B25: mahindramanulifemidc | C25: =IF(F25="",0,IFERROR(VLOOKUP(F25,NAVAll!$A:$E,5,FALSE),0)) -> 36.2885 | D25: =IF(F25="","Redeemed",IF(ISNUMBER(VLOOKUP(F25,NAVAll!$A:$E,5,FALSE)),"NAVAll","Last txn NAV")) -> NAVAll | F25: 142109
A26: Mirae Asset Large And Mid Cap Fund Growth | B26: miraeassetlargemidca | C26: =IF(F26="",0,IFERROR(VLOOKUP(F26,NAVAll!$A:$E,5,FALSE),0)) -> 154.526 | D26: =IF(F26="","Redeemed",IF(ISNUMBER(VLOOKUP(F26,NAVAll!$A:$E,5,FALSE)),"NAVAll","Last txn NAV")) -> NAVAll | F26: 112932
A27: Nippon India Elss Tax Saver Fund - Growth Plan | B27: nipponindiaelsstaxsa | C27: =IF(F27="",0,IFERROR(VLOOKUP(F27,NAVAll!$A:$E,5,FALSE),0)) -> 131.2407 | D27: =IF(F27="","Redeemed",IF(ISNUMBER(VLOOKUP(F27,NAVAll!$A:$E,5,FALSE)),"NAVAll","Last txn NAV")) -> NAVAll | F27: 103196 | G27: Already redeemed
A28: Nippon India Equity Linked Savings Fund Series - I Growth | B28: nipponindiaequitylin | C28: =IF(F28="",0,IFERROR(VLOOKUP(F28,NAVAll!$A:$E,5,FALSE),0)) -> 0 | D28: =IF(F28="","Redeemed",IF(ISNUMBER(VLOOKUP(F28,NAVAll!$A:$E,5,FALSE)),"NAVAll","Last txn NAV")) -> Redeemed | G28: Already redeemed
A29: Principal Emerging Bluechip Fund Growth | B29: principalemergingblu | C29: =IF(F29="",0,IFERROR(VLOOKUP(F29,NAVAll!$A:$E,5,FALSE),0)) -> 0 | D29: =IF(F29="","Redeemed",IF(ISNUMBER(VLOOKUP(F29,NAVAll!$A:$E,5,FALSE)),"NAVAll","Last txn NAV")) -> Redeemed | G29: Already redeemed
A30: Sbi Contra Fund Regular Idcw | B30: sbicontrafund | C30: =IF(F30="",0,IFERROR(VLOOKUP(F30,NAVAll!$A:$E,5,FALSE),0)) -> 0 | D30: =IF(F30="","Redeemed",IF(ISNUMBER(VLOOKUP(F30,NAVAll!$A:$E,5,FALSE)),"NAVAll","Last txn NAV")) -> Redeemed | G30: Already redeemed
A31: Sbi Elss Tax Saver Fund - Growth | B31: sbielsstaxsaverfund | C31: =IF(F31="",0,IFERROR(VLOOKUP(F31,NAVAll!$A:$E,5,FALSE),0)) -> 436.6786 | D31: =IF(F31="","Redeemed",IF(ISNUMBER(VLOOKUP(F31,NAVAll!$A:$E,5,FALSE)),"NAVAll","Last txn NAV")) -> NAVAll | F31: 105628
A32: Sbi Flexicap Fund - Growth | B32: sbiflexicapfund | C32: =IF(F32="",0,IFERROR(VLOOKUP(F32,NAVAll!$A:$E,5,FALSE),0)) -> 106.9365 | D32: =IF(F32="","Redeemed",IF(ISNUMBER(VLOOKUP(F32,NAVAll!$A:$E,5,FALSE)),"NAVAll","Last txn NAV")) -> NAVAll | F32: 103215
A33: Sbi Small Cap Fund Growth | B33: sbismallcapfund | C33: =IF(F33="",0,IFERROR(VLOOKUP(F33,NAVAll!$A:$E,5,FALSE),0)) -> 176.8409 | D33: =IF(F33="","Redeemed",IF(ISNUMBER(VLOOKUP(F33,NAVAll!$A:$E,5,FALSE)),"NAVAll","Last txn NAV")) -> NAVAll | F33: 125494
A34: Sundaram Large And Mid Cap Fund Growth | B34: sundaramlargemidcapf | C34: =IF(F34="",0,IFERROR(VLOOKUP(F34,NAVAll!$A:$E,5,FALSE),0)) -> 0 | D34: =IF(F34="","Redeemed",IF(ISNUMBER(VLOOKUP(F34,NAVAll!$A:$E,5,FALSE)),"NAVAll","Last txn NAV")) -> Redeemed | G34: Already redeemed
A35: Uti Focused Fund Growth | B35: utifocusedfund | C35: =IF(F35="",0,IFERROR(VLOOKUP(F35,NAVAll!$A:$E,5,FALSE),0)) -> 0 | D35: =IF(F35="","Redeemed",IF(ISNUMBER(VLOOKUP(F35,NAVAll!$A:$E,5,FALSE)),"NAVAll","Last txn NAV")) -> Redeemed | G35: Already redeemed

Sheet Scheme Map
A1: Scheme Map — Raw Platform Scheme → Canonical Display Name
A2: Each platform names schemes differently. The Display column is what the Dashboard groups by. Edit Display values here to merge two raw schemes under one canonical name.
A4: Scheme Name (raw) | B4: Scheme Key | C4: Display Scheme
A5: Aditya Birla Sun Life Banking and Financial Services Fund Growth | B5: adityabirlasunlifeba | C5: Aditya Birla Sun Life Banking And Financial Services Fund Growth
A6: Aditya Birla Sun Life Value Fund Growth | B6: adityabirlasunlifeva | C6: Aditya Birla Sun Life Value Fund Growth
A7: Canara Robeco Large And Mid Cap Fund Regular -Growth | B7: canararobecolargemid | C7: Canara Robeco Large And Mid Cap Fund Growth
A8: Canara Robeco Large and Mid Cap Fund Growth | B8: canararobecolargemid | C8: Canara Robeco Large And Mid Cap Fund Growth
A9: Canara Robeco Large Cap Fund Regulargrowth | B9: canararobecolargecap | C9: Canara Robeco Large Cap Fund Regulargrowth
A10: Hdfc Flexicap Fund - Direct Plan - Growth Option | B10: hdfcflexicapfund | C10: Hdfc Flexicap Fund Direct Growth Option
A11: Hdfc Gold Etf Fund Of Fund - Direct Plan - Growth Option | B11: hdfcgoldetffundoffun | C11: Hdfc Gold Etf Fund Of Fund Direct Growth Option
A12: HDFC Mid Cap Fund - Growth Option | B12: hdfcmidcapfund | C12: Hdfc Mid Cap Fund - Growth Option
A13: Hdfc Silver Etf Fund Of Fund Direct Growth | B13: hdfcsilveretffundoff | C13: Hdfc Silver Etf Fund Of Fund Direct Growth
A14: Icici Prudential Balanced Advantage Fund - Direct Plan - Growth | B14: iciciprudentialbalan | C14: Icici Prudential Balanced Advantage Fund Direct Growth
A15: ICICI Prudential Focused Equity Fund Growth | B15: iciciprudentialfocus | C15: Icici Prudential Focused Equity Fund Growth
... A37: UTI Focused Fund Growth | B37: utifocusedfund | C37: Uti Focused Fund Growth

Sheet Txn-ICICI-Ashu
A1: Transactions — ICICI Direct - Ashutosh
A2: 100 transactions • Add or delete rows freely — the Dashboard auto-recomputes via the Excel table named 'tICICIAshu'.
A4: Date | B4: Transaction ID | C4: Transaction Type | D4: Fund Name | E4: Scheme Name | F4: Display Scheme | G4: Folio No | H4: Last recorded NAV | I4: Amount | J4: Unit | K4: Signed Unit | L4: Signed Amount | M4: Status
A5: 46192 | B5: 220886957 | C5: Purchase | D5: Kotak Mahindra Mutual Fund | E5: Kotak Contra Fund - Growth | F5: Kotak Contra Fund - Growth | G5: 8338255 | H5: 152.096 | I5: 6000 | J5: 39.447 | K5: 39.447 | L5: =IF(EXACT(tICICIAshu[[#This Row],[Transaction Type]],"Initial Purchase Pre-Rejection"),0,IF(OR(EXACT(tICICIAshu[[#This Row],[Transaction Type]],"Redemption"),EXACT(tICICIAshu[[#This Row],[Transaction Type]],"Redeem"),EXACT(tICICIAshu[[#This Row],[Transaction Type]],"Switch Out"),EXACT(tICICIAshu[[#This Row],[Transaction Type]],"sell"),EXACT(tICICIAshu[[#This Row],[Transaction Type]],"Sell")),-tICICIAshu[[#This Row],[Amount]],tICICIAshu[[#This Row],[Amount]])) -> 6000 | M5: Executed
A6: 46161 | B6: 220886958 | C6: Purchase | D6: Kotak Mahindra Mutual Fund | E6: Kotak Contra Fund - Growth | F6: Kotak Contra Fund - Growth | G6: 8338255 | H6: 146.33 | I6: 6000 | J6: 41.001 | K6: 41.001 | L6: =IF(EXACT(tICICIAshu[[#This Row],[Transaction Type]],"Initial Purchase Pre-Rejection"),0,IF(OR(EXACT(tICICIAshu[[#This Row],[Transaction Type]],"Redemption"),EXACT(tICICIAshu[[#This Row],[Transaction Type]],"Redeem"),EXACT(tICICIAshu[[#This Row],[Transaction Type]],"Switch Out"),EXACT(tICICIAshu[[#This Row],[Transaction Type]],"sell"),EXACT(tICICIAshu[[#This Row],[Transaction Type]],"Sell")),-tICICIAshu[[#This Row],[Amount]],tICICIAshu[[#This Row],[Amount]])) -> 6000 | M6: Executed
A7: 46131 | B7: 220886959 | C7: Purchase | D7: Kotak Mahindra Mutual Fund | E7: Kotak Contra Fund - Growth | F7: Kotak Contra Fund - Growth | G7: 8338255 | H7: 149.797 | I7: 6000 | J7: 40.052 | K7: =IF(OR(EXACT(C7,"Redemption"),EXACT(C7,"Redeem"),EXACT(C7,"Switch Out"),EXACT(C7,"sell"),EXACT(C7,"Sell")),-J7,J7) -> 40.052 | L7: =IF(EXACT(tICICIAshu[[#This Row],[Transaction Type]],"Initial Purchase Pre-Rejection"),0,IF(OR(EXACT(tICICIAshu[[#This Row],[Transaction Type]],"Redemption"),EXACT(tICICIAshu[[#This Row],[Transaction Type]],"Redeem"),EXACT(tICICIAshu[[#This Row],[Transaction Type]],"Switch Out"),EXACT(tICICIAshu[[#This Row],[Transaction Type]],"sell"),EXACT(tICICIAshu[[#This Row],[Transaction Type]],"Sell")),-tICICIAshu[[#This Row],[Amount]],tICICIAshu[[#This Row],[Amount]])) -> 6000 | M7: Executed
A8: 46100 | B8: 218814304 | C8: Purchase | D8: Kotak Mahindra Mutual Fund | E8: Kotak Contra Fund - Growth | F8: Kotak Contra Fund - Growth | G8: 8338255 | H8: 140.882 | I8: 6000 | J8: 42.587 | K8: =IF(OR(EXACT(C8,"Redemption"),EXACT(C8,"Redeem"),EXACT(C8,"Switch Out"),EXACT(C8,"sell"),EXACT(C8,"Sell")),-J8,J8) -> 42.587 | L8: =IF(EXACT(tICICIAshu[[#This Row],[Transaction Type]],"Initial Purchase Pre-Rejection"),0,IF(OR(EXACT(tICICIAshu[[#This Row],[Transaction Type]],"Redemption"),EXACT(tICICIAshu[[#This Row],[Transaction Type]],"Redeem"),EXACT(tICICIAshu[[#This Row],[Transaction Type]],"Switch Out"),EXACT(tICICIAshu[[#This Row],[Transaction Type]],"sell"),EXACT(tICICIAshu[[#This Row],[Transaction Type]],"Sell")),-tICICIAshu[[#This Row],[Amount]],tICICIAshu[[#This Row],[Amount]])) -> 6000 | M8: Executed
A9: 46072 | B9: 216658609 | C9: Purchase | D9: Kotak Mahindra Mutual Fund | E9: Kotak Contra Fund - Growth | F9: Kotak Contra Fund - Growth | G9: 8338255 | H9: 155.095 | I9: 6000 | J9: 38.684 | K9: =IF(OR(EXACT(C9,"Redemption"),EXACT(C9,"Redeem"),EXACT(C9,"Switch Out"),EXACT(C9,"sell"),EXACT(C9,"Sell")),-J9,J9) -> 38.684 | L9: =IF(EXACT(tICICIAshu[[#This Row],[Transaction Type]],"Initial Purchase Pre-Rejection"),0,IF(OR(EXACT(tICICIAshu[[#This Row],[Transaction Type]],"Redemption"),EXACT(tICICIAshu[[#This Row],[Transaction Type]],"Redeem"),EXACT(tICICIAshu[[#This Row],[Transaction Type]],"Switch Out"),EXACT(tICICIAshu[[#This Row],[Transaction Type]],"sell"),EXACT(tICICIAshu[[#This Row],[Transaction Type]],"Sell")),-tICICIAshu[[#This Row],[Amount]],tICICIAshu[[#This Row],[Amount]])) -> 6000 | M9: Executed
A10: 46041 | B10: 214503559 | C10: Purchase | D10: Kotak Mahindra Mutual Fund | E10: Kotak Contra Fund - Growth | F10: Kotak Contra Fund - Growth | G10: 8338255 | H10: 154.768 | I10: 5500 | J10: 35.535 | K10: =IF(OR(EXACT(C10,"Redemption"),EXACT(C10,"Redeem"),EXACT(C10,"Switch Out"),EXACT(C10,"sell"),EXACT(C10,"Sell")),-J10,J10) -> 35.535 | L10: =IF(EXACT(tICICIAshu[[#This Row],[Transaction Type]],"Initial Purchase Pre-Rejection"),0,IF(OR(EXACT(tICICIAshu[[#This Row],[Transaction Type]],"Redemption"),EXACT(tICICIAshu[[#This Row],[Transaction Type]],"Redeem"),EXACT(tICICIAshu[[#This Row],[Transaction Type]],"Switch Out"),EXACT(tICICIAshu[[#This Row],[Transaction Type]],"sell"),EXACT(tICICIAshu[[#This Row],[Transaction Type]],"Sell")),-tICICIAshu[[#This Row],[Amount]],tICICIAshu[[#This Row],[Amount]])) -> 5500 | M10: Executed
A11: 46010 | B11: 212399210 | C11: Purchase | D11: Kotak Mahindra Mutual Fund | E11: Kotak Contra Fund - Growth | F11: Kotak Contra Fund - Growth | G11: 8338255 | H11: 155.174 | I11: 5500 | J11: 35.442 | K11: =IF(OR(EXACT(C11,"Redemption"),EXACT(C11,"Redeem"),EXACT(C11,"Switch Out"),EXACT(C11,"sell"),EXACT(C11,"Sell")),-J11,J11) -> 35.442 | L11: =IF(EXACT(tICICIAshu[[#This Row],[Transaction Type]],"Initial Purchase Pre-Rejection"),0,IF(OR(EXACT(tICICIAshu[[#This Row],[Transaction Type]],"Redemption"),EXACT(tICICIAshu[[#This Row],[Transaction Type]],"Redeem"),EXACT(tICICIAshu[[#This Row],[Transaction Type]],"Switch Out"),EXACT(tICICIAshu[[#This Row],[Transaction Type]],"sell"),EXACT(tICICIAshu[[#This Row],[Transaction Type]],"Sell")),-tICICIAshu[[#This Row],[Amount]],tICICIAshu[[#This Row],[Amount]])) -> 5500 | M11: Executed
A12: 45980 | B12: 210209359 | C12: Purchase | D12: Kotak Mahindra Mutual Fund | E12: Kotak Contra Fund - Growth | F12: Kotak Contra Fund - Growth | G12: 8338255 | H12: 155.388 | I12: 5500 | J12: 35.394 | K12: =IF(OR(EXACT(C12,"Redemption"),EXACT(C12,"Redeem"),EXACT(C12,"Switch Out"),EXACT(C12,"sell"),EXACT(C12,"Sell")),-J12,J12) -> 35.394 | L12: =IF(EXACT(tICICIAshu[[#This Row],[Transaction Type]],"Initial Purchase Pre-Rejection"),0,IF(OR(EXACT(tICICIAshu[[#This Row],[Transaction Type]],"Redemption"),EXACT(tICICIAshu[[#This Row],[Transaction Type]],"Redeem"),EXACT(tICICIAshu[[#This Row],[Transaction Type]],"Switch Out"),EXACT(tICICIAshu[[#This Row],[Transaction Type]],"sell"),EXACT(tICICIAshu[[#This Row],[Transaction Type]],"Sell")),-tICICIAshu[[#This Row],[Amount]],tICICIAshu[[#This Row],[Amount]])) -> 5500 | M12: Executed
A13: 45949 | B13: 208083815 | C13: Purchase | D13: Kotak Mahindra Mutual Fund | E13: Kotak Contra Fund - Growth | F13: Kotak Contra Fund - Growth | G13: 8338255 | H13: 155.261 | I13: 5500 | J13: 35.422 | K13: =IF(OR(EXACT(C13,"Redemption"),EXACT(C13,"Redeem"),EXACT(C13,"Switch Out"),EXACT(C13,"sell"),EXACT(C13,"Sell")),-J13,J13) -> 35.422 | L13: =IF(EXACT(tICICIAshu[[#This Row],[Transaction Type]],"Initial Purchase Pre-Rejection"),0,IF(OR(EXACT(tICICIAshu[[#This Row],[Transaction Type]],"Redemption"),EXACT(tICICIAshu[[#This Row],[Transaction Type]],"Redeem"),EXACT(tICICIAshu[[#This Row],[Transaction Type]],"Switch Out"),EXACT(tICICIAshu[[#This Row],[Transaction Type]],"sell"),EXACT(tICICIAshu[[#This Row],[Transaction Type]],"Sell")),-tICICIAshu[[#This Row],[Amount]],tICICIAshu[[#This Row],[Amount]])) -> 5500 | M13: Executed
A14: 45919 | B14: 205950151 | C14: Purchase | D14: Kotak Mahindra Mutual Fund | E14: Kotak Contra Fund - Growth | F14: Kotak Contra Fund - Growth | G14: 8338255 | H14: 153.844 | I14: 5500 | J14: 35.749 | K14: =IF(OR(EXACT(C14,"Redemption"),EXACT(C14,"Redeem"),EXACT(C14,"Switch Out"),EXACT(C14,"sell"),EXACT(C14,"Sell")),-J14,J14) -> 35.749 | L14: =IF(EXACT(tICICIAshu[[#This Row],[Transaction Type]],"Initial Purchase Pre-Rejection"),0,IF(OR(EXACT(tICICIAshu[[#This Row],[Transaction Type]],"Redemption"),EXACT(tICICIAshu[[#This Row],[Transaction Type]],"Redeem"),EXACT(tICICIAshu[[#This Row],[Transaction Type]],"Switch Out"),EXACT(tICICIAshu[[#This Row],[Transaction Type]],"sell"),EXACT(tICICIAshu[[#This Row],[Transaction Type]],"Sell")),-tICICIAshu[[#This Row],[Amount]],tICICIAshu[[#This Row],[Amount]])) -> 5500 | M14: Executed
A15: 45888 | B15: 203796826 | C15: Purchase | D15: Kotak Mahindra Mutual Fund | E15: Kotak Contra Fund - Growth | F15: Kotak Contra Fund - Growth | G15: 8338255 | H15: 150.765 | I15: 5500 | J15: 36.479 | K15: =IF(OR(EXACT(C15,"Redemption"),EXACT(C15,"Redeem"),EXACT(C15,"Switch Out"),EXACT(C15,"sell"),EXACT(C15,"Sell")),-J15,J15) -> 36.479 | L15: =IF(EXACT(tICICIAshu[[#This Row],[Transaction Type]],"Initial Purchase Pre-Rejection"),0,IF(OR(EXACT(tICICIAshu[[#This Row],[Transaction Type]],"Redemption"),EXACT(tICICIAshu[[#This Row],[Transaction Type]],"Redeem"),EXACT(tICICIAshu[[#This Row],[Transaction Type]],"Switch Out"),EXACT(tICICIAshu[[#This Row],[Transaction Type]],"sell"),EXACT(tICICIAshu[[#This Row],[Transaction Type]],"Sell")),-tICICIAshu[[#This Row],[Amount]],tICICIAshu[[#This Row],[Amount]])) -> 5500 | M15: Executed
A16: 45857 | B16: 201645407 | C16: Purchase | D16: Kotak Mahindra Mutual Fund | E16: Kotak Contra Fund - Growth | F16: Kotak Contra Fund - Growth | G16: 8338255 | H16: 151.219 | I16: 5500 | J16: 36.369 | K16: =IF(OR(EXACT(C16,"Redemption"),EXACT(C16,"Redeem"),EXACT(C16,"Switch Out"),EXACT(C16,"sell"),EXACT(C16,"Sell")),-J16,J16) -> 36.369 | L16: =IF(EXACT(tICICIAshu[[#This Row],[Transaction Type]],"Initial Purchase Pre-Rejection"),0,IF(OR(EXACT(tICICIAshu[[#This Row],[Transaction Type]],"Redemption"),EXACT(tICICIAshu[[#This Row],[Transaction Type]],"Redeem"),EXACT(tICICIAshu[[#This Row],[Transaction Type]],"Switch Out"),EXACT(tICICIAshu[[#This Row],[Transaction Type]],"sell"),EXACT(tICICIAshu[[#This Row],[Transaction Type]],"Sell")),-tICICIAshu[[#This Row],[Amount]],tICICIAshu[[#This Row],[Amount]])) -> 5500 | M16: Executed
A17: 45827 | B17: 199473355 | C17: Purchase | D17: Kotak Mahindra Mutual Fund | E17: Kotak Contra Fund - Growth | F17: Kotak Contra Fund - Growth | G17: 8338255 | H17: 146.337 | I17: 5500 | J17: 37.583 | K17: =IF(OR(EXACT(C17,"Redemption"),EXACT(C17,"Redeem"),EXACT(C17,"Switch Out"),EXACT(C17,"sell"),EXACT(C17,"Sell")),-J17,J17) -> 37.583 | L17: =IF(EXACT(tICICIAshu[[#This Row],[Transaction Type]],"Initial Purchase Pre-Rejection"),0,IF(OR(EXACT(tICICIAshu[[#This Row],[Transaction Type]],"Redemption"),EXACT(tICICIAshu[[#This Row],[Transaction Type]],"Redeem"),EXACT(tICICIAshu[[#This Row],[Transaction Type]],"Switch Out"),EXACT(tICICIAshu[[#This Row],[Transaction Type]],"sell"),EXACT(tICICIAshu[[#This Row],[Transaction Type]],"Sell")),-tICICIAshu[[#This Row],[Amount]],tICICIAshu[[#This Row],[Amount]])) -> 5500 | M17: Executed
A18: 45796 | B18: 197361292 | C18: Purchase | D18: Kotak Mahindra Mutual Fund | E18: Kotak Contra Fund - Growth | F18: Kotak Contra Fund - Growth | G18: 8338255 | H18: 145.792 | I18: 5500 | J18: 37.723 | K18: =IF(OR(EXACT(C18,"Redemption"),EXACT(C18,"Redeem"),EXACT(C18,"Switch Out"),EXACT(C18,"sell"),EXACT(C18,"Sell")),-J18,J18) -> 37.723 | L18: =IF(EXACT(tICICIAshu[[#This Row],[Transaction Type]],"Initial Purchase Pre-Rejection"),0,IF(OR(EXACT(tICICIAshu[[#This Row],[Transaction Type]],"Redemption"),EXACT(tICICIAshu[[#This Row],[Transaction Type]],"Redeem"),EXACT(tICICIAshu[[#This Row],[Transaction Type]],"Switch Out"),EXACT(tICICIAshu[[#This Row],[Transaction Type]],"sell"),EXACT(tICICIAshu[[#This Row],[Transaction Type]],"Sell")),-tICICIAshu[[#This Row],[Amount]],tICICIAshu[[#This Row],[Amount]])) -> 5500 | M18: Executed
... A106: 38623 | B106: 991631 | C106: Purchase | D106: L&T Asset Management Company | E106: LNT Flexicap Fund-Regular Plan-Growth Option | F106: Lnt Flexicap Fund Regular Growth Option | G106: 248264/71 | H106: 13.765 | I106: 5000 | J106: 363.24 | K106: =IF(OR(EXACT(C106,"Redemption"),EXACT(C106,"Redeem"),EXACT(C106,"Switch Out"),EXACT(C106,"sell"),EXACT(C106,"Sell")),-J106,J106) -> 363.24 | L106: =IF(EXACT(tICICIAshu[[#This Row],[Transaction Type]],"Initial Purchase Pre-Rejection"),0,IF(OR(EXACT(tICICIAshu[[#This Row],[Transaction Type]],"Redemption"),EXACT(tICICIAshu[[#This Row],[Transaction Type]],"Redeem"),EXACT(tICICIAshu[[#This Row],[Transaction Type]],"Switch Out"),EXACT(tICICIAshu[[#This Row],[Transaction Type]],"sell"),EXACT(tICICIAshu[[#This Row],[Transaction Type]],"Sell")),-tICICIAshu[[#This Row],[Amount]],tICICIAshu[[#This Row],[Amount]])) -> 5000 | M106: Executed

Sheet Txn-Maniqm-Ashu
A1: Transactions — Maniqmala - Ashutosh
A2: 182 transactions • Add or delete rows freely — the Dashboard auto-recomputes via the Excel table named 'tManiqAshu'.
A4: Date | B4: Transaction ID | C4: Transaction Type | D4: Fund Name | E4: Scheme Name | F4: Display Scheme | G4: Folio No | H4: Last recorded NAV | I4: Amount | J4: Unit | K4: Signed Unit | L4: Signed Amount | M4: Status
A5: 44264 | B5: 283638899 | C5: SIP Purchase | D5: Aditya Birla | E5: Aditya Birla Sun Life Banking and Financial Services Fund Growth | F5: Aditya Birla Sun Life Banking And Financial Services Fund Growth | H5: 35.06 | I5: 2499.88 | J5: 71.303 | K5: =IF(OR(EXACT(C5,"Redemption"),EXACT(C5,"Redeem"),EXACT(C5,"Switch Out"),EXACT(C5,"sell"),EXACT(C5,"Sell")),-J5,J5) -> 71.303 | L5: =IF(EXACT(tManiqAshu[[#This Row],[Transaction Type]],"Initial Purchase Pre-Rejection"),0,IF(OR(EXACT(tManiqAshu[[#This Row],[Transaction Type]],"Redemption"),EXACT(tManiqAshu[[#This Row],[Transaction Type]],"Redeem"),EXACT(tManiqAshu[[#This Row],[Transaction Type]],"Switch Out"),EXACT(tManiqAshu[[#This Row],[Transaction Type]],"sell"),EXACT(tManiqAshu[[#This Row],[Transaction Type]],"Sell")),-tManiqAshu[[#This Row],[Amount]],tManiqAshu[[#This Row],[Amount]])) -> 2499.88 | M5: Executed
A6: 44264 | B6: EB77737044183SIN7522762 | C6: SIP Purchase | D6: Mirae Asset | E6: Mirae Asset Large and Mid Cap Fund Growth | F6: Mirae Asset Large And Mid Cap Fund Growth | H6: 79.871 | I6: 2499.88 | J6: 31.299 | K6: =IF(OR(EXACT(C6,"Redemption"),EXACT(C6,"Redeem"),EXACT(C6,"Switch Out"),EXACT(C6,"sell"),EXACT(C6,"Sell")),-J6,J6) -> 31.299 | L6: =IF(EXACT(tManiqAshu[[#This Row],[Transaction Type]],"Initial Purchase Pre-Rejection"),0,IF(OR(EXACT(tManiqAshu[[#This Row],[Transaction Type]],"Redemption"),EXACT(tManiqAshu[[#This Row],[Transaction Type]],"Redeem"),EXACT(tManiqAshu[[#This Row],[Transaction Type]],"Switch Out"),EXACT(tManiqAshu[[#This Row],[Transaction Type]],"sell"),EXACT(tManiqAshu[[#This Row],[Transaction Type]],"Sell")),-tManiqAshu[[#This Row],[Amount]],tManiqAshu[[#This Row],[Amount]])) -> 2499.88 | M6: Executed
A7: 44264 | B7: 4644276 | C7: SIP Purchase | D7: Mahindra Manulife | E7: Mahindra Manulife Focused Fund Growth | F7: Mahindra Manulife Focused Fund Growth | H7: 12.2365 | I7: 1999.9 | J7: 163.437 | K7: =IF(OR(EXACT(C7,"Redemption"),EXACT(C7,"Redeem"),EXACT(C7,"Switch Out"),EXACT(C7,"sell"),EXACT(C7,"Sell")),-J7,J7) -> 163.437 | L7: =IF(EXACT(tManiqAshu[[#This Row],[Transaction Type]],"Initial Purchase Pre-Rejection"),0,IF(OR(EXACT(tManiqAshu[[#This Row],[Transaction Type]],"Redemption"),EXACT(tManiqAshu[[#This Row],[Transaction Type]],"Redeem"),EXACT(tManiqAshu[[#This Row],[Transaction Type]],"Switch Out"),EXACT(tManiqAshu[[#This Row],[Transaction Type]],"sell"),EXACT(tManiqAshu[[#This Row],[Transaction Type]],"Sell")),-tManiqAshu[[#This Row],[Amount]],tManiqAshu[[#This Row],[Amount]])) -> 1999.9 | M7: Executed
A8: 44313 | B8: 4930170 | C8: SIP Purchase | D8: Mahindra Manulife | E8: Mahindra Manulife Focused Fund Growth | F8: Mahindra Manulife Focused Fund Growth | H8: 12.1898 | I8: 1999.9 | J8: 164.063 | K8: =IF(OR(EXACT(C8,"Redemption"),EXACT(C8,"Redeem"),EXACT(C8,"Switch Out"),EXACT(C8,"sell"),EXACT(C8,"Sell")),-J8,J8) -> 164.063 | L8: =IF(EXACT(tManiqAshu[[#This Row],[Transaction Type]],"Initial Purchase Pre-Rejection"),0,IF(OR(EXACT(tManiqAshu[[#This Row],[Transaction Type]],"Redemption"),EXACT(tManiqAshu[[#This Row],[Transaction Type]],"Redeem"),EXACT(tManiqAshu[[#This Row],[Transaction Type]],"Switch Out"),EXACT(tManiqAshu[[#This Row],[Transaction Type]],"sell"),EXACT(tManiqAshu[[#This Row],[Transaction Type]],"Sell")),-tManiqAshu[[#This Row],[Amount]],tManiqAshu[[#This Row],[Amount]])) -> 1999.9 | M8: Executed
A9: 44313 | B9: EB77737044183SIN8348808 | C9: SIP Purchase | D9: Mirae Asset | E9: Mirae Asset Large and Mid Cap Fund Growth | F9: Mirae Asset Large And Mid Cap Fund Growth | H9: 79.35 | I9: 2499.88 | J9: 31.504 | K9: =IF(OR(EXACT(C9,"Redemption"),EXACT(C9,"Redeem"),EXACT(C9,"Switch Out"),EXACT(C9,"sell"),EXACT(C9,"Sell")),-J9,J9) -> 31.504 | L9: =IF(EXACT(tManiqAshu[[#This Row],[Transaction Type]],"Initial Purchase Pre-Rejection"),0,IF(OR(EXACT(tManiqAshu[[#This Row],[Transaction Type]],"Redemption"),EXACT(tManiqAshu[[#This Row],[Transaction Type]],"Redeem"),EXACT(tManiqAshu[[#This Row],[Transaction Type]],"Switch Out"),EXACT(tManiqAshu[[#This Row],[Transaction Type]],"sell"),EXACT(tManiqAshu[[#This Row],[Transaction Type]],"Sell")),-tManiqAshu[[#This Row],[Amount]],tManiqAshu[[#This Row],[Amount]])) -> 2499.88 | M9: Executed
A10: 44313 | B10: 292266072 | C10: SIP Purchase | D10: Aditya Birla | E10: Aditya Birla Sun Life Banking and Financial Services Fund Growth | F10: Aditya Birla Sun Life Banking And Financial Services Fund Growth | H10: 32.75 | I10: 2499.88 | J10: 76.332 | K10: =IF(OR(EXACT(C10,"Redemption"),EXACT(C10,"Redeem"),EXACT(C10,"Switch Out"),EXACT(C10,"sell"),EXACT(C10,"Sell")),-J10,J10) -> 76.332 | L10: =IF(EXACT(tManiqAshu[[#This Row],[Transaction Type]],"Initial Purchase Pre-Rejection"),0,IF(OR(EXACT(tManiqAshu[[#This Row],[Transaction Type]],"Redemption"),EXACT(tManiqAshu[[#This Row],[Transaction Type]],"Redeem"),EXACT(tManiqAshu[[#This Row],[Transaction Type]],"Switch Out"),EXACT(tManiqAshu[[#This Row],[Transaction Type]],"sell"),EXACT(tManiqAshu[[#This Row],[Transaction Type]],"Sell")),-tManiqAshu[[#This Row],[Amount]],tManiqAshu[[#This Row],[Amount]])) -> 2499.88 | M10: Executed
A11: 44342 | B11: 5099056 | C11: SIP Purchase | D11: Mahindra Manulife | E11: Mahindra Manulife Focused Fund Growth | F11: Mahindra Manulife Focused Fund Growth | H11: 12.8726 | I11: 1999.9 | J11: 155.361 | K11: =IF(OR(EXACT(C11,"Redemption"),EXACT(C11,"Redeem"),EXACT(C11,"Switch Out"),EXACT(C11,"sell"),EXACT(C11,"Sell")),-J11,J11) -> 155.361 | L11: =IF(EXACT(tManiqAshu[[#This Row],[Transaction Type]],"Initial Purchase Pre-Rejection"),0,IF(OR(EXACT(tManiqAshu[[#This Row],[Transaction Type]],"Redemption"),EXACT(tManiqAshu[[#This Row],[Transaction Type]],"Redeem"),EXACT(tManiqAshu[[#This Row],[Transaction Type]],"Switch Out"),EXACT(tManiqAshu[[#This Row],[Transaction Type]],"sell"),EXACT(tManiqAshu[[#This Row],[Transaction Type]],"Sell")),-tManiqAshu[[#This Row],[Amount]],tManiqAshu[[#This Row],[Amount]])) -> 1999.9 | M11: Executed
A12: 44342 | B12: EB77737044183SIN8914241 | C12: SIP Purchase | D12: Mirae Asset | E12: Mirae Asset Large and Mid Cap Fund Growth | F12: Mirae Asset Large And Mid Cap Fund Growth | H12: 84.134 | I12: 2499.88 | J12: 29.713 | K12: =IF(OR(EXACT(C12,"Redemption"),EXACT(C12,"Redeem"),EXACT(C12,"Switch Out"),EXACT(C12,"sell"),EXACT(C12,"Sell")),-J12,J12) -> 29.713 | L12: =IF(EXACT(tManiqAshu[[#This Row],[Transaction Type]],"Initial Purchase Pre-Rejection"),0,IF(OR(EXACT(tManiqAshu[[#This Row],[Transaction Type]],"Redemption"),EXACT(tManiqAshu[[#This Row],[Transaction Type]],"Redeem"),EXACT(tManiqAshu[[#This Row],[Transaction Type]],"Switch Out"),EXACT(tManiqAshu[[#This Row],[Transaction Type]],"sell"),EXACT(tManiqAshu[[#This Row],[Transaction Type]],"Sell")),-tManiqAshu[[#This Row],[Amount]],tManiqAshu[[#This Row],[Amount]])) -> 2499.88 | M12: Executed
A13: 44342 | B13: 296957598 | C13: SIP Purchase | D13: Aditya Birla | E13: Aditya Birla Sun Life Banking and Financial Services Fund Growth | F13: Aditya Birla Sun Life Banking And Financial Services Fund Growth | H13: 35.36 | I13: 2499.88 | J13: 70.698 | K13: =IF(OR(EXACT(C13,"Redemption"),EXACT(C13,"Redeem"),EXACT(C13,"Switch Out"),EXACT(C13,"sell"),EXACT(C13,"Sell")),-J13,J13) -> 70.698 | L13: =IF(EXACT(tManiqAshu[[#This Row],[Transaction Type]],"Initial Purchase Pre-Rejection"),0,IF(OR(EXACT(tManiqAshu[[#This Row],[Transaction Type]],"Redemption"),EXACT(tManiqAshu[[#This Row],[Transaction Type]],"Redeem"),EXACT(tManiqAshu[[#This Row],[Transaction Type]],"Switch Out"),EXACT(tManiqAshu[[#This Row],[Transaction Type]],"sell"),EXACT(tManiqAshu[[#This Row],[Transaction Type]],"Sell")),-tManiqAshu[[#This Row],[Amount]],tManiqAshu[[#This Row],[Amount]])) -> 2499.88 | M13: Executed
A14: 44372 | B14: 302355017 | C14: SIP Purchase | D14: Aditya Birla | E14: Aditya Birla Sun Life Banking and Financial Services Fund Growth | F14: Aditya Birla Sun Life Banking And Financial Services Fund Growth | H14: 36.34 | I14: 2499.88 | J14: 68.791 | K14: =IF(OR(EXACT(C14,"Redemption"),EXACT(C14,"Redeem"),EXACT(C14,"Switch Out"),EXACT(C14,"sell"),EXACT(C14,"Sell")),-J14,J14) -> 68.791 | L14: =IF(EXACT(tManiqAshu[[#This Row],[Transaction Type]],"Initial Purchase Pre-Rejection"),0,IF(OR(EXACT(tManiqAshu[[#This Row],[Transaction Type]],"Redemption"),EXACT(tManiqAshu[[#This Row],[Transaction Type]],"Redeem"),EXACT(tManiqAshu[[#This Row],[Transaction Type]],"Switch Out"),EXACT(tManiqAshu[[#This Row],[Transaction Type]],"sell"),EXACT(tManiqAshu[[#This Row],[Transaction Type]],"Sell")),-tManiqAshu[[#This Row],[Amount]],tManiqAshu[[#This Row],[Amount]])) -> 2499.88 | M14: Executed
A15: 44372 | B15: 5302318 | C15: SIP Purchase | D15: Mahindra Manulife | E15: Mahindra Manulife Focused Fund Growth | F15: Mahindra Manulife Focused Fund Growth | H15: 13.5215 | I15: 1999.9 | J15: 147.905 | K15: =IF(OR(EXACT(C15,"Redemption"),EXACT(C15,"Redeem"),EXACT(C15,"Switch Out"),EXACT(C15,"sell"),EXACT(C15,"Sell")),-J15,J15) -> 147.905 | L15: =IF(EXACT(tManiqAshu[[#This Row],[Transaction Type]],"Initial Purchase Pre-Rejection"),0,IF(OR(EXACT(tManiqAshu[[#This Row],[Transaction Type]],"Redemption"),EXACT(tManiqAshu[[#This Row],[Transaction Type]],"Redeem"),EXACT(tManiqAshu[[#This Row],[Transaction Type]],"Switch Out"),EXACT(tManiqAshu[[#This Row],[Transaction Type]],"sell"),EXACT(tManiqAshu[[#This Row],[Transaction Type]],"Sell")),-tManiqAshu[[#This Row],[Amount]],tManiqAshu[[#This Row],[Amount]])) -> 1999.9 | M15: Executed
A16: 44372 | B16: EB77737044183SIN9552635 | C16: SIP Purchase | D16: Mirae Asset | E16: Mirae Asset Large and Mid Cap Fund Growth | F16: Mirae Asset Large And Mid Cap Fund Growth | H16: 87.8 | I16: 2499.88 | J16: 28.472 | K16: =IF(OR(EXACT(C16,"Redemption"),EXACT(C16,"Redeem"),EXACT(C16,"Switch Out"),EXACT(C16,"sell"),EXACT(C16,"Sell")),-J16,J16) -> 28.472 | L16: =IF(EXACT(tManiqAshu[[#This Row],[Transaction Type]],"Initial Purchase Pre-Rejection"),0,IF(OR(EXACT(tManiqAshu[[#This Row],[Transaction Type]],"Redemption"),EXACT(tManiqAshu[[#This Row],[Transaction Type]],"Redeem"),EXACT(tManiqAshu[[#This Row],[Transaction Type]],"Switch Out"),EXACT(tManiqAshu[[#This Row],[Transaction Type]],"sell"),EXACT(tManiqAshu[[#This Row],[Transaction Type]],"Sell")),-tManiqAshu[[#This Row],[Amount]],tManiqAshu[[#This Row],[Amount]])) -> 2499.88 | M16: Executed
... A186: 46106 | B186: 59021679 | C186: SIP Purchase | D186: Mahindra Manulife | E186: Mahindra Manulife Focused Fund Growth | F186: Mahindra Manulife Focused Fund Growth | H186: 25.4283 | I186: 1999.9 | J186: 78.649 | K186: =IF(OR(EXACT(C186,"Redemption"),EXACT(C186,"Redeem"),EXACT(C186,"Switch Out"),EXACT(C186,"sell"),EXACT(C186,"Sell")),-J186,J186) -> 78.649 | L186: =IF(EXACT(tManiqAshu[[#This Row],[Transaction Type]],"Initial Purchase Pre-Rejection"),0,IF(OR(EXACT(tManiqAshu[[#This Row],[Transaction Type]],"Redemption"),EXACT(tManiqAshu[[#This Row],[Transaction Type]],"Redeem"),EXACT(tManiqAshu[[#This Row],[Transaction Type]],"Switch Out"),EXACT(tManiqAshu[[#This Row],[Transaction Type]],"sell"),EXACT(tManiqAshu[[#This Row],[Transaction Type]],"Sell")),-tManiqAshu[[#This Row],[Amount]],tManiqAshu[[#This Row],[Amount]])) -> 1999.9 | M186: Executed
A187: 46139 | C187: SIP Purchase | D187: Mirae Asset | E187: Mirae Asset Large and Mid Cap Fund Growth | F187: Mirae Asset Large And Mid Cap Fund Growth | H187: 150.954 | I187: 2499.88 | J187: 16.561 | K187: =IF(OR(EXACT(C187,"Redemption"),EXACT(C187,"Redeem"),EXACT(C187,"Switch Out"),EXACT(C187,"sell"),EXACT(C187,"Sell")),-J187,J187) -> 16.561 | L187: =IF(EXACT(tManiqAshu[[#This Row],[Transaction Type]],"Initial Purchase Pre-Rejection"),0,IF(OR(EXACT(tManiqAshu[[#This Row],[Transaction Type]],"Redemption"),EXACT(tManiqAshu[[#This Row],[Transaction Type]],"Redeem"),EXACT(tManiqAshu[[#This Row],[Transaction Type]],"Switch Out"),EXACT(tManiqAshu[[#This Row],[Transaction Type]],"sell"),EXACT(tManiqAshu[[#This Row],[Transaction Type]],"Sell")),-tManiqAshu[[#This Row],[Amount]],tManiqAshu[[#This Row],[Amount]])) -> 2499.88 | M187: Executed
A188: 46139 | C188: SIP Purchase | D188: Aditya Birla | E188: Aditya Birla Sun Life Banking and Financial Services Fund Growth | F188: Aditya Birla Sun Life Banking And Financial Services Fund Growth | H188: 62.09 | I188: 2499.88 | J188: 40.262 | K188: =IF(OR(EXACT(C188,"Redemption"),EXACT(C188,"Redeem"),EXACT(C188,"Switch Out"),EXACT(C188,"sell"),EXACT(C188,"Sell")),-J188,J188) -> 40.262 | L188: =IF(EXACT(tManiqAshu[[#This Row],[Transaction Type]],"Initial Purchase Pre-Rejection"),0,IF(OR(EXACT(tManiqAshu[[#This Row],[Transaction Type]],"Redemption"),EXACT(tManiqAshu[[#This Row],[Transaction Type]],"Redeem"),EXACT(tManiqAshu[[#This Row],[Transaction Type]],"Switch Out"),EXACT(tManiqAshu[[#This Row],[Transaction Type]],"sell"),EXACT(tManiqAshu[[#This Row],[Transaction Type]],"Sell")),-tManiqAshu[[#This Row],[Amount]],tManiqAshu[[#This Row],[Amount]])) -> 2499.88 | M188: Executed
A189: 46139 | C189: SIP Purchase | D189: Mahindra Manulife | E189: Mahindra Manulife Focused Fund Growth | F189: Mahindra Manulife Focused Fund Growth | H189: 26.4888 | I189: 1999.9 | J189: 75.5 | K189: =IF(OR(EXACT(C189,"Redemption"),EXACT(C189,"Redeem"),EXACT(C189,"Switch Out"),EXACT(C189,"sell"),EXACT(C189,"Sell")),-J189,J189) -> 75.5 | L189: =IF(EXACT(tManiqAshu[[#This Row],[Transaction Type]],"Initial Purchase Pre-Rejection"),0,IF(OR(EXACT(tManiqAshu[[#This Row],[Transaction Type]],"Redemption"),EXACT(tManiqAshu[[#This Row],[Transaction Type]],"Redeem"),EXACT(tManiqAshu[[#This Row],[Transaction Type]],"Switch Out"),EXACT(tManiqAshu[[#This Row],[Transaction Type]],"sell"),EXACT(tManiqAshu[[#This Row],[Transaction Type]],"Sell")),-tManiqAshu[[#This Row],[Amount]],tManiqAshu[[#This Row],[Amount]])) -> 1999.9 | M189: Executed
A190: 46167 | C190: SIP Purchase | D190: Mirae Asset | E190: Mirae Asset Large and Mid Cap Fund Growth | F190: Mirae Asset Large And Mid Cap Fund Growth | H190: 153.108 | I190: 2499.88 | J190: 16.561 | K190: =IF(OR(EXACT(C190,"Redemption"),EXACT(C190,"Redeem"),EXACT(C190,"Switch Out"),EXACT(C190,"sell"),EXACT(C190,"Sell")),-J190,J190) -> 16.561 | L190: =IF(EXACT(tManiqAshu[[#This Row],[Transaction Type]],"Initial Purchase Pre-Rejection"),0,IF(OR(EXACT(tManiqAshu[[#This Row],[Transaction Type]],"Redemption"),EXACT(tManiqAshu[[#This Row],[Transaction Type]],"Redeem"),EXACT(tManiqAshu[[#This Row],[Transaction Type]],"Switch Out"),EXACT(tManiqAshu[[#This Row],[Transaction Type]],"sell"),EXACT(tManiqAshu[[#This Row],[Transaction Type]],"Sell")),-tManiqAshu[[#This Row],[Amount]],tManiqAshu[[#This Row],[Amount]])) -> 2499.88 | M190: Executed
A191: 46167 | C191: SIP Purchase | D191: Aditya Birla | E191: Aditya Birla Sun Life Banking and Financial Services Fund Growth | F191: Aditya Birla Sun Life Banking And Financial Services Fund Growth | H191: 61.34 | I191: 2499.88 | J191: 40.754 | K191: =IF(OR(EXACT(C191,"Redemption"),EXACT(C191,"Redeem"),EXACT(C191,"Switch Out"),EXACT(C191,"sell"),EXACT(C191,"Sell")),-J191,J191) -> 40.754 | L191: =IF(EXACT(tManiqAshu[[#This Row],[Transaction Type]],"Initial Purchase Pre-Rejection"),0,IF(OR(EXACT(tManiqAshu[[#This Row],[Transaction Type]],"Redemption"),EXACT(tManiqAshu[[#This Row],[Transaction Type]],"Redeem"),EXACT(tManiqAshu[[#This Row],[Transaction Type]],"Switch Out"),EXACT(tManiqAshu[[#This Row],[Transaction Type]],"sell"),EXACT(tManiqAshu[[#This Row],[Transaction Type]],"Sell")),-tManiqAshu[[#This Row],[Amount]],tManiqAshu[[#This Row],[Amount]])) -> 2499.88 | M191: Executed
A192: 46167 | C192: SIP Purchase | D192: Mahindra Manulife | E192: Mahindra Manulife Focused Fund Growth | F192: Mahindra Manulife Focused Fund Growth | H192: 26.9338 | I192: 1999.9 | J192: 74.252 | K192: =IF(OR(EXACT(C192,"Redemption"),EXACT(C192,"Redeem"),EXACT(C192,"Switch Out"),EXACT(C192,"sell"),EXACT(C192,"Sell")),-J192,J192) -> 74.252 | L192: =IF(EXACT(tManiqAshu[[#This Row],[Transaction Type]],"Initial Purchase Pre-Rejection"),0,IF(OR(EXACT(tManiqAshu[[#This Row],[Transaction Type]],"Redemption"),EXACT(tManiqAshu[[#This Row],[Transaction Type]],"Redeem"),EXACT(tManiqAshu[[#This Row],[Transaction Type]],"Switch Out"),EXACT(tManiqAshu[[#This Row],[Transaction Type]],"sell"),EXACT(tManiqAshu[[#This Row],[Transaction Type]],"Sell")),-tManiqAshu[[#This Row],[Amount]],tManiqAshu[[#This Row],[Amount]])) -> 1999.9 | M192: Executed
A193: 46198 | C193: SIP Purchase | D193: Mirae Asset | E193: Mirae Asset Large and Mid Cap Fund Growth | F193: Mirae Asset Large And Mid Cap Fund Growth | H193: 154.526 | I193: 2499.88 | J193: 16.178 | K193: =IF(OR(EXACT(C193,"Redemption"),EXACT(C193,"Redeem"),EXACT(C193,"Switch Out"),EXACT(C193,"sell"),EXACT(C193,"Sell")),-J193,J193) -> 16.178 | L193: =IF(EXACT(tManiqAshu[[#This Row],[Transaction Type]],"Initial Purchase Pre-Rejection"),0,IF(OR(EXACT(tManiqAshu[[#This Row],[Transaction Type]],"Redemption"),EXACT(tManiqAshu[[#This Row],[Transaction Type]],"Redeem"),EXACT(tManiqAshu[[#This Row],[Transaction Type]],"Switch Out"),EXACT(tManiqAshu[[#This Row],[Transaction Type]],"sell"),EXACT(tManiqAshu[[#This Row],[Transaction Type]],"Sell")),-tManiqAshu[[#This Row],[Amount]],tManiqAshu[[#This Row],[Amount]])) -> 2499.88 | M193: Executed
A194: 46198 | C194: SIP Purchase | D194: Aditya Birla | E194: Aditya Birla Sun Life Banking and Financial Services Fund Growth | F194: Aditya Birla Sun Life Banking And Financial Services Fund Growth | H194: 63.59 | I194: 2499.88 | J194: 39.312 | K194: =IF(OR(EXACT(C194,"Redemption"),EXACT(C194,"Redeem"),EXACT(C194,"Switch Out"),EXACT(C194,"sell"),EXACT(C194,"Sell")),-J194,J194) -> 39.312 | L194: =IF(EXACT(tManiqAshu[[#This Row],[Transaction Type]],"Initial Purchase Pre-Rejection"),0,IF(OR(EXACT(tManiqAshu[[#This Row],[Transaction Type]],"Redemption"),EXACT(tManiqAshu[[#This Row],[Transaction Type]],"Redeem"),EXACT(tManiqAshu[[#This Row],[Transaction Type]],"Switch Out"),EXACT(tManiqAshu[[#This Row],[Transaction Type]],"sell"),EXACT(tManiqAshu[[#This Row],[Transaction Type]],"Sell")),-tManiqAshu[[#This Row],[Amount]],tManiqAshu[[#This Row],[Amount]])) -> 2499.88 | M194: Executed
A195: 46198 | C195: SIP Purchase | D195: Mahindra Manulife | E195: Mahindra Manulife Focused Fund Growth | F195: Mahindra Manulife Focused Fund Growth | H195: 26.9523 | I195: 1999.9 | J195: 74.201 | K195: =IF(OR(EXACT(C195,"Redemption"),EXACT(C195,"Redeem"),EXACT(C195,"Switch Out"),EXACT(C195,"sell"),EXACT(C195,"Sell")),-J195,J195) -> 74.201 | L195: =IF(EXACT(tManiqAshu[[#This Row],[Transaction Type]],"Initial Purchase Pre-Rejection"),0,IF(OR(EXACT(tManiqAshu[[#This Row],[Transaction Type]],"Redemption"),EXACT(tManiqAshu[[#This Row],[Transaction Type]],"Redeem"),EXACT(tManiqAshu[[#This Row],[Transaction Type]],"Switch Out"),EXACT(tManiqAshu[[#This Row],[Transaction Type]],"sell"),EXACT(tManiqAshu[[#This Row],[Transaction Type]],"Sell")),-tManiqAshu[[#This Row],[Amount]],tManiqAshu[[#This Row],[Amount]])) -> 1999.9 | M195: Executed

Sheet Txn-Maniqm-Hars
A1: Transactions — Maniqmala - Harsha
A2: 301 transactions • Add or delete rows freely — the Dashboard auto-recomputes via the Excel table named 'tManiqHars'.
A4: Date | B4: Transaction ID | C4: Transaction Type | D4: Fund Name | E4: Scheme Name | F4: Display Scheme | G4: Folio No | H4: Last recorded NAV | I4: Amount | J4: Unit | K4: Signed Unit | L4: Signed Amount | M4: Status
A5: 46049 | B5: EB77737362992SIN61556445 | C5: SIP Purchase | D5: Mirae Asset | E5: Mirae Asset Large and Mid Cap Fund Growth | F5: Mirae Asset Large And Mid Cap Fund Growth | H5: 150.007 | I5: 2499.88 | J5: 16.665 | K5: =IF(OR(EXACT(C5,"Redemption"),EXACT(C5,"Redeem"),EXACT(C5,"Switch Out"),EXACT(C5,"sell"),EXACT(C5,"Sell")),-J5,J5) -> 16.665 | L5: =IF(EXACT(tManiqHars[[#This Row],[Transaction Type]],"Initial Purchase Pre-Rejection"),0,IF(OR(EXACT(tManiqHars[[#This Row],[Transaction Type]],"Redemption"),EXACT(tManiqHars[[#This Row],[Transaction Type]],"Redeem"),EXACT(tManiqHars[[#This Row],[Transaction Type]],"Switch Out"),EXACT(tManiqHars[[#This Row],[Transaction Type]],"sell"),EXACT(tManiqHars[[#This Row],[Transaction Type]],"Sell")),-tManiqHars[[#This Row],[Amount]],tManiqHars[[#This Row],[Amount]])) -> 2499.88 | M5: Executed
A6: 46049 | B6: 1349215618 | C6: SIP Purchase | D6: Sbi Small | E6: SBI Small Cap Fund Growth | F6: Sbi Small Cap Fund Growth | H6: 156.2208 | I6: 2499.88 | J6: 16.002 | K6: =IF(OR(EXACT(C6,"Redemption"),EXACT(C6,"Redeem"),EXACT(C6,"Switch Out"),EXACT(C6,"sell"),EXACT(C6,"Sell")),-J6,J6) -> 16.002 | L6: =IF(EXACT(tManiqHars[[#This Row],[Transaction Type]],"Initial Purchase Pre-Rejection"),0,IF(OR(EXACT(tManiqHars[[#This Row],[Transaction Type]],"Redemption"),EXACT(tManiqHars[[#This Row],[Transaction Type]],"Redeem"),EXACT(tManiqHars[[#This Row],[Transaction Type]],"Switch Out"),EXACT(tManiqHars[[#This Row],[Transaction Type]],"sell"),EXACT(tManiqHars[[#This Row],[Transaction Type]],"Sell")),-tManiqHars[[#This Row],[Amount]],tManiqHars[[#This Row],[Amount]])) -> 2499.88 | M6: Executed
A7: 46049 | B7: EQ17725810101SIN39210888 | C7: SIP Purchase | D7: Canara Robeco | E7: Canara Robeco Large and Mid Cap Fund Growth | F7: Canara Robeco Large And Mid Cap Fund Growth | H7: 239.2 | I7: 2499.88 | J7: 10.451 | K7: =IF(OR(EXACT(C7,"Redemption"),EXACT(C7,"Redeem"),EXACT(C7,"Switch Out"),EXACT(C7,"sell"),EXACT(C7,"Sell")),-J7,J7) -> 10.451 | L7: =IF(EXACT(tManiqHars[[#This Row],[Transaction Type]],"Initial Purchase Pre-Rejection"),0,IF(OR(EXACT(tManiqHars[[#This Row],[Transaction Type]],"Redemption"),EXACT(tManiqHars[[#This Row],[Transaction Type]],"Redeem"),EXACT(tManiqHars[[#This Row],[Transaction Type]],"Switch Out"),EXACT(tManiqHars[[#This Row],[Transaction Type]],"sell"),EXACT(tManiqHars[[#This Row],[Transaction Type]],"Sell")),-tManiqHars[[#This Row],[Amount]],tManiqHars[[#This Row],[Amount]])) -> 2499.88 | M7: Executed
A8: 46049 | B8: 1454705404 | C8: SIP Purchase | D8: Icici Prudential | E8: ICICI Prudential Focused Equity Fund Growth | F8: Icici Prudential Focused Equity Fund Growth | H8: 94.11 | I8: 2499.88 | J8: 26.563 | K8: =IF(OR(EXACT(C8,"Redemption"),EXACT(C8,"Redeem"),EXACT(C8,"Switch Out"),EXACT(C8,"sell"),EXACT(C8,"Sell")),-J8,J8) -> 26.563 | L8: =IF(EXACT(tManiqHars[[#This Row],[Transaction Type]],"Initial Purchase Pre-Rejection"),0,IF(OR(EXACT(tManiqHars[[#This Row],[Transaction Type]],"Redemption"),EXACT(tManiqHars[[#This Row],[Transaction Type]],"Redeem"),EXACT(tManiqHars[[#This Row],[Transaction Type]],"Switch Out"),EXACT(tManiqHars[[#This Row],[Transaction Type]],"sell"),EXACT(tManiqHars[[#This Row],[Transaction Type]],"Sell")),-tManiqHars[[#This Row],[Amount]],tManiqHars[[#This Row],[Amount]])) -> 2499.88 | M8: Executed
A9: 46017 | B9: EQ17725810101SIN38487214 | C9: SIP Purchase | D9: Canara Robeco | E9: Canara Robeco Large and Mid Cap Fund Growth | F9: Canara Robeco Large And Mid Cap Fund Growth | H9: 253.36 | I9: 2499.88 | J9: 9.867 | K9: =IF(OR(EXACT(C9,"Redemption"),EXACT(C9,"Redeem"),EXACT(C9,"Switch Out"),EXACT(C9,"sell"),EXACT(C9,"Sell")),-J9,J9) -> 9.867 | L9: =IF(EXACT(tManiqHars[[#This Row],[Transaction Type]],"Initial Purchase Pre-Rejection"),0,IF(OR(EXACT(tManiqHars[[#This Row],[Transaction Type]],"Redemption"),EXACT(tManiqHars[[#This Row],[Transaction Type]],"Redeem"),EXACT(tManiqHars[[#This Row],[Transaction Type]],"Switch Out"),EXACT(tManiqHars[[#This Row],[Transaction Type]],"sell"),EXACT(tManiqHars[[#This Row],[Transaction Type]],"Sell")),-tManiqHars[[#This Row],[Amount]],tManiqHars[[#This Row],[Amount]])) -> 2499.88 | M9: Executed
A10: 46017 | B10: 1429710817 | C10: SIP Purchase | D10: Icici Prudential | E10: ICICI Prudential Focused Equity Fund Growth | F10: Icici Prudential Focused Equity Fund Growth | H10: 97.77 | I10: 2499.88 | J10: 25.569 | K10: =IF(OR(EXACT(C10,"Redemption"),EXACT(C10,"Redeem"),EXACT(C10,"Switch Out"),EXACT(C10,"sell"),EXACT(C10,"Sell")),-J10,J10) -> 25.569 | L10: =IF(EXACT(tManiqHars[[#This Row],[Transaction Type]],"Initial Purchase Pre-Rejection"),0,IF(OR(EXACT(tManiqHars[[#This Row],[Transaction Type]],"Redemption"),EXACT(tManiqHars[[#This Row],[Transaction Type]],"Redeem"),EXACT(tManiqHars[[#This Row],[Transaction Type]],"Switch Out"),EXACT(tManiqHars[[#This Row],[Transaction Type]],"sell"),EXACT(tManiqHars[[#This Row],[Transaction Type]],"Sell")),-tManiqHars[[#This Row],[Amount]],tManiqHars[[#This Row],[Amount]])) -> 2499.88 | M10: Executed
A11: 46017 | B11: EB77737362992SIN60618952 | C11: SIP Purchase | D11: Mirae Asset | E11: Mirae Asset Large and Mid Cap Fund Growth | F11: Mirae Asset Large And Mid Cap Fund Growth | H11: 156.962 | I11: 2499.88 | J11: 15.927 | K11: =IF(OR(EXACT(C11,"Redemption"),EXACT(C11,"Redeem"),EXACT(C11,"Switch Out"),EXACT(C11,"sell"),EXACT(C11,"Sell")),-J11,J11) -> 15.927 | L11: =IF(EXACT(tManiqHars[[#This Row],[Transaction Type]],"Initial Purchase Pre-Rejection"),0,IF(OR(EXACT(tManiqHars[[#This Row],[Transaction Type]],"Redemption"),EXACT(tManiqHars[[#This Row],[Transaction Type]],"Redeem"),EXACT(tManiqHars[[#This Row],[Transaction Type]],"Switch Out"),EXACT(tManiqHars[[#This Row],[Transaction Type]],"sell"),EXACT(tManiqHars[[#This Row],[Transaction Type]],"Sell")),-tManiqHars[[#This Row],[Amount]],tManiqHars[[#This Row],[Amount]])) -> 2499.88 | M11: Executed
A12: 46017 | B12: 1324799666 | C12: SIP Purchase | D12: Sbi Small | E12: SBI Small Cap Fund Growth | F12: Sbi Small Cap Fund Growth | H12: 167.6867 | I12: 2499.88 | J12: 14.908 | K12: =IF(OR(EXACT(C12,"Redemption"),EXACT(C12,"Redeem"),EXACT(C12,"Switch Out"),EXACT(C12,"sell"),EXACT(C12,"Sell")),-J12,J12) -> 14.908 | L12: =IF(EXACT(tManiqHars[[#This Row],[Transaction Type]],"Initial Purchase Pre-Rejection"),0,IF(OR(EXACT(tManiqHars[[#This Row],[Transaction Type]],"Redemption"),EXACT(tManiqHars[[#This Row],[Transaction Type]],"Redeem"),EXACT(tManiqHars[[#This Row],[Transaction Type]],"Switch Out"),EXACT(tManiqHars[[#This Row],[Transaction Type]],"sell"),EXACT(tManiqHars[[#This Row],[Transaction Type]],"Sell")),-tManiqHars[[#This Row],[Amount]],tManiqHars[[#This Row],[Amount]])) -> 2499.88 | M12: Executed
A13: 45986 | B13: EB77737362992SIN59666749 | C13: SIP Purchase | D13: Mirae Asset | E13: Mirae Asset Large and Mid Cap Fund Growth | F13: Mirae Asset Large And Mid Cap Fund Growth | H13: 156.031 | I13: 2499.88 | J13: 16.022 | K13: =IF(OR(EXACT(C13,"Redemption"),EXACT(C13,"Redeem"),EXACT(C13,"Switch Out"),EXACT(C13,"sell"),EXACT(C13,"Sell")),-J13,J13) -> 16.022 | L13: =IF(EXACT(tManiqHars[[#This Row],[Transaction Type]],"Initial Purchase Pre-Rejection"),0,IF(OR(EXACT(tManiqHars[[#This Row],[Transaction Type]],"Redemption"),EXACT(tManiqHars[[#This Row],[Transaction Type]],"Redeem"),EXACT(tManiqHars[[#This Row],[Transaction Type]],"Switch Out"),EXACT(tManiqHars[[#This Row],[Transaction Type]],"sell"),EXACT(tManiqHars[[#This Row],[Transaction Type]],"Sell")),-tManiqHars[[#This Row],[Amount]],tManiqHars[[#This Row],[Amount]])) -> 2499.88 | M13: Executed
A14: 45986 | B14: 1404072054 | C14: SIP Purchase | D14: Icici Prudential | E14: ICICI Prudential Focused Equity Fund Growth | F14: Icici Prudential Focused Equity Fund Growth | H14: 96.35 | I14: 2499.88 | J14: 25.946 | K14: =IF(OR(EXACT(C14,"Redemption"),EXACT(C14,"Redeem"),EXACT(C14,"Switch Out"),EXACT(C14,"sell"),EXACT(C14,"Sell")),-J14,J14) -> 25.946 | L14: =IF(EXACT(tManiqHars[[#This Row],[Transaction Type]],"Initial Purchase Pre-Rejection"),0,IF(OR(EXACT(tManiqHars[[#This Row],[Transaction Type]],"Redemption"),EXACT(tManiqHars[[#This Row],[Transaction Type]],"Redeem"),EXACT(tManiqHars[[#This Row],[Transaction Type]],"Switch Out"),EXACT(tManiqHars[[#This Row],[Transaction Type]],"sell"),EXACT(tManiqHars[[#This Row],[Transaction Type]],"Sell")),-tManiqHars[[#This Row],[Amount]],tManiqHars[[#This Row],[Amount]])) -> 2499.88 | M14: Executed
A15: 45986 | B15: EQ17725810101SIN37814827 | C15: SIP Purchase | D15: Canara Robeco | E15: Canara Robeco Large and Mid Cap Fund Growth | F15: Canara Robeco Large And Mid Cap Fund Growth | H15: 256.05 | I15: 2499.88 | J15: 9.763 | K15: =IF(OR(EXACT(C15,"Redemption"),EXACT(C15,"Redeem"),EXACT(C15,"Switch Out"),EXACT(C15,"sell"),EXACT(C15,"Sell")),-J15,J15) -> 9.763 | L15: =IF(EXACT(tManiqHars[[#This Row],[Transaction Type]],"Initial Purchase Pre-Rejection"),0,IF(OR(EXACT(tManiqHars[[#This Row],[Transaction Type]],"Redemption"),EXACT(tManiqHars[[#This Row],[Transaction Type]],"Redeem"),EXACT(tManiqHars[[#This Row],[Transaction Type]],"Switch Out"),EXACT(tManiqHars[[#This Row],[Transaction Type]],"sell"),EXACT(tManiqHars[[#This Row],[Transaction Type]],"Sell")),-tManiqHars[[#This Row],[Amount]],tManiqHars[[#This Row],[Amount]])) -> 2499.88 | M15: Executed
A16: 45986 | B16: 1300545794 | C16: SIP Purchase | D16: Sbi Small | E16: SBI Small Cap Fund Growth | F16: Sbi Small Cap Fund Growth | H16: 169.2102 | I16: 2499.88 | J16: 14.774 | K16: =IF(OR(EXACT(C16,"Redemption"),EXACT(C16,"Redeem"),EXACT(C16,"Switch Out"),EXACT(C16,"sell"),EXACT(C16,"Sell")),-J16,J16) -> 14.774 | L16: =IF(EXACT(tManiqHars[[#This Row],[Transaction Type]],"Initial Purchase Pre-Rejection"),0,IF(OR(EXACT(tManiqHars[[#This Row],[Transaction Type]],"Redemption"),EXACT(tManiqHars[[#This Row],[Transaction Type]],"Redeem"),EXACT(tManiqHars[[#This Row],[Transaction Type]],"Switch Out"),EXACT(tManiqHars[[#This Row],[Transaction Type]],"sell"),EXACT(tManiqHars[[#This Row],[Transaction Type]],"Sell")),-tManiqHars[[#This Row],[Amount]],tManiqHars[[#This Row],[Amount]])) -> 2499.88 | M16: Executed
... A270: 44433 | B270: 387629842 | C270: SIP Purchase | D270: Sbi Small | E270: SBI Small Cap Fund Growth | F270: Sbi Small Cap Fund Growth | H270: 92.1878 | I270: 2499.88 | J270: 27.117 | K270: =IF(OR(EXACT(C270,"Redemption"),EXACT(C270,"Redeem"),EXACT(C270,"Switch Out"),EXACT(C270,"sell"),EXACT(C270,"Sell")),-J270,J270) -> 27.117 | L270: =IF(EXACT(tManiqHars[[#This Row],[Transaction Type]],"Initial Purchase Pre-Rejection"),0,IF(OR(EXACT(tManiqHars[[#This Row],[Transaction Type]],"Redemption"),EXACT(tManiqHars[[#This Row],[Transaction Type]],"Redeem"),EXACT(tManiqHars[[#This Row],[Transaction Type]],"Switch Out"),EXACT(tManiqHars[[#This Row],[Transaction Type]],"sell"),EXACT(tManiqHars[[#This Row],[Transaction Type]],"Sell")),-tManiqHars[[#This Row],[Amount]],tManiqHars[[#This Row],[Amount]])) -> 2499.88 | M270: Executed
A271: 44424 | B271: EY577339161541IPOD3573721 | C271: Initial Purchase Pre-Rejection | D271: Uti Focused | E271: UTI Focused Fund Growth | F271: Uti Focused Fund Growth | I271: 500000 | J271: 0 | K271: =IF(OR(EXACT(C271,"Redemption"),EXACT(C271,"Redeem"),EXACT(C271,"Switch Out"),EXACT(C271,"sell"),EXACT(C271,"Sell")),-J271,J271) -> 0 | L271: =IF(EXACT(tManiqHars[[#This Row],[Transaction Type]],"Initial Purchase Pre-Rejection"),0,IF(OR(EXACT(tManiqHars[[#This Row],[Transaction Type]],"Redemption"),EXACT(tManiqHars[[#This Row],[Transaction Type]],"Redeem"),EXACT(tManiqHars[[#This Row],[Transaction Type]],"Switch Out"),EXACT(tManiqHars[[#This Row],[Transaction Type]],"sell"),EXACT(tManiqHars[[#This Row],[Transaction Type]],"Sell")),-tManiqHars[[#This Row],[Amount]],tManiqHars[[#This Row],[Amount]])) -> 0 | M271: Executed
A272: 44418 | B272: 367453379 | C272: SIP Purchase | D272: Icici Prudential | E272: ICICI Prudential Value Fund Growth | F272: Icici Prudential Value Fund Growth | H272: 224.38 | I272: 4999.75 | J272: 22.283 | K272: =IF(OR(EXACT(C272,"Redemption"),EXACT(C272,"Redeem"),EXACT(C272,"Switch Out"),EXACT(C272,"sell"),EXACT(C272,"Sell")),-J272,J272) -> 22.283 | L272: =IF(EXACT(tManiqHars[[#This Row],[Transaction Type]],"Initial Purchase Pre-Rejection"),0,IF(OR(EXACT(tManiqHars[[#This Row],[Transaction Type]],"Redemption"),EXACT(tManiqHars[[#This Row],[Transaction Type]],"Redeem"),EXACT(tManiqHars[[#This Row],[Transaction Type]],"Switch Out"),EXACT(tManiqHars[[#This Row],[Transaction Type]],"sell"),EXACT(tManiqHars[[#This Row],[Transaction Type]],"Sell")),-tManiqHars[[#This Row],[Amount]],tManiqHars[[#This Row],[Amount]])) -> 4999.75 | M272: Executed
A273: 44418 | B273: 310984318 | C273: SIP Purchase | D273: Aditya Birla | E273: Aditya Birla Sun Life Value Fund Growth | F273: Aditya Birla Sun Life Value Fund Growth | H273: 69.5353 | I273: 4999.75 | J273: 71.902 | K273: =IF(OR(EXACT(C273,"Redemption"),EXACT(C273,"Redeem"),EXACT(C273,"Switch Out"),EXACT(C273,"sell"),EXACT(C273,"Sell")),-J273,J273) -> 71.902 | L273: =IF(EXACT(tManiqHars[[#This Row],[Transaction Type]],"Initial Purchase Pre-Rejection"),0,IF(OR(EXACT(tManiqHars[[#This Row],[Transaction Type]],"Redemption"),EXACT(tManiqHars[[#This Row],[Transaction Type]],"Redeem"),EXACT(tManiqHars[[#This Row],[Transaction Type]],"Switch Out"),EXACT(tManiqHars[[#This Row],[Transaction Type]],"sell"),EXACT(tManiqHars[[#This Row],[Transaction Type]],"Sell")),-tManiqHars[[#This Row],[Amount]],tManiqHars[[#This Row],[Amount]])) -> 4999.75 | M273: Executed
A274: 44418 | B274: 5658374 | C274: SIP Purchase | D274: Mahindra Manulife | E274: Mahindra Manulife Mid Cap Fund Growth | F274: Mahindra Manulife Mid Cap Fund Growth | H274: 16.0583 | I274: 4999.75 | J274: 311.35 | K274: =IF(OR(EXACT(C274,"Redemption"),EXACT(C274,"Redeem"),EXACT(C274,"Switch Out"),EXACT(C274,"sell"),EXACT(C274,"Sell")),-J274,J274) -> 311.35 | L274: =IF(EXACT(tManiqHars[[#This Row],[Transaction Type]],"Initial Purchase Pre-Rejection"),0,IF(OR(EXACT(tManiqHars[[#This Row],[Transaction Type]],"Redemption"),EXACT(tManiqHars[[#This Row],[Transaction Type]],"Redeem"),EXACT(tManiqHars[[#This Row],[Transaction Type]],"Switch Out"),EXACT(tManiqHars[[#This Row],[Transaction Type]],"sell"),EXACT(tManiqHars[[#This Row],[Transaction Type]],"Sell")),-tManiqHars[[#This Row],[Amount]],tManiqHars[[#This Row],[Amount]])) -> 4999.75 | M274: Executed
A275: 44418 | B275: EQ17728054215SIN3181741 | C275: SIP Purchase | D275: Canara Robeco | E275: Canara Robeco Large and Mid Cap Fund Growth | F275: Canara Robeco Large And Mid Cap Fund Growth | H275: 151.26 | I275: 4999.75 | J275: 33.054 | K275: =IF(OR(EXACT(C275,"Redemption"),EXACT(C275,"Redeem"),EXACT(C275,"Switch Out"),EXACT(C275,"sell"),EXACT(C275,"Sell")),-J275,J275) -> 33.054 | L275: =IF(EXACT(tManiqHars[[#This Row],[Transaction Type]],"Initial Purchase Pre-Rejection"),0,IF(OR(EXACT(tManiqHars[[#This Row],[Transaction Type]],"Redemption"),EXACT(tManiqHars[[#This Row],[Transaction Type]],"Redeem"),EXACT(tManiqHars[[#This Row],[Transaction Type]],"Switch Out"),EXACT(tManiqHars[[#This Row],[Transaction Type]],"sell"),EXACT(tManiqHars[[#This Row],[Transaction Type]],"Sell")),-tManiqHars[[#This Row],[Amount]],tManiqHars[[#This Row],[Amount]])) -> 4999.75 | M275: Executed
A276: 44403 | B276: 362578893 | C276: SIP Purchase | D276: Icici Prudential | E276: ICICI Prudential Focused Equity Fund Growth | F276: Icici Prudential Focused Equity Fund Growth | H276: 44.63 | I276: 2499.88 | J276: 56.013 | K276: =IF(OR(EXACT(C276,"Redemption"),EXACT(C276,"Redeem"),EXACT(C276,"Switch Out"),EXACT(C276,"sell"),EXACT(C276,"Sell")),-J276,J276) -> 56.013 | L276: =IF(EXACT(tManiqHars[[#This Row],[Transaction Type]],"Initial Purchase Pre-Rejection"),0,IF(OR(EXACT(tManiqHars[[#This Row],[Transaction Type]],"Redemption"),EXACT(tManiqHars[[#This Row],[Transaction Type]],"Redeem"),EXACT(tManiqHars[[#This Row],[Transaction Type]],"Switch Out"),EXACT(tManiqHars[[#This Row],[Transaction Type]],"sell"),EXACT(tManiqHars[[#This Row],[Transaction Type]],"Sell")),-tManiqHars[[#This Row],[Amount]],tManiqHars[[#This Row],[Amount]])) -> 2499.88 | M276: Executed
A277: 44403 | B277: EQ17725810101SIN3024185 | C277: SIP Purchase | D277: Canara Robeco | E277: Canara Robeco Large and Mid Cap Fund Growth | F277: Canara Robeco Large And Mid Cap Fund Growth | H277: 149.65 | I277: 2499.88 | J277: 16.705 | K277: =IF(OR(EXACT(C277,"Redemption"),EXACT(C277,"Redeem"),EXACT(C277,"Switch Out"),EXACT(C277,"sell"),EXACT(C277,"Sell")),-J277,J277) -> 16.705 | L277: =IF(EXACT(tManiqHars[[#This Row],[Transaction Type]],"Initial Purchase Pre-Rejection"),0,IF(OR(EXACT(tManiqHars[[#This Row],[Transaction Type]],"Redemption"),EXACT(tManiqHars[[#This Row],[Transaction Type]],"Redeem"),EXACT(tManiqHars[[#This Row],[Transaction Type]],"Switch Out"),EXACT(tManiqHars[[#This Row],[Transaction Type]],"sell"),EXACT(tManiqHars[[#This Row],[Transaction Type]],"Sell")),-tManiqHars[[#This Row],[Amount]],tManiqHars[[#This Row],[Amount]])) -> 2499.88 | M277: Executed
A278: 44403 | B278: EB77737362992SIN10205153 | C278: SIP Purchase | D278: Mirae Asset | E278: Mirae Asset Large and Mid Cap Fund Growth | F278: Mirae Asset Large And Mid Cap Fund Growth | H278: 90.323 | I278: 2499.88 | J278: 27.677 | K278: =IF(OR(EXACT(C278,"Redemption"),EXACT(C278,"Redeem"),EXACT(C278,"Switch Out"),EXACT(C278,"sell"),EXACT(C278,"Sell")),-J278,J278) -> 27.677 | L278: =IF(EXACT(tManiqHars[[#This Row],[Transaction Type]],"Initial Purchase Pre-Rejection"),0,IF(OR(EXACT(tManiqHars[[#This Row],[Transaction Type]],"Redemption"),EXACT(tManiqHars[[#This Row],[Transaction Type]],"Redeem"),EXACT(tManiqHars[[#This Row],[Transaction Type]],"Switch Out"),EXACT(tManiqHars[[#This Row],[Transaction Type]],"sell"),EXACT(tManiqHars[[#This Row],[Transaction Type]],"Sell")),-tManiqHars[[#This Row],[Amount]],tManiqHars[[#This Row],[Amount]])) -> 2499.88 | M278: Executed
A279: 44403 | B279: 377436785 | C279: SIP Purchase | D279: Sbi Small | E279: SBI Small Cap Fund Growth | F279: Sbi Small Cap Fund Growth | H279: 94.877 | I279: 2499.88 | J279: 26.349 | K279: =IF(OR(EXACT(C279,"Redemption"),EXACT(C279,"Redeem"),EXACT(C279,"Switch Out"),EXACT(C279,"sell"),EXACT(C279,"Sell")),-J279,J279) -> 26.349 | L279: =IF(EXACT(tManiqHars[[#This Row],[Transaction Type]],"Initial Purchase Pre-Rejection"),0,IF(OR(EXACT(tManiqHars[[#This Row],[Transaction Type]],"Redemption"),EXACT(tManiqHars[[#This Row],[Transaction Type]],"Redeem"),EXACT(tManiqHars[[#This Row],[Transaction Type]],"Switch Out"),EXACT(tManiqHars[[#This Row],[Transaction Type]],"sell"),EXACT(tManiqHars[[#This Row],[Transaction Type]],"Sell")),-tManiqHars[[#This Row],[Amount]],tManiqHars[[#This Row],[Amount]])) -> 2499.88 | M279: Executed
A280: 44389 | B280: EQ17728054215SIN2898410 | C280: SIP Purchase | D280: Canara Robeco | E280: Canara Robeco Large and Mid Cap Fund Growth | F280: Canara Robeco Large And Mid Cap Fund Growth | H280: 147.05 | I280: 4999.75 | J280: 34 | K280: =IF(OR(EXACT(C280,"Redemption"),EXACT(C280,"Redeem"),EXACT(C280,"Switch Out"),EXACT(C280,"sell"),EXACT(C280,"Sell")),-J280,J280) -> 34 | L280: =IF(EXACT(tManiqHars[[#This Row],[Transaction Type]],"Initial Purchase Pre-Rejection"),0,IF(OR(EXACT(tManiqHars[[#This Row],[Transaction Type]],"Redemption"),EXACT(tManiqHars[[#This Row],[Transaction Type]],"Redeem"),EXACT(tManiqHars[[#This Row],[Transaction Type]],"Switch Out"),EXACT(tManiqHars[[#This Row],[Transaction Type]],"sell"),EXACT(tManiqHars[[#This Row],[Transaction Type]],"Sell")),-tManiqHars[[#This Row],[Amount]],tManiqHars[[#This Row],[Amount]])) -> 4999.75 | M280: Executed
A281: 44389 | B281: 5420700 | C281: SIP Purchase | D281: Mahindra Manulife | E281: Mahindra Manulife Mid Cap Fund Growth | F281: Mahindra Manulife Mid Cap Fund Growth | H281: 15.998 | I281: 4999.75 | J281: 312.523 | K281: =IF(OR(EXACT(C281,"Redemption"),EXACT(C281,"Redeem"),EXACT(C281,"Switch Out"),EXACT(C281,"sell"),EXACT(C281,"Sell")),-J281,J281) -> 312.523 | L281: =IF(EXACT(tManiqHars[[#This Row],[Transaction Type]],"Initial Purchase Pre-Rejection"),0,IF(OR(EXACT(tManiqHars[[#This Row],[Transaction Type]],"Redemption"),EXACT(tManiqHars[[#This Row],[Transaction Type]],"Redeem"),EXACT(tManiqHars[[#This Row],[Transaction Type]],"Switch Out"),EXACT(tManiqHars[[#This Row],[Transaction Type]],"sell"),EXACT(tManiqHars[[#This Row],[Transaction Type]],"Sell")),-tManiqHars[[#This Row],[Amount]],tManiqHars[[#This Row],[Amount]])) -> 4999.75 | M281: Executed
A282: 44389 | B282: 305245663 | C282: SIP Purchase | D282: Aditya Birla | E282: Aditya Birla Sun Life Value Fund Growth | F282: Aditya Birla Sun Life Value Fund Growth | H282: 68.0465 | I282: 4999.75 | J282: 73.475 | K282: =IF(OR(EXACT(C282,"Redemption"),EXACT(C282,"Redeem"),EXACT(C282,"Switch Out"),EXACT(C282,"sell"),EXACT(C282,"Sell")),-J282,J282) -> 73.475 | L282: =IF(EXACT(tManiqHars[[#This Row],[Transaction Type]],"Initial Purchase Pre-Rejection"),0,IF(OR(EXACT(tManiqHars[[#This Row],[Transaction Type]],"Redemption"),EXACT(tManiqHars[[#This Row],[Transaction Type]],"Redeem"),EXACT(tManiqHars[[#This Row],[Transaction Type]],"Switch Out"),EXACT(tManiqHars[[#This Row],[Transaction Type]],"sell"),EXACT(tManiqHars[[#This Row],[Transaction Type]],"Sell")),-tManiqHars[[#This Row],[Amount]],tManiqHars[[#This Row],[Amount]])) -> 4999.75 | M282: Executed
A283: 44389 | B283: 357331804 | C283: SIP Purchase | D283: Icici Prudential | E283: ICICI Prudential Value Fund Growth | F283: Icici Prudential Value Fund Growth | H283: 214.98 | I283: 4999.75 | J283: 23.257 | K283: =IF(OR(EXACT(C283,"Redemption"),EXACT(C283,"Redeem"),EXACT(C283,"Switch Out"),EXACT(C283,"sell"),EXACT(C283,"Sell")),-J283,J283) -> 23.257 | L283: =IF(EXACT(tManiqHars[[#This Row],[Transaction Type]],"Initial Purchase Pre-Rejection"),0,IF(OR(EXACT(tManiqHars[[#This Row],[Transaction Type]],"Redemption"),EXACT(tManiqHars[[#This Row],[Transaction Type]],"Redeem"),EXACT(tManiqHars[[#This Row],[Transaction Type]],"Switch Out"),EXACT(tManiqHars[[#This Row],[Transaction Type]],"sell"),EXACT(tManiqHars[[#This Row],[Transaction Type]],"Sell")),-tManiqHars[[#This Row],[Amount]],tManiqHars[[#This Row],[Amount]])) -> 4999.75 | M283: Executed
... A305: 44271 | B305: EB77737362992SIN7639105 | C305: SIP Purchase | D305: Mirae Asset | E305: Mirae Asset Large and Mid Cap Fund Growth | F305: Mirae Asset Large And Mid Cap Fund Growth | H305: 79.457 | I305: 2499.88 | J305: 31.462 | K305: =IF(OR(EXACT(C305,"Redemption"),EXACT(C305,"Redeem"),EXACT(C305,"Switch Out"),EXACT(C305,"sell"),EXACT(C305,"Sell")),-J305,J305) -> 31.462 | L305: =IF(EXACT(tManiqHars[[#This Row],[Transaction Type]],"Initial Purchase Pre-Rejection"),0,IF(OR(EXACT(tManiqHars[[#This Row],[Transaction Type]],"Redemption"),EXACT(tManiqHars[[#This Row],[Transaction Type]],"Redeem"),EXACT(tManiqHars[[#This Row],[Transaction Type]],"Switch Out"),EXACT(tManiqHars[[#This Row],[Transaction Type]],"sell"),EXACT(tManiqHars[[#This Row],[Transaction Type]],"Sell")),-tManiqHars[[#This Row],[Amount]],tManiqHars[[#This Row],[Amount]])) -> 2499.88 | M305: Executed
A306: 46139 | C306: SIP Purchase | D306: Canara Robeco | E306: Canara Robeco Large and Mid Cap Fund Growth | F306: Canara Robeco Large And Mid Cap Fund Growth | H306: 246.29 | I306: 2499.88 | J306: 10.15 | K306: =IF(OR(EXACT(C306,"Redemption"),EXACT(C306,"Redeem"),EXACT(C306,"Switch Out"),EXACT(C306,"sell"),EXACT(C306,"Sell")),-J306,J306) -> 10.15 | L306: =IF(EXACT(tManiqHars[[#This Row],[Transaction Type]],"Initial Purchase Pre-Rejection"),0,IF(OR(EXACT(tManiqHars[[#This Row],[Transaction Type]],"Redemption"),EXACT(tManiqHars[[#This Row],[Transaction Type]],"Redeem"),EXACT(tManiqHars[[#This Row],[Transaction Type]],"Switch Out"),EXACT(tManiqHars[[#This Row],[Transaction Type]],"sell"),EXACT(tManiqHars[[#This Row],[Transaction Type]],"Sell")),-tManiqHars[[#This Row],[Amount]],tManiqHars[[#This Row],[Amount]])) -> 2499.88 | M306: Executed
A307: 46139 | C307: SIP Purchase | D307: Mirae Asset | E307: Mirae Asset Large and Mid Cap Fund Growth | F307: Mirae Asset Large And Mid Cap Fund Growth | H307: 150.954 | I307: 2499.88 | J307: 16.561 | K307: =IF(OR(EXACT(C307,"Redemption"),EXACT(C307,"Redeem"),EXACT(C307,"Switch Out"),EXACT(C307,"sell"),EXACT(C307,"Sell")),-J307,J307) -> 16.561 | L307: =IF(EXACT(tManiqHars[[#This Row],[Transaction Type]],"Initial Purchase Pre-Rejection"),0,IF(OR(EXACT(tManiqHars[[#This Row],[Transaction Type]],"Redemption"),EXACT(tManiqHars[[#This Row],[Transaction Type]],"Redeem"),EXACT(tManiqHars[[#This Row],[Transaction Type]],"Switch Out"),EXACT(tManiqHars[[#This Row],[Transaction Type]],"sell"),EXACT(tManiqHars[[#This Row],[Transaction Type]],"Sell")),-tManiqHars[[#This Row],[Amount]],tManiqHars[[#This Row],[Amount]])) -> 2499.88 | M307: Executed
A308: 46139 | C308: SIP Purchase | D308: Sbi Small | E308: SBI Small Cap Fund Growth | F308: Sbi Small Cap Fund Growth | H308: 168.309 | I308: 2499.88 | J308: 14.853 | K308: =IF(OR(EXACT(C308,"Redemption"),EXACT(C308,"Redeem"),EXACT(C308,"Switch Out"),EXACT(C308,"sell"),EXACT(C308,"Sell")),-J308,J308) -> 14.853 | L308: =IF(EXACT(tManiqHars[[#This Row],[Transaction Type]],"Initial Purchase Pre-Rejection"),0,IF(OR(EXACT(tManiqHars[[#This Row],[Transaction Type]],"Redemption"),EXACT(tManiqHars[[#This Row],[Transaction Type]],"Redeem"),EXACT(tManiqHars[[#This Row],[Transaction Type]],"Switch Out"),EXACT(tManiqHars[[#This Row],[Transaction Type]],"sell"),EXACT(tManiqHars[[#This Row],[Transaction Type]],"Sell")),-tManiqHars[[#This Row],[Amount]],tManiqHars[[#This Row],[Amount]])) -> 2499.88 | M308: Executed
A309: 46139 | C309: SIP Purchase | D309: Icici Prudential | E309: ICICI Prudential Focused Equity Fund Growth | F309: Icici Prudential Focused Equity Fund Growth | H309: 91.52 | I309: 2499.88 | J309: 27.315 | K309: =IF(OR(EXACT(C309,"Redemption"),EXACT(C309,"Redeem"),EXACT(C309,"Switch Out"),EXACT(C309,"sell"),EXACT(C309,"Sell")),-J309,J309) -> 27.315 | L309: =IF(EXACT(tManiqHars[[#This Row],[Transaction Type]],"Initial Purchase Pre-Rejection"),0,IF(OR(EXACT(tManiqHars[[#This Row],[Transaction Type]],"Redemption"),EXACT(tManiqHars[[#This Row],[Transaction Type]],"Redeem"),EXACT(tManiqHars[[#This Row],[Transaction Type]],"Switch Out"),EXACT(tManiqHars[[#This Row],[Transaction Type]],"sell"),EXACT(tManiqHars[[#This Row],[Transaction Type]],"Sell")),-tManiqHars[[#This Row],[Amount]],tManiqHars[[#This Row],[Amount]])) -> 2499.88 | M309: Executed
A310: 46167 | C310: SIP Purchase | D310: Canara Robeco | E310: Canara Robeco Large and Mid Cap Fund Growth | F310: Canara Robeco Large And Mid Cap Fund Growth | H310: 246.29 | I310: 2499.88 | J310: 10.15 | K310: =IF(OR(EXACT(C310,"Redemption"),EXACT(C310,"Redeem"),EXACT(C310,"Switch Out"),EXACT(C310,"sell"),EXACT(C310,"Sell")),-J310,J310) -> 10.15 | L310: =IF(EXACT(tManiqHars[[#This Row],[Transaction Type]],"Initial Purchase Pre-Rejection"),0,IF(OR(EXACT(tManiqHars[[#This Row],[Transaction Type]],"Redemption"),EXACT(tManiqHars[[#This Row],[Transaction Type]],"Redeem"),EXACT(tManiqHars[[#This Row],[Transaction Type]],"Switch Out"),EXACT(tManiqHars[[#This Row],[Transaction Type]],"sell"),EXACT(tManiqHars[[#This Row],[Transaction Type]],"Sell")),-tManiqHars[[#This Row],[Amount]],tManiqHars[[#This Row],[Amount]])) -> 2499.88 | M310: Executed
A311: 46167 | C311: SIP Purchase | D311: Mirae Asset | E311: Mirae Asset Large and Mid Cap Fund Growth | F311: Mirae Asset Large And Mid Cap Fund Growth | H311: 150.954 | I311: 2499.88 | J311: 16.561 | K311: =IF(OR(EXACT(C311,"Redemption"),EXACT(C311,"Redeem"),EXACT(C311,"Switch Out"),EXACT(C311,"sell"),EXACT(C311,"Sell")),-J311,J311) -> 16.561 | L311: =IF(EXACT(tManiqHars[[#This Row],[Transaction Type]],"Initial Purchase Pre-Rejection"),0,IF(OR(EXACT(tManiqHars[[#This Row],[Transaction Type]],"Redemption"),EXACT(tManiqHars[[#This Row],[Transaction Type]],"Redeem"),EXACT(tManiqHars[[#This Row],[Transaction Type]],"Switch Out"),EXACT(tManiqHars[[#This Row],[Transaction Type]],"sell"),EXACT(tManiqHars[[#This Row],[Transaction Type]],"Sell")),-tManiqHars[[#This Row],[Amount]],tManiqHars[[#This Row],[Amount]])) -> 2499.88 | M311: Executed
A312: 46167 | C312: SIP Purchase | D312: Sbi Small | E312: SBI Small Cap Fund Growth | F312: Sbi Small Cap Fund Growth | H312: 168.309 | I312: 2499.88 | J312: 14.853 | K312: =IF(OR(EXACT(C312,"Redemption"),EXACT(C312,"Redeem"),EXACT(C312,"Switch Out"),EXACT(C312,"sell"),EXACT(C312,"Sell")),-J312,J312) -> 14.853 | L312: =IF(EXACT(tManiqHars[[#This Row],[Transaction Type]],"Initial Purchase Pre-Rejection"),0,IF(OR(EXACT(tManiqHars[[#This Row],[Transaction Type]],"Redemption"),EXACT(tManiqHars[[#This Row],[Transaction Type]],"Redeem"),EXACT(tManiqHars[[#This Row],[Transaction Type]],"Switch Out"),EXACT(tManiqHars[[#This Row],[Transaction Type]],"sell"),EXACT(tManiqHars[[#This Row],[Transaction Type]],"Sell")),-tManiqHars[[#This Row],[Amount]],tManiqHars[[#This Row],[Amount]])) -> 2499.88 | M312: Executed
A313: 46167 | C313: SIP Purchase | D313: Icici Prudential | E313: ICICI Prudential Focused Equity Fund Growth | F313: Icici Prudential Focused Equity Fund Growth | H313: 91.52 | I313: 2499.88 | J313: 27.315 | K313: =IF(OR(EXACT(C313,"Redemption"),EXACT(C313,"Redeem"),EXACT(C313,"Switch Out"),EXACT(C313,"sell"),EXACT(C313,"Sell")),-J313,J313) -> 27.315 | L313: =IF(EXACT(tManiqHars[[#This Row],[Transaction Type]],"Initial Purchase Pre-Rejection"),0,IF(OR(EXACT(tManiqHars[[#This Row],[Transaction Type]],"Redemption"),EXACT(tManiqHars[[#This Row],[Transaction Type]],"Redeem"),EXACT(tManiqHars[[#This Row],[Transaction Type]],"Switch Out"),EXACT(tManiqHars[[#This Row],[Transaction Type]],"sell"),EXACT(tManiqHars[[#This Row],[Transaction Type]],"Sell")),-tManiqHars[[#This Row],[Amount]],tManiqHars[[#This Row],[Amount]])) -> 2499.88 | M313: Executed
A314: 46198 | C314: SIP Purchase | D314: Canara Robeco | E314: Canara Robeco Large and Mid Cap Fund Growth | F314: Canara Robeco Large And Mid Cap Fund Growth | H314: 246.29 | I314: 2499.88 | J314: 10.15 | K314: =IF(OR(EXACT(C314,"Redemption"),EXACT(C314,"Redeem"),EXACT(C314,"Switch Out"),EXACT(C314,"sell"),EXACT(C314,"Sell")),-J314,J314) -> 10.15 | L314: =IF(EXACT(tManiqHars[[#This Row],[Transaction Type]],"Initial Purchase Pre-Rejection"),0,IF(OR(EXACT(tManiqHars[[#This Row],[Transaction Type]],"Redemption"),EXACT(tManiqHars[[#This Row],[Transaction Type]],"Redeem"),EXACT(tManiqHars[[#This Row],[Transaction Type]],"Switch Out"),EXACT(tManiqHars[[#This Row],[Transaction Type]],"sell"),EXACT(tManiqHars[[#This Row],[Transaction Type]],"Sell")),-tManiqHars[[#This Row],[Amount]],tManiqHars[[#This Row],[Amount]])) -> 2499.88 | M314: Executed
A315: 46198 | C315: SIP Purchase | D315: Mirae Asset | E315: Mirae Asset Large and Mid Cap Fund Growth | F315: Mirae Asset Large And Mid Cap Fund Growth | H315: 150.954 | I315: 2499.88 | J315: 16.561 | K315: =IF(OR(EXACT(C315,"Redemption"),EXACT(C315,"Redeem"),EXACT(C315,"Switch Out"),EXACT(C315,"sell"),EXACT(C315,"Sell")),-J315,J315) -> 16.561 | L315: =IF(EXACT(tManiqHars[[#This Row],[Transaction Type]],"Initial Purchase Pre-Rejection"),0,IF(OR(EXACT(tManiqHars[[#This Row],[Transaction Type]],"Redemption"),EXACT(tManiqHars[[#This Row],[Transaction Type]],"Redeem"),EXACT(tManiqHars[[#This Row],[Transaction Type]],"Switch Out"),EXACT(tManiqHars[[#This Row],[Transaction Type]],"sell"),EXACT(tManiqHars[[#This Row],[Transaction Type]],"Sell")),-tManiqHars[[#This Row],[Amount]],tManiqHars[[#This Row],[Amount]])) -> 2499.88 | M315: Executed
A316: 46198 | C316: SIP Purchase | D316: Sbi Small | E316: SBI Small Cap Fund Growth | F316: Sbi Small Cap Fund Growth | H316: 168.309 | I316: 2499.88 | J316: 14.853 | K316: =IF(OR(EXACT(C316,"Redemption"),EXACT(C316,"Redeem"),EXACT(C316,"Switch Out"),EXACT(C316,"sell"),EXACT(C316,"Sell")),-J316,J316) -> 14.853 | L316: =IF(EXACT(tManiqHars[[#This Row],[Transaction Type]],"Initial Purchase Pre-Rejection"),0,IF(OR(EXACT(tManiqHars[[#This Row],[Transaction Type]],"Redemption"),EXACT(tManiqHars[[#This Row],[Transaction Type]],"Redeem"),EXACT(tManiqHars[[#This Row],[Transaction Type]],"Switch Out"),EXACT(tManiqHars[[#This Row],[Transaction Type]],"sell"),EXACT(tManiqHars[[#This Row],[Transaction Type]],"Sell")),-tManiqHars[[#This Row],[Amount]],tManiqHars[[#This Row],[Amount]])) -> 2499.88 | M316: Executed
A317: 46198 | C317: SIP Purchase | D317: Icici Prudential | E317: ICICI Prudential Focused Equity Fund Growth | F317: Icici Prudential Focused Equity Fund Growth | H317: 91.52 | I317: 2499.88 | J317: 27.315 | K317: =IF(OR(EXACT(C317,"Redemption"),EXACT(C317,"Redeem"),EXACT(C317,"Switch Out"),EXACT(C317,"sell"),EXACT(C317,"Sell")),-J317,J317) -> 27.315 | L317: =IF(EXACT(tManiqHars[[#This Row],[Transaction Type]],"Initial Purchase Pre-Rejection"),0,IF(OR(EXACT(tManiqHars[[#This Row],[Transaction Type]],"Redemption"),EXACT(tManiqHars[[#This Row],[Transaction Type]],"Redeem"),EXACT(tManiqHars[[#This Row],[Transaction Type]],"Switch Out"),EXACT(tManiqHars[[#This Row],[Transaction Type]],"sell"),EXACT(tManiqHars[[#This Row],[Transaction Type]],"Sell")),-tManiqHars[[#This Row],[Amount]],tManiqHars[[#This Row],[Amount]])) -> 2499.88 | M317: Executed

Sheet Txn-Zerodh-Ashu
A1: Transactions — Zerodha - Ashutosh
A2: 6 transactions • Add or delete rows freely — the Dashboard auto-recomputes via the Excel table named 'tZerodhAshu'.
A4: Date | B4: Transaction ID | C4: Transaction Type | D4: Fund Name | E4: Scheme Name | F4: Display Scheme | G4: Folio No | H4: Last recorded NAV | I4: Amount | J4: Unit | K4: Signed Unit | L4: Signed Amount | M4: Status
A5: 45987 | B5: 2275390896 | C5: Purchase | D5: Mirae Asset | E5: Mirae Asset Large & Midcap Fund - Direct Plan - Growth | F5: Mirae Asset Large And Mid Cap Fund Growth | G5: INF769K01BI1 | H5: 178.28 | I5: 49997.56 | J5: 280.444 | K5: =IF(OR(EXACT(C5,"Redemption"),EXACT(C5,"Redeem"),EXACT(C5,"Switch Out"),EXACT(C5,"sell"),EXACT(C5,"Sell")),-J5,J5) -> 280.444 | L5: =IF(EXACT(tZerodhAshu[[#This Row],[Transaction Type]],"Initial Purchase Pre-Rejection"),0,IF(OR(EXACT(tZerodhAshu[[#This Row],[Transaction Type]],"Redemption"),EXACT(tZerodhAshu[[#This Row],[Transaction Type]],"Redeem"),EXACT(tZerodhAshu[[#This Row],[Transaction Type]],"Switch Out"),EXACT(tZerodhAshu[[#This Row],[Transaction Type]],"sell"),EXACT(tZerodhAshu[[#This Row],[Transaction Type]],"Sell")),-tZerodhAshu[[#This Row],[Amount]],tZerodhAshu[[#This Row],[Amount]])) -> 49997.56 | M5: Executed
A6: 45980 | B6: 2262311934 | C6: Purchase | D6: Mirae Asset | E6: Mirae Asset Large & Midcap Fund - Direct Plan - Growth | F6: Mirae Asset Large And Mid Cap Fund Growth | G6: INF769K01BI1 | H6: 177.605 | I6: 49997.58 | J6: 281.51 | K6: =IF(OR(EXACT(C6,"Redemption"),EXACT(C6,"Redeem"),EXACT(C6,"Switch Out"),EXACT(C6,"sell"),EXACT(C6,"Sell")),-J6,J6) -> 281.51 | L6: =IF(EXACT(tZerodhAshu[[#This Row],[Transaction Type]],"Initial Purchase Pre-Rejection"),0,IF(OR(EXACT(tZerodhAshu[[#This Row],[Transaction Type]],"Redemption"),EXACT(tZerodhAshu[[#This Row],[Transaction Type]],"Redeem"),EXACT(tZerodhAshu[[#This Row],[Transaction Type]],"Switch Out"),EXACT(tZerodhAshu[[#This Row],[Transaction Type]],"sell"),EXACT(tZerodhAshu[[#This Row],[Transaction Type]],"Sell")),-tZerodhAshu[[#This Row],[Amount]],tZerodhAshu[[#This Row],[Amount]])) -> 49997.58 | M6: Executed
A7: 45973 | B7: 2247476443 | C7: Purchase | D7: Hdfc Gold | E7: Hdfc Gold Etf Fund Of Fund - Direct Plan - Growth Option | F7: Hdfc Gold Etf Fund Of Fund Direct Growth Option | G7: INF179K01VX0 | H7: 38.7598 | I7: 49997.51 | J7: 1289.932 | K7: =IF(OR(EXACT(C7,"Redemption"),EXACT(C7,"Redeem"),EXACT(C7,"Switch Out"),EXACT(C7,"sell"),EXACT(C7,"Sell")),-J7,J7) -> 1289.932 | L7: =IF(EXACT(tZerodhAshu[[#This Row],[Transaction Type]],"Initial Purchase Pre-Rejection"),0,IF(OR(EXACT(tZerodhAshu[[#This Row],[Transaction Type]],"Redemption"),EXACT(tZerodhAshu[[#This Row],[Transaction Type]],"Redeem"),EXACT(tZerodhAshu[[#This Row],[Transaction Type]],"Switch Out"),EXACT(tZerodhAshu[[#This Row],[Transaction Type]],"sell"),EXACT(tZerodhAshu[[#This Row],[Transaction Type]],"Sell")),-tZerodhAshu[[#This Row],[Amount]],tZerodhAshu[[#This Row],[Amount]])) -> 49997.51 | M7: Executed
A8: 45897 | B8: 2067782380 | C8: Purchase | D8: Mirae Asset | E8: Mirae Asset Large & Midcap Fund - Direct Plan - Growth | F8: Mirae Asset Large And Mid Cap Fund Growth | G8: INF769K01BI1 | H8: 165.328 | I8: 49997.5 | J8: 302.414 | K8: =IF(OR(EXACT(C8,"Redemption"),EXACT(C8,"Redeem"),EXACT(C8,"Switch Out"),EXACT(C8,"sell"),EXACT(C8,"Sell")),-J8,J8) -> 302.414 | L8: =IF(EXACT(tZerodhAshu[[#This Row],[Transaction Type]],"Initial Purchase Pre-Rejection"),0,IF(OR(EXACT(tZerodhAshu[[#This Row],[Transaction Type]],"Redemption"),EXACT(tZerodhAshu[[#This Row],[Transaction Type]],"Redeem"),EXACT(tZerodhAshu[[#This Row],[Transaction Type]],"Switch Out"),EXACT(tZerodhAshu[[#This Row],[Transaction Type]],"sell"),EXACT(tZerodhAshu[[#This Row],[Transaction Type]],"Sell")),-tZerodhAshu[[#This Row],[Amount]],tZerodhAshu[[#This Row],[Amount]])) -> 49997.5 | M8: Executed
A9: 45866 | B9: 2001085180 | C9: Purchase | D9: Invesco India | E9: Invesco India Contra Fund - Direct Plan | F9: Invesco India Contra Fund - Direct Plan | G9: INF205K01LE4 | H9: 158.59 | I9: 49997.56 | J9: 315.263 | K9: =IF(OR(EXACT(C9,"Redemption"),EXACT(C9,"Redeem"),EXACT(C9,"Switch Out"),EXACT(C9,"sell"),EXACT(C9,"Sell")),-J9,J9) -> 315.263 | L9: =IF(EXACT(tZerodhAshu[[#This Row],[Transaction Type]],"Initial Purchase Pre-Rejection"),0,IF(OR(EXACT(tZerodhAshu[[#This Row],[Transaction Type]],"Redemption"),EXACT(tZerodhAshu[[#This Row],[Transaction Type]],"Redeem"),EXACT(tZerodhAshu[[#This Row],[Transaction Type]],"Switch Out"),EXACT(tZerodhAshu[[#This Row],[Transaction Type]],"sell"),EXACT(tZerodhAshu[[#This Row],[Transaction Type]],"Sell")),-tZerodhAshu[[#This Row],[Amount]],tZerodhAshu[[#This Row],[Amount]])) -> 49997.56 | M9: Executed
A10: 44294 | B10: 222538790 | C10: Purchase | D10: Invesco India | E10: Invesco India Contra Fund - Direct Plan | F10: Invesco India Contra Fund - Direct Plan | G10: INF205K01LE4 | H10: 71.19 | I10: 49997.52 | J10: 702.311 | K10: =IF(OR(EXACT(C10,"Redemption"),EXACT(C10,"Redeem"),EXACT(C10,"Switch Out"),EXACT(C10,"sell"),EXACT(C10,"Sell")),-J10,J10) -> 702.311 | L10: =IF(EXACT(tZerodhAshu[[#This Row],[Transaction Type]],"Initial Purchase Pre-Rejection"),0,IF(OR(EXACT(tZerodhAshu[[#This Row],[Transaction Type]],"Redemption"),EXACT(tZerodhAshu[[#This Row],[Transaction Type]],"Redeem"),EXACT(tZerodhAshu[[#This Row],[Transaction Type]],"Switch Out"),EXACT(tZerodhAshu[[#This Row],[Transaction Type]],"sell"),EXACT(tZerodhAshu[[#This Row],[Transaction Type]],"Sell")),-tZerodhAshu[[#This Row],[Amount]],tZerodhAshu[[#This Row],[Amount]])) -> 49997.52 | M10: Executed

Sheet Txn-Zerodh-Hars
A1: Transactions — Zerodha - Harsha
A2: 16 transactions • Add or delete rows freely — the Dashboard auto-recomputes via the Excel table named 'tZerodhHars'.
A4: Date | B4: Transaction ID | C4: Transaction Type | D4: Fund Name | E4: Scheme Name | F4: Display Scheme | G4: Folio No | H4: Last recorded NAV | I4: Amount | J4: Unit | K4: Signed Unit | L4: Signed Amount | M4: Status
A5: 46125 | B5: 2635339247 | C5: Purchase | D5: Icici Prudential | E5: Icici Prudential Balanced Advantage Fund - Direct Plan - Growth | F5: Icici Prudential Balanced Advantage Fund Direct Growth | G5: INF109K012B0 | H5: 84.78 | I5: 2499.91 | J5: 29.487 | K5: =IF(OR(EXACT(C5,"Redemption"),EXACT(C5,"Redeem"),EXACT(C5,"Switch Out"),EXACT(C5,"sell"),EXACT(C5,"Sell")),-J5,J5) -> 29.487 | L5: =IF(EXACT(tZerodhHars[[#This Row],[Transaction Type]],"Initial Purchase Pre-Rejection"),0,IF(OR(EXACT(tZerodhHars[[#This Row],[Transaction Type]],"Redemption"),EXACT(tZerodhHars[[#This Row],[Transaction Type]],"Redeem"),EXACT(tZerodhHars[[#This Row],[Transaction Type]],"Switch Out"),EXACT(tZerodhHars[[#This Row],[Transaction Type]],"sell"),EXACT(tZerodhHars[[#This Row],[Transaction Type]],"Sell")),-tZerodhHars[[#This Row],[Amount]],tZerodhHars[[#This Row],[Amount]])) -> 2499.91 | M5: Executed
A6: 46108 | B6: 2589024593 | C6: Purchase | D6: Icici Prudential | E6: Icici Prudential Balanced Advantage Fund - Direct Plan - Growth | F6: Icici Prudential Balanced Advantage Fund Direct Growth | G6: INF109K012B0 | H6: 81.56 | I6: 2499.9 | J6: 30.651 | K6: =IF(OR(EXACT(C6,"Redemption"),EXACT(C6,"Redeem"),EXACT(C6,"Switch Out"),EXACT(C6,"sell"),EXACT(C6,"Sell")),-J6,J6) -> 30.651 | L6: =IF(EXACT(tZerodhHars[[#This Row],[Transaction Type]],"Initial Purchase Pre-Rejection"),0,IF(OR(EXACT(tZerodhHars[[#This Row],[Transaction Type]],"Redemption"),EXACT(tZerodhHars[[#This Row],[Transaction Type]],"Redeem"),EXACT(tZerodhHars[[#This Row],[Transaction Type]],"Switch Out"),EXACT(tZerodhHars[[#This Row],[Transaction Type]],"sell"),EXACT(tZerodhHars[[#This Row],[Transaction Type]],"Sell")),-tZerodhHars[[#This Row],[Amount]],tZerodhHars[[#This Row],[Amount]])) -> 2499.9 | M6: Executed
A7: 46093 | B7: 2556981312 | C7: Purchase | D7: Icici Prudential | E7: Icici Prudential Balanced Advantage Fund - Direct Plan - Growth | F7: Icici Prudential Balanced Advantage Fund Direct Growth | G7: INF109K012B0 | H7: 83.15 | I7: 2499.9 | J7: 30.065 | K7: =IF(OR(EXACT(C7,"Redemption"),EXACT(C7,"Redeem"),EXACT(C7,"Switch Out"),EXACT(C7,"sell"),EXACT(C7,"Sell")),-J7,J7) -> 30.065 | L7: =IF(EXACT(tZerodhHars[[#This Row],[Transaction Type]],"Initial Purchase Pre-Rejection"),0,IF(OR(EXACT(tZerodhHars[[#This Row],[Transaction Type]],"Redemption"),EXACT(tZerodhHars[[#This Row],[Transaction Type]],"Redeem"),EXACT(tZerodhHars[[#This Row],[Transaction Type]],"Switch Out"),EXACT(tZerodhHars[[#This Row],[Transaction Type]],"sell"),EXACT(tZerodhHars[[#This Row],[Transaction Type]],"Sell")),-tZerodhHars[[#This Row],[Amount]],tZerodhHars[[#This Row],[Amount]])) -> 2499.9 | M7: Executed
A8: 46063 | B8: 2468301967 | C8: Purchase | D8: Icici Prudential | E8: Icici Prudential Balanced Advantage Fund - Direct Plan - Growth | F8: Icici Prudential Balanced Advantage Fund Direct Growth | G8: INF109K012B0 | H8: 87.34 | I8: 2499.85 | J8: 28.622 | K8: =IF(OR(EXACT(C8,"Redemption"),EXACT(C8,"Redeem"),EXACT(C8,"Switch Out"),EXACT(C8,"sell"),EXACT(C8,"Sell")),-J8,J8) -> 28.622 | L8: =IF(EXACT(tZerodhHars[[#This Row],[Transaction Type]],"Initial Purchase Pre-Rejection"),0,IF(OR(EXACT(tZerodhHars[[#This Row],[Transaction Type]],"Redemption"),EXACT(tZerodhHars[[#This Row],[Transaction Type]],"Redeem"),EXACT(tZerodhHars[[#This Row],[Transaction Type]],"Switch Out"),EXACT(tZerodhHars[[#This Row],[Transaction Type]],"sell"),EXACT(tZerodhHars[[#This Row],[Transaction Type]],"Sell")),-tZerodhHars[[#This Row],[Amount]],tZerodhHars[[#This Row],[Amount]])) -> 2499.85 | M8: Executed
A9: 46052 | B9: 2433900591 | C9: Purchase | D9: Hdfc Gold | E9: Hdfc Gold Etf Fund Of Fund - Direct Plan - Growth Option | F9: Hdfc Gold Etf Fund Of Fund Direct Growth Option | G9: INF179K01VX0 | H9: 49.7868 | I9: 49997.5 | J9: 1004.232 | K9: =IF(OR(EXACT(C9,"Redemption"),EXACT(C9,"Redeem"),EXACT(C9,"Switch Out"),EXACT(C9,"sell"),EXACT(C9,"Sell")),-J9,J9) -> 1004.232 | L9: =IF(EXACT(tZerodhHars[[#This Row],[Transaction Type]],"Initial Purchase Pre-Rejection"),0,IF(OR(EXACT(tZerodhHars[[#This Row],[Transaction Type]],"Redemption"),EXACT(tZerodhHars[[#This Row],[Transaction Type]],"Redeem"),EXACT(tZerodhHars[[#This Row],[Transaction Type]],"Switch Out"),EXACT(tZerodhHars[[#This Row],[Transaction Type]],"sell"),EXACT(tZerodhHars[[#This Row],[Transaction Type]],"Sell")),-tZerodhHars[[#This Row],[Amount]],tZerodhHars[[#This Row],[Amount]])) -> 49997.5 | M9: Executed
A10: 46052 | B10: 2433899090 | C10: Purchase | D10: Hdfc Silver | E10: Hdfc Silver Etf Fund Of Fund Direct Growth | F10: Hdfc Silver Etf Fund Of Fund Direct Growth | G10: INF179KC1DU7 | H10: 51.4809 | I10: 49997.48 | J10: 971.185 | K10: =IF(OR(EXACT(C10,"Redemption"),EXACT(C10,"Redeem"),EXACT(C10,"Switch Out"),EXACT(C10,"sell"),EXACT(C10,"Sell")),-J10,J10) -> 971.185 | L10: =IF(EXACT(tZerodhHars[[#This Row],[Transaction Type]],"Initial Purchase Pre-Rejection"),0,IF(OR(EXACT(tZerodhHars[[#This Row],[Transaction Type]],"Redemption"),EXACT(tZerodhHars[[#This Row],[Transaction Type]],"Redeem"),EXACT(tZerodhHars[[#This Row],[Transaction Type]],"Switch Out"),EXACT(tZerodhHars[[#This Row],[Transaction Type]],"sell"),EXACT(tZerodhHars[[#This Row],[Transaction Type]],"Sell")),-tZerodhHars[[#This Row],[Amount]],tZerodhHars[[#This Row],[Amount]])) -> 49997.48 | M10: Executed
A11: 46052 | B11: 2433898499 | C11: Purchase | D11: Invesco India | E11: Invesco India Arbitrage Fund - Direct Plan Growth | F11: Invesco India Arbitrage Fund - Direct Plan Growth | G11: INF205K01KR8 | H11: 35.8691 | I11: 49997.51 | J11: 1393.888 | K11: =IF(OR(EXACT(C11,"Redemption"),EXACT(C11,"Redeem"),EXACT(C11,"Switch Out"),EXACT(C11,"sell"),EXACT(C11,"Sell")),-J11,J11) -> 1393.888 | L11: =IF(EXACT(tZerodhHars[[#This Row],[Transaction Type]],"Initial Purchase Pre-Rejection"),0,IF(OR(EXACT(tZerodhHars[[#This Row],[Transaction Type]],"Redemption"),EXACT(tZerodhHars[[#This Row],[Transaction Type]],"Redeem"),EXACT(tZerodhHars[[#This Row],[Transaction Type]],"Switch Out"),EXACT(tZerodhHars[[#This Row],[Transaction Type]],"sell"),EXACT(tZerodhHars[[#This Row],[Transaction Type]],"Sell")),-tZerodhHars[[#This Row],[Amount]],tZerodhHars[[#This Row],[Amount]])) -> 49997.51 | M11: Executed
A12: 46052 | B12: 2433897751 | C12: Purchase | D12: Invesco India | E12: Invesco India Arbitrage Fund - Direct Plan Growth | F12: Invesco India Arbitrage Fund - Direct Plan Growth | G12: INF205K01KR8 | H12: 35.8691 | I12: 49997.51 | J12: 1393.888 | K12: =IF(OR(EXACT(C12,"Redemption"),EXACT(C12,"Redeem"),EXACT(C12,"Switch Out"),EXACT(C12,"sell"),EXACT(C12,"Sell")),-J12,J12) -> 1393.888 | L12: =IF(EXACT(tZerodhHars[[#This Row],[Transaction Type]],"Initial Purchase Pre-Rejection"),0,IF(OR(EXACT(tZerodhHars[[#This Row],[Transaction Type]],"Redemption"),EXACT(tZerodhHars[[#This Row],[Transaction Type]],"Redeem"),EXACT(tZerodhHars[[#This Row],[Transaction Type]],"Switch Out"),EXACT(tZerodhHars[[#This Row],[Transaction Type]],"sell"),EXACT(tZerodhHars[[#This Row],[Transaction Type]],"Sell")),-tZerodhHars[[#This Row],[Amount]],tZerodhHars[[#This Row],[Amount]])) -> 49997.51 | M12: Executed
A13: 46049 | B13: 2423379772 | C13: Purchase | D13: Hdfc Gold | E13: Hdfc Gold Etf Fund Of Fund - Direct Plan - Growth Option | F13: Hdfc Gold Etf Fund Of Fund Direct Growth Option | G13: INF179K01VX0 | H13: 49.5816 | I13: 49997.49 | J13: 1008.388 | K13: =IF(OR(EXACT(C13,"Redemption"),EXACT(C13,"Redeem"),EXACT(C13,"Switch Out"),EXACT(C13,"sell"),EXACT(C13,"Sell")),-J13,J13) -> 1008.388 | L13: =IF(EXACT(tZerodhHars[[#This Row],[Transaction Type]],"Initial Purchase Pre-Rejection"),0,IF(OR(EXACT(tZerodhHars[[#This Row],[Transaction Type]],"Redemption"),EXACT(tZerodhHars[[#This Row],[Transaction Type]],"Redeem"),EXACT(tZerodhHars[[#This Row],[Transaction Type]],"Switch Out"),EXACT(tZerodhHars[[#This Row],[Transaction Type]],"sell"),EXACT(tZerodhHars[[#This Row],[Transaction Type]],"Sell")),-tZerodhHars[[#This Row],[Amount]],tZerodhHars[[#This Row],[Amount]])) -> 49997.49 | M13: Executed
A14: 46049 | B14: 2423379427 | C14: Purchase | D14: Hdfc Silver | E14: Hdfc Silver Etf Fund Of Fund Direct Growth | F14: Hdfc Silver Etf Fund Of Fund Direct Growth | G14: INF179KC1DU7 | H14: 55.7852 | I14: 49997.49 | J14: 896.25 | K14: =IF(OR(EXACT(C14,"Redemption"),EXACT(C14,"Redeem"),EXACT(C14,"Switch Out"),EXACT(C14,"sell"),EXACT(C14,"Sell")),-J14,J14) -> 896.25 | L14: =IF(EXACT(tZerodhHars[[#This Row],[Transaction Type]],"Initial Purchase Pre-Rejection"),0,IF(OR(EXACT(tZerodhHars[[#This Row],[Transaction Type]],"Redemption"),EXACT(tZerodhHars[[#This Row],[Transaction Type]],"Redeem"),EXACT(tZerodhHars[[#This Row],[Transaction Type]],"Switch Out"),EXACT(tZerodhHars[[#This Row],[Transaction Type]],"sell"),EXACT(tZerodhHars[[#This Row],[Transaction Type]],"Sell")),-tZerodhHars[[#This Row],[Amount]],tZerodhHars[[#This Row],[Amount]])) -> 49997.49 | M14: Executed
A15: 46049 | B15: 2423381154 | C15: Purchase | D15: Icici Prudential | E15: Icici Prudential Balanced Advantage Fund - Direct Plan - Growth | F15: Icici Prudential Balanced Advantage Fund Direct Growth | G15: INF109K012B0 | H15: 85.34 | I15: 4999.73 | J15: 58.586 | K15: =IF(OR(EXACT(C15,"Redemption"),EXACT(C15,"Redeem"),EXACT(C15,"Switch Out"),EXACT(C15,"sell"),EXACT(C15,"Sell")),-J15,J15) -> 58.586 | L15: =IF(EXACT(tZerodhHars[[#This Row],[Transaction Type]],"Initial Purchase Pre-Rejection"),0,IF(OR(EXACT(tZerodhHars[[#This Row],[Transaction Type]],"Redemption"),EXACT(tZerodhHars[[#This Row],[Transaction Type]],"Redeem"),EXACT(tZerodhHars[[#This Row],[Transaction Type]],"Switch Out"),EXACT(tZerodhHars[[#This Row],[Transaction Type]],"sell"),EXACT(tZerodhHars[[#This Row],[Transaction Type]],"Sell")),-tZerodhHars[[#This Row],[Amount]],tZerodhHars[[#This Row],[Amount]])) -> 4999.73 | M15: Executed
A16: 46028 | B16: 2377410585 | C16: Purchase | D16: Hdfc Silver | E16: Hdfc Silver Etf Fund Of Fund Direct Growth | F16: Hdfc Silver Etf Fund Of Fund Direct Growth | G16: INF179KC1DU7 | H16: 40.2191 | I16: 9999.51 | J16: 248.626 | K16: =IF(OR(EXACT(C16,"Redemption"),EXACT(C16,"Redeem"),EXACT(C16,"Switch Out"),EXACT(C16,"sell"),EXACT(C16,"Sell")),-J16,J16) -> 248.626 | L16: =IF(EXACT(tZerodhHars[[#This Row],[Transaction Type]],"Initial Purchase Pre-Rejection"),0,IF(OR(EXACT(tZerodhHars[[#This Row],[Transaction Type]],"Redemption"),EXACT(tZerodhHars[[#This Row],[Transaction Type]],"Redeem"),EXACT(tZerodhHars[[#This Row],[Transaction Type]],"Switch Out"),EXACT(tZerodhHars[[#This Row],[Transaction Type]],"sell"),EXACT(tZerodhHars[[#This Row],[Transaction Type]],"Sell")),-tZerodhHars[[#This Row],[Amount]],tZerodhHars[[#This Row],[Amount]])) -> 9999.51 | M16: Executed
... A24: 46181 | B24: 2635339247 | C24: Purchase | D24: Icici Prudential | E24: Icici Prudential Balanced Advantage Fund - Direct Plan - Growth | F24: Icici Prudential Balanced Advantage Fund Direct Growth | G24: INF109K012B0 | H24: 84.78 | I24: 2499.91 | J24: 29.487 | K24: =IF(OR(EXACT(C24,"Redemption"),EXACT(C24,"Redeem"),EXACT(C24,"Switch Out"),EXACT(C24,"sell"),EXACT(C24,"Sell")),-J24,J24) -> 29.487 | L24: =IF(EXACT(tZerodhHars[[#This Row],[Transaction Type]],"Initial Purchase Pre-Rejection"),0,IF(OR(EXACT(tZerodhHars[[#This Row],[Transaction Type]],"Redemption"),EXACT(tZerodhHars[[#This Row],[Transaction Type]],"Redeem"),EXACT(tZerodhHars[[#This Row],[Transaction Type]],"Switch Out"),EXACT(tZerodhHars[[#This Row],[Transaction Type]],"sell"),EXACT(tZerodhHars[[#This Row],[Transaction Type]],"Sell")),-tZerodhHars[[#This Row],[Amount]],tZerodhHars[[#This Row],[Amount]])) -> 2499.91 | M24: Executed

Sheet SIPs
A1: Include? (Y/N) | B1: Display Scheme | C1: Scheme Code | D1: Start Date | E1: Frequency | F1: Amount (₹) | G1: Account | H1: End Date (blank = today) | I1: Scheme Name (auto-check)
A2: N | B2: Kotak Contra Fund - Growth | C2: 103040 | D2: 44305 | E2: Monthly | F2: 6000 | G2: ICICI Direct - Ashutosh | I2: =IFERROR(INDEX(NAVAll[Scheme Name],MATCH(C2&"",NAVAll[Scheme Code],0)),"⚠ code not found") -> Kotak Contra Fund - Regular Plan - Growth

Sheet NAVAll
A1: Scheme Code | B1: ISIN Div Payout/ ISIN Growth | C1: ISIN Div Reinvestment | D1: Scheme Name | E1: Net Asset Value | F1: Date
A3: Open Ended Schemes(Debt Scheme - Banking and PSU Fund)
A5: Aditya Birla Sun Life Mutual Fund
A7: 119551 | B7: INF209KA12Z1 | C7: INF209KA13Z9 | D7: Aditya Birla Sun Life Banking & PSU Debt Fund - DIRECT - IDCW | E7: 106.3057 | F7: 46198
A8: 119552 | B8: INF209K01YM2 | C8: - | D8: Aditya Birla Sun Life Banking & PSU Debt Fund - DIRECT - MONTHLY IDCW | E8: 117.4995 | F8: 46198
A9: 119553 | B9: INF209K01YO8 | C9: - | D9: Aditya Birla Sun Life Banking & PSU Debt Fund - Direct - Quarterly IDCW | E9: 104.3487 | F9: 46198
A10: 108272 | B10: INF209K01LX6 | C10: INF209KA11Z3 | D10: Aditya Birla Sun Life Banking & PSU Debt Fund - REGULAR - IDCW | E10: 148.8252 | F10: 46198
A11: 110282 | B11: INF209K01LU2 | C11: - | D11: Aditya Birla Sun Life Banking & PSU Debt Fund - REGULAR - MONTHLY IDCW | E11: 112.7942 | F11: 46198
A12: 108274 | B12: INF209K01LN7 | C12: - | D12: Aditya Birla Sun Life Banking & PSU Debt Fund - REGULAR - Quarterly IDCW | E12: 101.967 | F12: 46198
A13: 108273 | B13: INF209K01LV0 | C13: - | D13: Aditya Birla Sun Life Banking & PSU Debt Fund - Regular Plan-Growth | E13: 385.5394 | F13: 46198
A14: 119550 | B14: INF209K01YN0 | C14: - | D14: Aditya Birla Sun Life Banking & PSU Debt Fund- Direct Plan-Growth | E14: 401.4726 | F14: 46198
A16: Axis Mutual Fund
A18: 128952 | B18: INF846K01NF8 | C18: - | D18: Axis Banking & PSU Debt Fund - Direct Plan - Bonus Option | E18: 1532.8272 | F18: 42900
A19: 120437 | B19: - | C19: INF846K01CU0 | D19: Axis Banking & PSU Debt Fund - Direct Plan - Daily IDCW | E19: 1039.131 | F19: 46198
A20: 120438 | B20: INF846K01CR6 | C20: - | D20: Axis Banking & PSU Debt Fund - Direct Plan - Growth Option | E20: 2874.9114 | F20: 46198
A21: 120439 | B21: INF846K01CT2 | C21: INF846K01CS4 | D21: Axis Banking & PSU Debt Fund - Direct Plan - Monthly IDCW | E21: 1032.8188 | F21: 46198
A22: 120436 | B22: INF846K01CV8 | C22: INF846K01CW6 | D22: Axis Banking & PSU Debt Fund - Direct Plan - Weekly IDCW | E22: 1040.9475 | F22: 46198
A23: 128953 | B23: INF846K01NG6 | C23: - | D23: Axis Banking & PSU Debt Fund - Regular Plan - Bonus Option | E23: 1289.4075 | F23: 42142
A24: 117447 | B24: - | C24: INF846K01CC8 | D24: Axis Banking & PSU Debt Fund - Regular Plan - Daily IDCW | E24: 1039.1303 | F24: 46198
A25: 117446 | B25: INF846K01CB0 | C25: - | D25: Axis Banking & PSU Debt Fund - Regular Plan - Growth option | E25: 2780.2688 | F25: 46198
A26: 117449 | B26: INF846K01CF1 | C26: INF846K01CG9 | D26: Axis Banking & PSU Debt Fund - Regular Plan - Monthly IDCW | E26: 1032.8102 | F26: 46198
A27: 117448 | B27: INF846K01CD6 | C27: INF846K01CE4 | D27: Axis Banking & PSU Debt Fund - Regular Plan - Weekly IDCW | E27: 1040.9204 | F27: 46198
A29: Bajaj Finserv Mutual Fund
A31: 152164 | B31: INF0QA701649 | C31: INF0QA701631 | D31: Bajaj Finserv Banking and PSU Fund- Direct Plan-Monthly- IDCW | E31: 11.0141 | F31: 46198
A32: 152163 | B32: INF0QA701615 | C32: INF0QA701623 | D32: Bajaj Finserv Banking and PSU Fund- Direct Plan- IDCW | E32: 12.1344 | F32: 46198
A33: 152165 | B33: INF0QA701557 | C33: - | D33: Bajaj Finserv Banking and PSU Fund- Regular Plan- Growth | E33: 11.9611 | F33: 46198
A34: 152166 | B34: INF0QA701565 | C34: INF0QA701573 | D34: Bajaj Finserv Banking and PSU Fund- Regular Plan- IDCW | E34: 11.9611 | F34: 46198
A35: 152162 | B35: INF0QA701607 | C35: - | D35: Bajaj Finserv Banking and PSU Fund-Direct Plan- Growth | E35: 12.1344 | F35: 46198
A36: 152167 | B36: INF0QA701599 | C36: INF0QA701581 | D36: Bajaj Finserv Banking and PSU Fund-Regular Plan-Monthly-IDCW | E36: 10.9438 | F36: 46198
A38: Bandhan Mutual Fund
A40: 121936 | B40: INF194K019M8 | C40: - | D40: Bandhan Banking and PSU Fund - Direct Annual IDCW | E40: 12.3045 | F40: 46198
A41: 127471 | B41: - | C41: INF194KA1JD3 | D41: Bandhan Banking and PSU Fund - Direct Daily IDCW | E41: 10.4768 | F41: 46198
A42: 121934 | B42: - | C42: INF194K010N5 | D42: Bandhan Banking and PSU Fund - Direct Fortnightly IDCW | E42: 10.5058 | F42: 46198
A43: 121279 | B43: INF194K015G8 | C43: - | D43: Bandhan Banking and PSU Fund - Direct Growth | E43: 26.8925 | F43: 46198
A44: 121281 | B44: INF194K016G6 | C44: INF194K017G4 | D44: Bandhan Banking and PSU Fund - Direct IDCW | E44: 14.146 | F44: 46198
A45: 121935 | B45: - | C45: INF194K011N3 | D45: Bandhan Banking and PSU Fund - Direct Monthly IDCW | E45: 10.616 | F45: 46198
A46: 121938 | B46: INF194K018M0 | C46: - | D46: Bandhan Banking and PSU Fund - Direct Quarterly IDCW | E46: 11.2019 | F46: 46198
A47: 121933 | B47: INF194K015M6 | C47: - | D47: Bandhan Banking and PSU Fund - Regular Annual IDCW | E47: 11.3243 | F47: 46198
A48: 127470 | B48: - | C48: INF194KA1JC5 | D48: Bandhan Banking and PSU Fund - Regular Daily IDCW | E48: 10.8788 | F48: 46198
A49: 121931 | B49: - | C49: INF194K016M4 | D49: Bandhan Banking and PSU Fund - Regular Fortnightly IDCW | E49: 10.6614 | F49: 46198
A50: 121280 | B50: INF194K01SN6 | C50: - | D50: Bandhan Banking and PSU Fund - Regular Growth | E50: 26.0533 | F50: 46198
A51: 121282 | B51: INF194K01SO4 | C51: INF194K012D2 | D51: Bandhan Banking and PSU Fund - Regular IDCW | E51: 14.0686 | F51: 46198
... A53: 121937 | B53: INF194K014M9 | C53: - | D53: Bandhan Banking and PSU Fund - Regular Quarterly IDCW | E53: 11.089 | F53: 46198
A55: Canara Robeco Mutual Fund
A57: 150505 | B57: INF760K01KC4 | C57: - | D57: Canara Robeco Banking and PSU Debt Fund- Direct Plan- Growth Option | E57: 12.8231 | F57: 46198
A58: 150507 | B58: INF760K01KE0 | C58: INF760K01KD2 | D58: Canara Robeco Banking and PSU Debt Fund- Direct Plan- IDCW Payout | E58: 11.0201 | F58: 46198
A59: 150503 | B59: INF760K01KF7 | C59: - | D59: Canara Robeco Banking and PSU Debt Fund- Regular Plan- Growth Option | E59: 12.6745 | F59: 46198
A60: 150504 | B60: INF760K01KH3 | C60: INF760K01KG5 | D60: Canara Robeco Banking and PSU Debt Fund- Regular Plan- IDCW (Payout/ Reinvestment) | E60: 10.9045 | F60: 46198
A62: DSP Mutual Fund
A64: 124175 | B64: INF740K01ZW2 | C64: - | D64: DSP Banking & PSU Debt Fund - Direct Plan - Growth | E64: 26.1977 | F64: 46198
A65: 124178 | B65: INF740K01A18 | C65: INF740K01A26 | D65: DSP Banking & PSU Debt Fund - Direct Plan - IDCW | E65: 10.5728 | F65: 46198
A66: 124182 | B66: - | C66: INF740KA1OF7 | D66: DSP Banking & PSU Debt Fund - Direct Plan - IDCW - Daily Reinvest | E66: 10.1889 | F66: 46198
A67: 124176 | B67: INF740K01ZX0 | C67: INF740K01ZY8 | D67: DSP Banking & PSU Debt Fund - Direct Plan - IDCW - Monthly | E67: 10.5767 | F67: 46198
A68: 124177 | B68: INF740K01ZZ5 | C68: INF740K01A00 | D68: DSP Banking & PSU Debt Fund - Direct Plan - IDCW - Quarterly | E68: 10.6351 | F68: 46198
A69: 124183 | B69: INF740KA1OG5 | C69: INF740KA1OH3 | D69: DSP Banking & PSU Debt Fund - Direct Plan - IDCW - Weekly | E69: 10.1845 | F69: 46198
A70: 124172 | B70: INF740K01ZP6 | C70: - | D70: DSP Banking & PSU Debt Fund - Regular Plan - Growth | E70: 25.234 | F70: 46198
A71: 124174 | B71: INF740K01ZU6 | C71: INF740K01ZV4 | D71: DSP Banking & PSU Debt Fund - Regular Plan - IDCW | E71: 10.5626 | F71: 46198
A72: 124173 | B72: - | C72: INF740KA1OI1 | D72: DSP Banking & PSU Debt Fund - Regular Plan - IDCW - Daily Reinvest | E72: 10.1888 | F72: 46198
A73: 124180 | B73: INF740K01ZQ4 | C73: INF740K01ZR2 | D73: DSP Banking & PSU Debt Fund - Regular Plan - IDCW - Monthly | E73: 10.5557 | F73: 46198
A74: 124181 | B74: INF740K01ZS0 | C74: INF740K01ZT8 | D74: DSP Banking & PSU Debt Fund - Regular Plan - IDCW - Quarterly | E74: 10.62 | F74: 46198
A75: 124179 | B75: INF740KA1OJ9 | C75: INF740KA1OK7 | D75: DSP Banking & PSU Debt Fund - Regular Plan - IDCW - Weekly | E75: 10.1845 | F75: 46198
A77: Edelweiss Mutual Fund
A79: 140286 | B79: INF843K01FC8 | C79: - | D79: Edelweiss Banking and PSU Debt Fund - Direct Plan - Growth Option | E79: 26.7999 | F79: 46198
A80: 140288 | B80: INF843K01FD6 | C80: INF843K01FE4 | D80: Edelweiss Banking and PSU Debt Fund - Direct Plan - IDCW Option | E80: 18.5639 | F80: 46198
A81: 140291 | B81: INF843K01FG9 | C81: - | D81: Edelweiss Banking and PSU Debt Fund - Direct Plan Fortnightly - IDCW Option | E81: 14.3946 | F81: 46198
A82: 140293 | B82: INF843K01FI5 | C82: INF843K01FH7 | D82: Edelweiss Banking and PSU Debt Fund - Direct Plan Monthly - IDCW Option | E82: 11.0423 | F82: 46198
A83: 140290 | B83: INF843K01FF1 | C83: - | D83: Edelweiss Banking and PSU Debt Fund - Direct Plan weekly - IDCW Option | E83: 10.5656 | F83: 46198
A84: 140283 | B84: INF843K01FK1 | C84: - | D84: Edelweiss Banking and PSU Debt Fund - Regular Plan - Growth Option | E84: 25.7879 | F84: 46198
A85: 140284 | B85: INF843K01FL9 | C85: INF843K01FM7 | D85: Edelweiss Banking and PSU Debt Fund - Regular Plan - IDCW Option | E85: 17.6291 | F85: 46198
A86: 140294 | B86: INF843K01FO3 | C86: - | D86: Edelweiss Banking and PSU Debt Fund - Regular Plan Fortnightly - IDCW Option | E86: 13.9159 | F86: 46198
A87: 140292 | B87: INF843K01FQ8 | C87: INF843K01FP0 | D87: Edelweiss Banking and PSU Debt Fund - Regular Plan Monthly - IDCW Option | E87: 11.2863 | F87: 46198
A88: 140289 | B88: INF843K01FN5 | C88: - | D88: Edelweiss Banking and PSU Debt Fund - Regular Plan Weekly - IDCW Option | E88: 10.1591 | F88: 46198
A90: Franklin Templeton Mutual Fund
A92: 129008 | B92: INF090I01KR8 | C92: - | D92: Franklin India Banking & PSU Debt Fund - Direct - Growth | E92: 24.9466 | F92: 46198
A93: 129006 | B93: INF090I01KO5 | C93: - | D93: Franklin India Banking & PSU Debt Fund - Growth | E93: 23.8078 | F93: 46198
A94: 129009 | B94: INF090I01KS6 | C94: INF090I01KT4 | D94: Franklin India Banking and PSU Debt Fund - Direct - IDCW | E94: 11.4662 | F94: 46198
A95: 129007 | B95: INF090I01KP2 | C95: INF090I01KQ0 | D95: Franklin India Banking and PSU Debt Fund - IDCW | E95: 10.8439 | F95: 46198
A97: HDFC Mutual Fund
A99: 128628 | B99: INF179KA1JC4 | C99: - | D99: HDFC Banking and PSU Debt Fund - Growth Option | E99: 24.2491 | F99: 46198
A100: 128629 | B100: INF179KA1IZ7 | C100: - | D100: HDFC Banking and PSU Debt Fund - Growth Option - Direct Plan | E100: 25.3419 | F100: 46198
A101: 128627 | B101: INF179KA1JD2 | C101: INF179KA1JE0 | D101: HDFC Banking and PSU Debt Fund - IDCW Option | E101: 10.1709 | F101: 46198
A102: 128626 | B102: INF179KA1JA8 | C102: INF179KA1JB6 | D102: HDFC Banking and PSU Debt Fund - IDCW Option - Direct Plan | E102: 10.061 | F102: 46198
A104: HSBC Mutual Fund
A106: 151108 | B106: - | C106: INF917K01HL7 | D106: HSBC Banking and PSU Debt Fund - Direct Daily IDCW | E106: 11.1907 | F106: 46198
A107: 151107 | B107: INF917K01HH5 | C107: - | D107: HSBC Banking and PSU Debt Fund - Direct Growth | E107: 27.0258 | F107: 46198
A108: 151106 | B108: INF917K01HJ1 | C108: INF917K01HI3 | D108: HSBC Banking and PSU Debt Fund - Direct Monthly IDCW | E108: 11.2411 | F108: 46198
A109: 151109 | B109: - | C109: INF917K01HK9 | D109: HSBC Banking and PSU Debt Fund - Direct Weekly IDCW | E109: 10.3703 | F109: 46198
A110: 151102 | B110: - | C110: INF677K01AF4 | D110: HSBC Banking and PSU Debt Fund - Regular Daily IDCW | E110: 11.116 | F110: 46198
A111: 151104 | B111: INF677K01AE7 | C111: - | D111: HSBC Banking and PSU Debt Fund - Regular Growth | E111: 25.5746 | F111: 46198
A112: 151105 | B112: INF677K01AI8 | C112: INF677K01AJ6 | D112: HSBC Banking and PSU Debt Fund - Regular Monthly IDCW | E112: 10.4374 | F112: 46198
A113: 151103 | B113: - | C113: INF917K01HM5 | D113: HSBC Banking and PSU Debt Fund - Regular Weekly IDCW | E113: 10.3431 | F113: 46198
A115: ICICI Prudential Mutual Fund
A117: 112343 | B117: INF109K01WS5 | C117: INF109K01RV9 | D117: ICICI Prudential Banking and PSU Debt Fund - Daily IDCW | E117: 10.0549 | F117: 44820
A118: 112344 | B118: INF109K01WR7 | C118: INF109K01RU1 | D118: ICICI Prudential Banking and PSU Debt Fund - Weekly IDCW | E118: 10.2427 | F118: 44820
A119: 130897 | B119: INF109KA1B57 | C119: - | D119: ICICI Prudential Banking and PSU Debt Fund - Bonus | E119: 15.8889 | F119: 43945
A120: 120257 | B120: INF109K01Z89 | C120: INF109K01Z97 | D120: ICICI Prudential Banking and PSU Debt Fund - Direct Plan - Daily IDCW | E120: 10.2538 | F120: 44820
A121: 120256 | B121: INF109K010A6 | C121: - | D121: ICICI Prudential Banking and PSU Debt Fund - Direct Plan - Growth | E121: 36.2428 | F121: 46198
A122: 120258 | B122: INF109K011A4 | C122: INF109K012A2 | D122: ICICI Prudential Banking and PSU Debt Fund - Direct Plan - Quarterly IDCW | E122: 13.1439 | F122: 46198
A123: 120255 | B123: INF109K013A0 | C123: INF109K014A8 | D123: ICICI Prudential Banking and PSU Debt Fund - Direct Plan - Weekly IDCW | E123: 10.3708 | F123: 44820
A124: 130950 | B124: INF109KA1B40 | C124: - | D124: ICICI Prudential Banking and PSU Debt Fund - Direct Plan Bonus | E124: 13.8665 | F124: 43200
...

Sheet _CashFlows
A1: Account | B1: Display Scheme | C1: Date | D1: Signed Amount
A2: ICICI Direct - Ashutosh | B2: =INDEX(tICICIAshu[Display Scheme],1) -> Kotak Contra Fund - Growth | C2: =INDEX(tICICIAshu[Date],1) -> 46192 | D2: =INDEX(tICICIAshu[Signed Amount],1) -> 6000
A3: ICICI Direct - Ashutosh | B3: =INDEX(tICICIAshu[Display Scheme],2) -> Kotak Contra Fund - Growth | C3: =INDEX(tICICIAshu[Date],2) -> 46161 | D3: =INDEX(tICICIAshu[Signed Amount],2) -> 6000
A4: ICICI Direct - Ashutosh | B4: =INDEX(tICICIAshu[Display Scheme],3) -> Kotak Contra Fund - Growth | C4: =INDEX(tICICIAshu[Date],3) -> 46131 | D4: =INDEX(tICICIAshu[Signed Amount],3) -> 6000
A5: ICICI Direct - Ashutosh | B5: =INDEX(tICICIAshu[Display Scheme],4) -> Kotak Contra Fund - Growth | C5: =INDEX(tICICIAshu[Date],4) -> 46100 | D5: =INDEX(tICICIAshu[Signed Amount],4) -> 6000
A6: ICICI Direct - Ashutosh | B6: =INDEX(tICICIAshu[Display Scheme],5) -> Kotak Contra Fund - Growth | C6: =INDEX(tICICIAshu[Date],5) -> 46072 | D6: =INDEX(tICICIAshu[Signed Amount],5) -> 6000
A7: ICICI Direct - Ashutosh | B7: =INDEX(tICICIAshu[Display Scheme],6) -> Kotak Contra Fund - Growth | C7: =INDEX(tICICIAshu[Date],6) -> 46041 | D7: =INDEX(tICICIAshu[Signed Amount],6) -> 5500
A8: ICICI Direct - Ashutosh | B8: =INDEX(tICICIAshu[Display Scheme],7) -> Kotak Contra Fund - Growth | C8: =INDEX(tICICIAshu[Date],7) -> 46010 | D8: =INDEX(tICICIAshu[Signed Amount],7) -> 5500
A9: ICICI Direct - Ashutosh | B9: =INDEX(tICICIAshu[Display Scheme],8) -> Kotak Contra Fund - Growth | C9: =INDEX(tICICIAshu[Date],8) -> 45980 | D9: =INDEX(tICICIAshu[Signed Amount],8) -> 5500
A10: ICICI Direct - Ashutosh | B10: =INDEX(tICICIAshu[Display Scheme],9) -> Kotak Contra Fund - Growth | C10: =INDEX(tICICIAshu[Date],9) -> 45949 | D10: =INDEX(tICICIAshu[Signed Amount],9) -> 5500
A11: ICICI Direct - Ashutosh | B11: =INDEX(tICICIAshu[Display Scheme],10) -> Kotak Contra Fund - Growth | C11: =INDEX(tICICIAshu[Date],10) -> 45919 | D11: =INDEX(tICICIAshu[Signed Amount],10) -> 5500
A12: ICICI Direct - Ashutosh | B12: =INDEX(tICICIAshu[Display Scheme],11) -> Kotak Contra Fund - Growth | C12: =INDEX(tICICIAshu[Date],11) -> 45888 | D12: =INDEX(tICICIAshu[Signed Amount],11) -> 5500
A13: ICICI Direct - Ashutosh | B13: =INDEX(tICICIAshu[Display Scheme],12) -> Kotak Contra Fund - Growth | C13: =INDEX(tICICIAshu[Date],12) -> 45857 | D13: =INDEX(tICICIAshu[Signed Amount],12) -> 5500
A14: ICICI Direct - Ashutosh | B14: =INDEX(tICICIAshu[Display Scheme],13) -> Kotak Contra Fund - Growth | C14: =INDEX(tICICIAshu[Date],13) -> 45827 | D14: =INDEX(tICICIAshu[Signed Amount],13) -> 5500
A15: ICICI Direct - Ashutosh | B15: =INDEX(tICICIAshu[Display Scheme],14) -> Kotak Contra Fund - Growth | C15: =INDEX(tICICIAshu[Date],14) -> 45796 | D15: =INDEX(tICICIAshu[Signed Amount],14) -> 5500
A16: ICICI Direct - Ashutosh | B16: =INDEX(tICICIAshu[Display Scheme],15) -> Kotak Contra Fund - Growth | C16: =INDEX(tICICIAshu[Date],15) -> 45766 | D16: =INDEX(tICICIAshu[Signed Amount],15) -> 5500
A17: ICICI Direct - Ashutosh | B17: =INDEX(tICICIAshu[Display Scheme],16) -> Kotak Contra Fund - Growth | C17: =INDEX(tICICIAshu[Date],16) -> 45735 | D17: =INDEX(tICICIAshu[Signed Amount],16) -> 5500
A18: ICICI Direct - Ashutosh | B18: =INDEX(tICICIAshu[Display Scheme],17) -> Kotak Contra Fund - Growth | C18: =INDEX(tICICIAshu[Date],17) -> 45707 | D18: =INDEX(tICICIAshu[Signed Amount],17) -> 5500
A19: ICICI Direct - Ashutosh | B19: =INDEX(tICICIAshu[Display Scheme],18) -> Kotak Contra Fund - Growth | C19: =INDEX(tICICIAshu[Date],18) -> 45676 | D19: =INDEX(tICICIAshu[Signed Amount],18) -> 5500
A20: ICICI Direct - Ashutosh | B20: =INDEX(tICICIAshu[Display Scheme],19) -> Kotak Contra Fund - Growth | C20: =INDEX(tICICIAshu[Date],19) -> 45645 | D20: =INDEX(tICICIAshu[Signed Amount],19) -> 5500
A21: ICICI Direct - Ashutosh | B21: =INDEX(tICICIAshu[Display Scheme],20) -> Kotak Contra Fund - Growth | C21: =INDEX(tICICIAshu[Date],20) -> 45615 | D21: =INDEX(tICICIAshu[Signed Amount],20) -> 5500
A22: ICICI Direct - Ashutosh | B22: =INDEX(tICICIAshu[Display Scheme],21) -> Kotak Contra Fund - Growth | C22: =INDEX(tICICIAshu[Date],21) -> 45584 | D22: =INDEX(tICICIAshu[Signed Amount],21) -> 5500
A23: ICICI Direct - Ashutosh | B23: =INDEX(tICICIAshu[Display Scheme],22) -> Kotak Contra Fund - Growth | C23: =INDEX(tICICIAshu[Date],22) -> 45554 | D23: =INDEX(tICICIAshu[Signed Amount],22) -> 5500
A24: ICICI Direct - Ashutosh | B24: =INDEX(tICICIAshu[Display Scheme],23) -> Kotak Contra Fund - Growth | C24: =INDEX(tICICIAshu[Date],23) -> 45523 | D24: =INDEX(tICICIAshu[Signed Amount],23) -> 5500
A25: ICICI Direct - Ashutosh | B25: =INDEX(tICICIAshu[Display Scheme],24) -> Kotak Contra Fund - Growth | C25: =INDEX(tICICIAshu[Date],24) -> 45492 | D25: =INDEX(tICICIAshu[Signed Amount],24) -> 5500
A26: ICICI Direct - Ashutosh | B26: =INDEX(tICICIAshu[Display Scheme],25) -> Kotak Contra Fund - Growth | C26: =INDEX(tICICIAshu[Date],25) -> 45462 | D26: =INDEX(tICICIAshu[Signed Amount],25) -> 5500
A27: ICICI Direct - Ashutosh | B27: =INDEX(tICICIAshu[Display Scheme],26) -> Kotak Contra Fund - Growth | C27: =INDEX(tICICIAshu[Date],26) -> 45431 | D27: =INDEX(tICICIAshu[Signed Amount],26) -> 5500
A28: ICICI Direct - Ashutosh | B28: =INDEX(tICICIAshu[Display Scheme],27) -> Kotak Contra Fund - Growth | C28: =INDEX(tICICIAshu[Date],27) -> 45401 | D28: =INDEX(tICICIAshu[Signed Amount],27) -> 5500
A29: ICICI Direct - Ashutosh | B29: =INDEX(tICICIAshu[Display Scheme],28) -> Kotak Contra Fund - Growth | C29: =INDEX(tICICIAshu[Date],28) -> 45370 | D29: =INDEX(tICICIAshu[Signed Amount],28) -> 5500
A30: ICICI Direct - Ashutosh | B30: =INDEX(tICICIAshu[Display Scheme],29) -> Kotak Contra Fund - Growth | C30: =INDEX(tICICIAshu[Date],29) -> 45341 | D30: =INDEX(tICICIAshu[Signed Amount],29) -> 5500
A31: ICICI Direct - Ashutosh | B31: =INDEX(tICICIAshu[Display Scheme],30) -> Kotak Contra Fund - Growth | C31: =INDEX(tICICIAshu[Date],30) -> 45310 | D31: =INDEX(tICICIAshu[Signed Amount],30) -> 5500
A32: ICICI Direct - Ashutosh | B32: =INDEX(tICICIAshu[Display Scheme],31) -> Kotak Contra Fund - Growth | C32: =INDEX(tICICIAshu[Date],31) -> 45279 | D32: =INDEX(tICICIAshu[Signed Amount],31) -> 5500
A33: ICICI Direct - Ashutosh | B33: =INDEX(tICICIAshu[Display Scheme],32) -> Kotak Contra Fund - Growth | C33: =INDEX(tICICIAshu[Date],32) -> 45249 | D33: =INDEX(tICICIAshu[Signed Amount],32) -> 5500
A34: ICICI Direct - Ashutosh | B34: =INDEX(tICICIAshu[Display Scheme],33) -> Kotak Contra Fund - Growth | C34: =INDEX(tICICIAshu[Date],33) -> 45218 | D34: =INDEX(tICICIAshu[Signed Amount],33) -> 5500
A35: ICICI Direct - Ashutosh | B35: =INDEX(tICICIAshu[Display Scheme],34) -> Kotak Contra Fund - Growth | C35: =INDEX(tICICIAshu[Date],34) -> 45188 | D35: =INDEX(tICICIAshu[Signed Amount],34) -> 5500
A36: ICICI Direct - Ashutosh | B36: =INDEX(tICICIAshu[Display Scheme],35) -> Kotak Contra Fund - Growth | C36: =INDEX(tICICIAshu[Date],35) -> 45157 | D36: =INDEX(tICICIAshu[Signed Amount],35) -> 5500
A37: ICICI Direct - Ashutosh | B37: =INDEX(tICICIAshu[Display Scheme],36) -> Kotak Contra Fund - Growth | C37: =INDEX(tICICIAshu[Date],36) -> 45126 | D37: =INDEX(tICICIAshu[Signed Amount],36) -> 5500
A38: ICICI Direct - Ashutosh | B38: =INDEX(tICICIAshu[Display Scheme],37) -> Kotak Contra Fund - Growth | C38: =INDEX(tICICIAshu[Date],37) -> 45096 | D38: =INDEX(tICICIAshu[Signed Amount],37) -> 5500
A39: ICICI Direct - Ashutosh | B39: =INDEX(tICICIAshu[Display Scheme],38) -> Kotak Contra Fund - Growth | C39: =INDEX(tICICIAshu[Date],38) -> 45065 | D39: =INDEX(tICICIAshu[Signed Amount],38) -> 5500
A40: ICICI Direct - Ashutosh | B40: =INDEX(tICICIAshu[Display Scheme],39) -> Kotak Contra Fund - Growth | C40: =INDEX(tICICIAshu[Date],39) -> 45035 | D40: =INDEX(tICICIAshu[Signed Amount],39) -> 5500
A41: ICICI Direct - Ashutosh | B41: =INDEX(tICICIAshu[Display Scheme],40) -> Kotak Contra Fund - Growth | C41: =INDEX(tICICIAshu[Date],40) -> 45004 | D41: =INDEX(tICICIAshu[Signed Amount],40) -> 5500
A42: ICICI Direct - Ashutosh | B42: =INDEX(tICICIAshu[Display Scheme],41) -> Kotak Contra Fund - Growth | C42: =INDEX(tICICIAshu[Date],41) -> 44976 | D42: =INDEX(tICICIAshu[Signed Amount],41) -> 5500
A43: ICICI Direct - Ashutosh | B43: =INDEX(tICICIAshu[Display Scheme],42) -> Kotak Contra Fund - Growth | C43: =INDEX(tICICIAshu[Date],42) -> 44945 | D43: =INDEX(tICICIAshu[Signed Amount],42) -> 5500
A44: ICICI Direct - Ashutosh | B44: =INDEX(tICICIAshu[Display Scheme],43) -> Kotak Contra Fund - Growth | C44: =INDEX(tICICIAshu[Date],43) -> 44914 | D44: =INDEX(tICICIAshu[Signed Amount],43) -> 5500
A45: ICICI Direct - Ashutosh | B45: =INDEX(tICICIAshu[Display Scheme],44) -> Kotak Contra Fund - Growth | C45: =INDEX(tICICIAshu[Date],44) -> 44884 | D45: =INDEX(tICICIAshu[Signed Amount],44) -> 5500
A46: ICICI Direct - Ashutosh | B46: =INDEX(tICICIAshu[Display Scheme],45) -> Kotak Contra Fund - Growth | C46: =INDEX(tICICIAshu[Date],45) -> 44853 | D46: =INDEX(tICICIAshu[Signed Amount],45) -> 5500
A47: ICICI Direct - Ashutosh | B47: =INDEX(tICICIAshu[Display Scheme],46) -> Kotak Contra Fund - Growth | C47: =INDEX(tICICIAshu[Date],46) -> 44823 | D47: =INDEX(tICICIAshu[Signed Amount],46) -> 5500
A48: ICICI Direct - Ashutosh | B48: =INDEX(tICICIAshu[Display Scheme],47) -> Kotak Contra Fund - Growth | C48: =INDEX(tICICIAshu[Date],47) -> 44792 | D48: =INDEX(tICICIAshu[Signed Amount],47) -> 5500
A49: ICICI Direct - Ashutosh | B49: =INDEX(tICICIAshu[Display Scheme],48) -> Kotak Contra Fund - Growth | C49: =INDEX(tICICIAshu[Date],48) -> 44761 | D49: =INDEX(tICICIAshu[Signed Amount],48) -> 5500
A50: ICICI Direct - Ashutosh | B50: =INDEX(tICICIAshu[Display Scheme],49) -> Kotak Contra Fund - Growth | C50: =INDEX(tICICIAshu[Date],49) -> 44731 | D50: =INDEX(tICICIAshu[Signed Amount],49) -> 5500
A51: ICICI Direct - Ashutosh | B51: =INDEX(tICICIAshu[Display Scheme],50) -> Kotak Contra Fund - Growth | C51: =INDEX(tICICIAshu[Date],50) -> 44700 | D51: =INDEX(tICICIAshu[Signed Amount],50) -> 5500
A52: ICICI Direct - Ashutosh | B52: =INDEX(tICICIAshu[Display Scheme],51) -> Kotak Contra Fund - Growth | C52: =INDEX(tICICIAshu[Date],51) -> 44670 | D52: =INDEX(tICICIAshu[Signed Amount],51) -> 5500
A53: ICICI Direct - Ashutosh | B53: =INDEX(tICICIAshu[Display Scheme],52) -> Kotak Contra Fund - Growth | C53: =INDEX(tICICIAshu[Date],52) -> 44639 | D53: =INDEX(tICICIAshu[Signed Amount],52) -> 5500
A54: ICICI Direct - Ashutosh | B54: =INDEX(tICICIAshu[Display Scheme],53) -> Kotak Contra Fund - Growth | C54: =INDEX(tICICIAshu[Date],53) -> 44611 | D54: =INDEX(tICICIAshu[Signed Amount],53) -> 5500
A55: ICICI Direct - Ashutosh | B55: =INDEX(tICICIAshu[Display Scheme],54) -> Kotak Contra Fund - Growth | C55: =INDEX(tICICIAshu[Date],54) -> 44580 | D55: =INDEX(tICICIAshu[Signed Amount],54) -> 5500
A56: ICICI Direct - Ashutosh | B56: =INDEX(tICICIAshu[Display Scheme],55) -> Kotak Contra Fund - Growth | C56: =INDEX(tICICIAshu[Date],55) -> 44549 | D56: =INDEX(tICICIAshu[Signed Amount],55) -> 5500
A57: ICICI Direct - Ashutosh | B57: =INDEX(tICICIAshu[Display Scheme],56) -> Kotak Contra Fund - Growth | C57: =INDEX(tICICIAshu[Date],56) -> 44519 | D57: =INDEX(tICICIAshu[Signed Amount],56) -> 5500
A58: ICICI Direct - Ashutosh | B58: =INDEX(tICICIAshu[Display Scheme],57) -> Kotak Contra Fund - Growth | C58: =INDEX(tICICIAshu[Date],57) -> 44488 | D58: =INDEX(tICICIAshu[Signed Amount],57) -> 5500
A59: ICICI Direct - Ashutosh | B59: =INDEX(tICICIAshu[Display Scheme],58) -> Canara Robeco Large Cap Fund Regulargrowth | C59: =INDEX(tICICIAshu[Date],58) -> 44465 | D59: =INDEX(tICICIAshu[Signed Amount],58) -> 60000
A60: ICICI Direct - Ashutosh | B60: =INDEX(tICICIAshu[Display Scheme],59) -> Kotak Contra Fund - Growth | C60: =INDEX(tICICIAshu[Date],59) -> 44458 | D60: =INDEX(tICICIAshu[Signed Amount],59) -> 5500
A61: ICICI Direct - Ashutosh | B61: =INDEX(tICICIAshu[Display Scheme],60) -> Kotak Contra Fund - Growth | C61: =INDEX(tICICIAshu[Date],60) -> 44427 | D61: =INDEX(tICICIAshu[Signed Amount],60) -> 5500
A62: ICICI Direct - Ashutosh | B62: =INDEX(tICICIAshu[Display Scheme],61) -> Kotak Contra Fund - Growth | C62: =INDEX(tICICIAshu[Date],61) -> 44396 | D62: =INDEX(tICICIAshu[Signed Amount],61) -> 5500
A63: ICICI Direct - Ashutosh | B63: =INDEX(tICICIAshu[Display Scheme],62) -> Kotak Contra Fund - Growth | C63: =INDEX(tICICIAshu[Date],62) -> 44366 | D63: =INDEX(tICICIAshu[Signed Amount],62) -> 5500
A64: ICICI Direct - Ashutosh | B64: =INDEX(tICICIAshu[Display Scheme],63) -> Canara Robeco Large And Mid Cap Fund Growth | C64: =INDEX(tICICIAshu[Date],63) -> 44354 | D64: =INDEX(tICICIAshu[Signed Amount],63) -> 500000
A65: ICICI Direct - Ashutosh | B65: =INDEX(tICICIAshu[Display Scheme],64) -> Kotak Contra Fund - Growth | C65: =INDEX(tICICIAshu[Date],64) -> 44335 | D65: =INDEX(tICICIAshu[Signed Amount],64) -> 5500
A66: ICICI Direct - Ashutosh | B66: =INDEX(tICICIAshu[Display Scheme],65) -> Kotak Contra Fund - Growth | C66: =INDEX(tICICIAshu[Date],65) -> 44305 | D66: =INDEX(tICICIAshu[Signed Amount],65) -> 5500
A67: ICICI Direct - Ashutosh | B67: =INDEX(tICICIAshu[Display Scheme],66) -> Nippon India Elss Tax Saver Fund - Growth Plan | C67: =INDEX(tICICIAshu[Date],66) -> 44276 | D67: =INDEX(tICICIAshu[Signed Amount],66) -> -47834
A68: ICICI Direct - Ashutosh | B68: =INDEX(tICICIAshu[Display Scheme],67) -> Hdfc Mid Cap Fund - Growth Option | C68: =INDEX(tICICIAshu[Date],67) -> 43110 | D68: =INDEX(tICICIAshu[Signed Amount],67) -> 5000
A69: ICICI Direct - Ashutosh | B69: =INDEX(tICICIAshu[Display Scheme],68) -> Hdfc Mid Cap Fund - Growth Option | C69: =INDEX(tICICIAshu[Date],68) -> 43079 | D69: =INDEX(tICICIAshu[Signed Amount],68) -> 5000
A70: ICICI Direct - Ashutosh | B70: =INDEX(tICICIAshu[Display Scheme],69) -> Hdfc Mid Cap Fund - Growth Option | C70: =INDEX(tICICIAshu[Date],69) -> 43049 | D70: =INDEX(tICICIAshu[Signed Amount],69) -> 5000
A71: ICICI Direct - Ashutosh | B71: =INDEX(tICICIAshu[Display Scheme],70) -> Hdfc Mid Cap Fund - Growth Option | C71: =INDEX(tICICIAshu[Date],70) -> 43018 | D71: =INDEX(tICICIAshu[Signed Amount],70) -> 5000
A72: ICICI Direct - Ashutosh | B72: =INDEX(tICICIAshu[Display Scheme],71) -> Hdfc Mid Cap Fund - Growth Option | C72: =INDEX(tICICIAshu[Date],71) -> 42988 | D72: =INDEX(tICICIAshu[Signed Amount],71) -> 5000
A73: ICICI Direct - Ashutosh | B73: =INDEX(tICICIAshu[Display Scheme],72) -> Sbi Flexicap Fund - Growth | C73: =INDEX(tICICIAshu[Date],72) -> 42967 | D73: =INDEX(tICICIAshu[Signed Amount],72) -> 5000
A74: ICICI Direct - Ashutosh | B74: =INDEX(tICICIAshu[Display Scheme],73) -> Hdfc Mid Cap Fund - Growth Option | C74: =INDEX(tICICIAshu[Date],73) -> 42957 | D74: =INDEX(tICICIAshu[Signed Amount],73) -> 5000
A75: ICICI Direct - Ashutosh | B75: =INDEX(tICICIAshu[Display Scheme],74) -> Sbi Flexicap Fund - Growth | C75: =INDEX(tICICIAshu[Date],74) -> 42936 | D75: =INDEX(tICICIAshu[Signed Amount],74) -> 5000
A76: ICICI Direct - Ashutosh | B76: =INDEX(tICICIAshu[Display Scheme],75) -> Hdfc Mid Cap Fund - Growth Option | C76: =INDEX(tICICIAshu[Date],75) -> 42926 | D76: =INDEX(tICICIAshu[Signed Amount],75) -> 5000
A77: ICICI Direct - Ashutosh | B77: =INDEX(tICICIAshu[Display Scheme],76) -> Sbi Flexicap Fund - Growth | C77: =INDEX(tICICIAshu[Date],76) -> 42906 | D77: =INDEX(tICICIAshu[Signed Amount],76) -> 5000
A78: ICICI Direct - Ashutosh | B78: =INDEX(tICICIAshu[Display Scheme],77) -> Hdfc Mid Cap Fund - Growth Option | C78: =INDEX(tICICIAshu[Date],77) -> 42896 | D78: =INDEX(tICICIAshu[Signed Amount],77) -> 5000
A79: ICICI Direct - Ashutosh | B79: =INDEX(tICICIAshu[Display Scheme],78) -> Sbi Flexicap Fund - Growth | C79: =INDEX(tICICIAshu[Date],78) -> 42875 | D79: =INDEX(tICICIAshu[Signed Amount],78) -> 5000
A80: ICICI Direct - Ashutosh | B80: =INDEX(tICICIAshu[Display Scheme],79) -> Sbi Flexicap Fund - Growth | C80: =INDEX(tICICIAshu[Date],79) -> 42845 | D80: =INDEX(tICICIAshu[Signed Amount],79) -> 5000
A81: ICICI Direct - Ashutosh | B81: =INDEX(tICICIAshu[Display Scheme],80) -> Sbi Flexicap Fund - Growth | C81: =INDEX(tICICIAshu[Date],80) -> 42814 | D81: =INDEX(tICICIAshu[Signed Amount],80) -> 5000
A82: ICICI Direct - Ashutosh | B82: =INDEX(tICICIAshu[Display Scheme],81) -> Sbi Flexicap Fund - Growth | C82: =INDEX(tICICIAshu[Date],81) -> 42786 | D82: =INDEX(tICICIAshu[Signed Amount],81) -> 5000
A83: ICICI Direct - Ashutosh | B83: =INDEX(tICICIAshu[Display Scheme],82) -> Sbi Flexicap Fund - Growth | C83: =INDEX(tICICIAshu[Date],82) -> 42755 | D83: =INDEX(tICICIAshu[Signed Amount],82) -> 5000
A84: ICICI Direct - Ashutosh | B84: =INDEX(tICICIAshu[Display Scheme],83) -> Sbi Flexicap Fund - Growth | C84: =INDEX(tICICIAshu[Date],83) -> 42724 | D84: =INDEX(tICICIAshu[Signed Amount],83) -> 5000
A85: ICICI Direct - Ashutosh | B85: =INDEX(tICICIAshu[Display Scheme],84) -> Sbi Flexicap Fund - Growth | C85: =INDEX(tICICIAshu[Date],84) -> 42694 | D85: =INDEX(tICICIAshu[Signed Amount],84) -> 5000
A86: ICICI Direct - Ashutosh | B86: =INDEX(tICICIAshu[Display Scheme],85) -> Sbi Flexicap Fund - Growth | C86: =INDEX(tICICIAshu[Date],85) -> 42663 | D86: =INDEX(tICICIAshu[Signed Amount],85) -> 5000
A87: ICICI Direct - Ashutosh | B87: =INDEX(tICICIAshu[Display Scheme],86) -> Sbi Flexicap Fund - Growth | C87: =INDEX(tICICIAshu[Date],86) -> 42633 | D87: =INDEX(tICICIAshu[Signed Amount],86) -> 5000
A88: ICICI Direct - Ashutosh | B88: =INDEX(tICICIAshu[Display Scheme],87) -> Nippon India Equity Linked Savings Fund Series - I Growth | C88: =INDEX(tICICIAshu[Date],87) -> 42526 | D88: =INDEX(tICICIAshu[Signed Amount],87) -> -11949.15
A89: ICICI Direct - Ashutosh | B89: =INDEX(tICICIAshu[Display Scheme],88) -> Hdfc Mid Cap Fund - Growth Option | C89: =INDEX(tICICIAshu[Date],88) -> 42526 | D89: =INDEX(tICICIAshu[Signed Amount],88) -> 5000
A90: ICICI Direct - Ashutosh | B90: =INDEX(tICICIAshu[Display Scheme],89) -> Hdfc Mid Cap Fund - Growth Option | C90: =INDEX(tICICIAshu[Date],89) -> 42353 | D90: =INDEX(tICICIAshu[Signed Amount],89) -> 5000
A91: ICICI Direct - Ashutosh | B91: =INDEX(tICICIAshu[Display Scheme],90) -> Hdfc Mid Cap Fund - Growth Option | C91: =INDEX(tICICIAshu[Date],90) -> 42323 | D91: =INDEX(tICICIAshu[Signed Amount],90) -> 5000
A92: ICICI Direct - Ashutosh | B92: =INDEX(tICICIAshu[Display Scheme],91) -> Hdfc Mid Cap Fund - Growth Option | C92: =INDEX(tICICIAshu[Date],91) -> 42292 | D92: =INDEX(tICICIAshu[Signed Amount],91) -> 5000
A93: ICICI Direct - Ashutosh | B93: =INDEX(tICICIAshu[Display Scheme],92) -> Hdfc Mid Cap Fund - Growth Option | C93: =INDEX(tICICIAshu[Date],92) -> 42262 | D93: =INDEX(tICICIAshu[Signed Amount],92) -> 5000
A94: ICICI Direct - Ashutosh | B94: =INDEX(tICICIAshu[Display Scheme],93) -> Hdfc Mid Cap Fund - Growth Option | C94: =INDEX(tICICIAshu[Date],93) -> 42231 | D94: =INDEX(tICICIAshu[Signed Amount],93) -> 5000
A95: ICICI Direct - Ashutosh | B95: =INDEX(tICICIAshu[Display Scheme],94) -> Hdfc Mid Cap Fund - Growth Option | C95: =INDEX(tICICIAshu[Date],94) -> 42200 | D95: =INDEX(tICICIAshu[Signed Amount],94) -> 5000
A96: ICICI Direct - Ashutosh | B96: =INDEX(tICICIAshu[Display Scheme],95) -> Hdfc Mid Cap Fund - Growth Option | C96: =INDEX(tICICIAshu[Date],95) -> 41977 | D96: =INDEX(tICICIAshu[Signed Amount],95) -> 15000
A97: ICICI Direct - Ashutosh | B97: =INDEX(tICICIAshu[Display Scheme],96) -> Nippon India Equity Linked Savings Fund Series - I Growth | C97: =INDEX(tICICIAshu[Date],96) -> 39453 | D97: =INDEX(tICICIAshu[Signed Amount],96) -> 5000
A98: ICICI Direct - Ashutosh | B98: =INDEX(tICICIAshu[Display Scheme],97) -> Sbi Elss Tax Saver Fund - Growth | C98: =INDEX(tICICIAshu[Date],97) -> 39432 | D98: =INDEX(tICICIAshu[Signed Amount],97) -> 5000
A99: ICICI Direct - Ashutosh | B99: =INDEX(tICICIAshu[Display Scheme],98) -> Lnt Flexicap Fund Regular Growth Option | C99: =INDEX(tICICIAshu[Date],98) -> 39425 | D99: =INDEX(tICICIAshu[Signed Amount],98) -> -11280.05
A100: ICICI Direct - Ashutosh | B100: =INDEX(tICICIAshu[Display Scheme],99) -> Nippon India Elss Tax Saver Fund - Growth Plan | C100: =INDEX(tICICIAshu[Date],99) -> 39405 | D100: =INDEX(tICICIAshu[Signed Amount],99) -> 15000
...
